Workbook

Sheet Informe Subasta
A1: INFORME DE SUBASTA Y CÁLCULO DE DEUDA
A2: Azul = dato que introduce usted · Verde = enlace (no editar) · Morado = interruptor · Amarillo = total · Blanco = cálculo
A4: RESUMEN
A5: TOTAL DEUDA ACTUALIZADA | F5: Intereses devengados | K5: TOTAL con cargas | P5: Puja mínima total (LOANCO) | U5: Cash Out total (LOANCO) | Z5: Cobertura puja / deuda
A6: =$K$13 | F6: =$K$11 | K6: =$K$16 | P6: =V60 | U6: =W60 | Z6: =IFERROR(V60/$K$16,0)
A8: LoanID | H8: LegalID | O8: LoanNumber | V8: OriginalLoanNumber
A9: 2 · DATOS ECONÓMICOS DE LA DEUDA | O9: 4 · PARÁMETROS DE SUBASTA
A10: Principal (€) | H10: Total Deuda A.D.E. (€) | K10: =SUM($D$10:$D$13) | O10: Law 1/2025 Regime (Y/N) | R10: Y | V10: ExecutionOrderAmount (€)
A11: Interest (€) | H11: UpdatedInterestAmount (€) | K11: ='Cálculo Intereses'!$D$21 | O11: BudgetAmount (€) | V11: Total presupuesto (techo REOCO) (€) | Y11: =IF($Y$10+$R$11=0,$K$10,$Y$10+$R$11)
A12: PenaltyInterest (€) | H12: Costas (tope 5% si VH) (€) | K12: =IF($D$17=0,$D$14,MIN(($K$10*0.05),IF($D$14>0,$D$14,$K$10*0.05))) | O12: Comentarios
A13: Expenses (€) | H13: TOTAL DEUDA (€) | K13: =$K$10+$K$11+IF($D$17>0,$K$12,$D$14)
A14: JudicialCostsAmount (€) | H14: SecondLienAmount (€)
A15: AccountClosureDate | H15: ThirdLienAmount (€) | O15: DATOS DE DEVENGO (informativo)
A16: CalculationDate | H16: TOTAL DEUDAS (con cargas) (€) | K16: =$K$13+$K$14+$K$15 | O16: Días de devengo | R16: =IF(AND(ISNUMBER($D$16),ISNUMBER($D$15)),$D$16-$D$15,0) | V16: Nº de tramos (interés) | Y16: ='Cálculo Intereses'!$D$23
A17: Nº fincas vivienda habitual | D17: =COUNTIF(B30:B59,"Y") | H17: Cash out (1ª finca) (€) | K17: =W30 | O17: Tipo medio aplicado | R17: ='Cálculo Intereses'!$D$24 | V17: Régimen del tipo | Y17: ='Cálculo Intereses'!$D$18
A19: 3 · PARÁMETROS DE INTERÉS (cálculo automático en «Cálculo Intereses») | O19: 5 · CHECK-LIST PROCESAL
A20: Mode | D20: VARIABLE | H20: ReferenceRate (BdE) | K20: Euríbor a 12 meses | O20: Certificación de cargas | Y20: ✗
A21: Personado / Consumidor (Consumer) | D21: N | H21: DifferentialRate (puntos) | O21: Notificación a deudores | Y21: ✗
A22: InterestApplicableRate | H22: UpdateRateFrequency (meses) | K22: 12 | O22: Demandados titulares registrales | Y22: ✗
A23: PenaltyInterestApplicableRate | H23: LastRateUpdateDate | K23: 43814 | O23: Revisión completa del edicto | Y23: ✗
A24: NegativeRatesToZero | D24: Sí | H24: RateDelay (meses) | K24: 1 | O24: Revisión nulidades / cláusulas abusivas | Y24: ✗
O25: Pagos realizados | Y25: ✗
A27: 6 · DETALLE POR FINCA — responsabilidad hipotecaria, distribución de deuda y pujas
A28: IDENTIFICACIÓN | E28: % del tipo de subasta | I28: RESP. HIPOTECARIA MÁX. (límites registrales) | N28: Peso | O28: DISTRIBUCIÓN DE LA DEUDA | T28: Cargas/Total | V28: ESC. LOANCO | X28: ESC. REOCO | Z28: DATOS REGISTRALES
A29: PropertyID | B29: IsFirstResidence | C29: LoancoReoco | D29: BaseAmount | E29: 70% t.s. | F29: 60% t.s. | G29: 50% t.s. | H29: 40% t.s. | I29: Capital (MSA) | J29: Interest (MSA) | K29: PenaltyInterest (MSA) | L29: OtherExp+JudCosts (MSA) | M29: TOTAL RRHH | N29: % peso | O29: Capital deuda | P29: Ordinarios deuda | Q29: Moratorios + LI | R29: Costas y comis. | S29: TOTAL DEBT | T29: Cargas post. | U29: TOTAL + cargas | V29: Puja Mín. LOANCO | W29: Cash out LOANCO | X29: Puja Mín. REOCO | Y29: Cash out REOCO | Z29: CadastralReference | AA29: Registro Propiedad | AB29: Tomo/Libro/Folio | AC29: Dirección | AD29: Titularidad | AE29: Cargas anteriores
E30: =+$D30*0.7 | F30: =+$D30*0.6 | G30: =+$D30*0.5 | H30: =+$D30*0.4 | M30: =SUM(I30:L30) | N30: =IFERROR(M30/SUM($M$30:$M$59),0) | O30: =MIN(I30,$D$10*N30) | P30: =MIN($D$11*N30,J30) | Q30: =MIN(K30,($D$12+$K$11)*N30) | R30: =MIN(($K$12+$D$13)*N30,L30) | S30: =SUM(O30:R30) | T30: =($K$14+$K$15)*N30 | U30: =S30+T30 | V30: =IF($R$10="Y",IF(A30=0,0,IF(B30="N",MIN(G30,IF(H30<S30,S30,H30)),IF(B30="Y",MIN(E30,IF(F30<S30,S30,F30))))),IF(B30="N",MIN(G30,S30),IF(E30>S30,F30,E30))) | W30: =IF(V30-U30>0,U30-V30,0) | X30: =IF(A30=0,0,IF($R$10="N",IF(W30<0,MIN(G30+1,$Y$11),"No aplica"),"No aplica")) | Y30: =IFERROR(IF(X30-U30>0,U30-X30,0),0)
E31: =+$D31*0.7 | F31: =+$D31*0.6 | G31: =+$D31*0.5 | H31: =+$D31*0.4 | M31: =SUM(I31:L31) | N31: =IFERROR(M31/SUM($M$30:$M$59),0) | O31: =MIN(I31,$D$10*N31) | P31: =MIN($D$11*N31,J31) | Q31: =MIN(K31,($D$12+$K$11)*N31) | R31: =MIN(($K$12+$D$13)*N31,L31) | S31: =SUM(O31:R31) | T31: =($K$14+$K$15)*N31 | U31: =S31+T31 | V31: =IF($R$10="Y",IF(A31=0,0,IF(B31="N",MIN(G31,IF(H31<S31,S31,H31)),IF(B31="Y",MIN(E31,IF(F31<S31,S31,F31))))),IF(B31="N",MIN(G31,S31),IF(E31>S31,F31,E31))) | W31: =IF(V31-U31>0,U31-V31,0) | X31: =IF(A31=0,0,IF($R$10="N",IF(W31<0,MIN(G31+1,$Y$11),"No aplica"),"No aplica")) | Y31: =IFERROR(IF(X31-U31>0,U31-X31,0),0)
E32: =+$D32*0.7 | F32: =+$D32*0.6 | G32: =+$D32*0.5 | H32: =+$D32*0.4 | M32: =SUM(I32:L32) | N32: =IFERROR(M32/SUM($M$30:$M$59),0) | O32: =MIN(I32,$D$10*N32) | P32: =MIN($D$11*N32,J32) | Q32: =MIN(K32,($D$12+$K$11)*N32) | R32: =MIN(($K$12+$D$13)*N32,L32) | S32: =SUM(O32:R32) | T32: =($K$14+$K$15)*N32 | U32: =S32+T32 | V32: =IF($R$10="Y",IF(A32=0,0,IF(B32="N",MIN(G32,IF(H32<S32,S32,H32)),IF(B32="Y",MIN(E32,IF(F32<S32,S32,F32))))),IF(B32="N",MIN(G32,S32),IF(E32>S32,F32,E32))) | W32: =IF(V32-U32>0,U32-V32,0) | X32: =IF(A32=0,0,IF($R$10="N",IF(W32<0,MIN(G32+1,$Y$11),"No aplica"),"No aplica")) | Y32: =IFERROR(IF(X32-U32>0,U32-X32,0),0)
E33: =+$D33*0.7 | F33: =+$D33*0.6 | G33: =+$D33*0.5 | H33: =+$D33*0.4 | M33: =SUM(I33:L33) | N33: =IFERROR(M33/SUM($M$30:$M$59),0) | O33: =MIN(I33,$D$10*N33) | P33: =MIN($D$11*N33,J33) | Q33: =MIN(K33,($D$12+$K$11)*N33) | R33: =MIN(($K$12+$D$13)*N33,L33) | S33: =SUM(O33:R33) | T33: =($K$14+$K$15)*N33 | U33: =S33+T33 | V33: =IF($R$10="Y",IF(A33=0,0,IF(B33="N",MIN(G33,IF(H33<S33,S33,H33)),IF(B33="Y",MIN(E33,IF(F33<S33,S33,F33))))),IF(B33="N",MIN(G33,S33),IF(E33>S33,F33,E33))) | W33: =IF(V33-U33>0,U33-V33,0) | X33: =IF(A33=0,0,IF($R$10="N",IF(W33<0,MIN(G33+1,$Y$11),"No aplica"),"No aplica")) | Y33: =IFERROR(IF(X33-U33>0,U33-X33,0),0)
E34: =+$D34*0.7 | F34: =+$D34*0.6 | G34: =+$D34*0.5 | H34: =+$D34*0.4 | M34: =SUM(I34:L34) | N34: =IFERROR(M34/SUM($M$30:$M$59),0) | O34: =MIN(I34,$D$10*N34) | P34: =MIN($D$11*N34,J34) | Q34: =MIN(K34,($D$12+$K$11)*N34) | R34: =MIN(($K$12+$D$13)*N34,L34) | S34: =SUM(O34:R34) | T34: =($K$14+$K$15)*N34 | U34: =S34+T34 | V34: =IF($R$10="Y",IF(A34=0,0,IF(B34="N",MIN(G34,IF(H34<S34,S34,H34)),IF(B34="Y",MIN(E34,IF(F34<S34,S34,F34))))),IF(B34="N",MIN(G34,S34),IF(E34>S34,F34,E34))) | W34: =IF(V34-U34>0,U34-V34,0) | X34: =IF(A34=0,0,IF($R$10="N",IF(W34<0,MIN(G34+1,$Y$11),"No aplica"),"No aplica")) | Y34: =IFERROR(IF(X34-U34>0,U34-X34,0),0)
E35: =+$D35*0.7 | F35: =+$D35*0.6 | G35: =+$D35*0.5 | H35: =+$D35*0.4 | M35: =SUM(I35:L35) | N35: =IFERROR(M35/SUM($M$30:$M$59),0) | O35: =MIN(I35,$D$10*N35) | P35: =MIN($D$11*N35,J35) | Q35: =MIN(K35,($D$12+$K$11)*N35) | R35: =MIN(($K$12+$D$13)*N35,L35) | S35: =SUM(O35:R35) | T35: =($K$14+$K$15)*N35 | U35: =S35+T35 | V35: =IF($R$10="Y",IF(A35=0,0,IF(B35="N",MIN(G35,IF(H35<S35,S35,H35)),IF(B35="Y",MIN(E35,IF(F35<S35,S35,F35))))),IF(B35="N",MIN(G35,S35),IF(E35>S35,F35,E35))) | W35: =IF(V35-U35>0,U35-V35,0) | X35: =IF(A35=0,0,IF($R$10="N",IF(W35<0,MIN(G35+1,$Y$11),"No aplica"),"No aplica")) | Y35: =IFERROR(IF(X35-U35>0,U35-X35,0),0)
E36: =+$D36*0.7 | F36: =+$D36*0.6 | G36: =+$D36*0.5 | H36: =+$D36*0.4 | M36: =SUM(I36:L36) | N36: =IFERROR(M36/SUM($M$30:$M$59),0) | O36: =MIN(I36,$D$10*N36) | P36: =MIN($D$11*N36,J36) | Q36: =MIN(K36,($D$12+$K$11)*N36) | R36: =MIN(($K$12+$D$13)*N36,L36) | S36: =SUM(O36:R36) | T36: =($K$14+$K$15)*N36 | U36: =S36+T36 | V36: =IF($R$10="Y",IF(A36=0,0,IF(B36="N",MIN(G36,IF(H36<S36,S36,H36)),IF(B36="Y",MIN(E36,IF(F36<S36,S36,F36))))),IF(B36="N",MIN(G36,S36),IF(E36>S36,F36,E36))) | W36: =IF(V36-U36>0,U36-V36,0) | X36: =IF(A36=0,0,IF($R$10="N",IF(W36<0,MIN(G36+1,$Y$11),"No aplica"),"No aplica")) | Y36: =IFERROR(IF(X36-U36>0,U36-X36,0),0)
E37: =+$D37*0.7 | F37: =+$D37*0.6 | G37: =+$D37*0.5 | H37: =+$D37*0.4 | M37: =SUM(I37:L37) | N37: =IFERROR(M37/SUM($M$30:$M$59),0) | O37: =MIN(I37,$D$10*N37) | P37: =MIN($D$11*N37,J37) | Q37: =MIN(K37,($D$12+$K$11)*N37) | R37: =MIN(($K$12+$D$13)*N37,L37) | S37: =SUM(O37:R37) | T37: =($K$14+$K$15)*N37 | U37: =S37+T37 | V37: =IF($R$10="Y",IF(A37=0,0,IF(B37="N",MIN(G37,IF(H37<S37,S37,H37)),IF(B37="Y",MIN(E37,IF(F37<S37,S37,F37))))),IF(B37="N",MIN(G37,S37),IF(E37>S37,F37,E37))) | W37: =IF(V37-U37>0,U37-V37,0) | X37: =IF(A37=0,0,IF($R$10="N",IF(W37<0,MIN(G37+1,$Y$11),"No aplica"),"No aplica")) | Y37: =IFERROR(IF(X37-U37>0,U37-X37,0),0)
E38: =+$D38*0.7 | F38: =+$D38*0.6 | G38: =+$D38*0.5 | H38: =+$D38*0.4 | M38: =SUM(I38:L38) | N38: =IFERROR(M38/SUM($M$30:$M$59),0) | O38: =MIN(I38,$D$10*N38) | P38: =MIN($D$11*N38,J38) | Q38: =MIN(K38,($D$12+$K$11)*N38) | R38: =MIN(($K$12+$D$13)*N38,L38) | S38: =SUM(O38:R38) | T38: =($K$14+$K$15)*N38 | U38: =S38+T38 | V38: =IF($R$10="Y",IF(A38=0,0,IF(B38="N",MIN(G38,IF(H38<S38,S38,H38)),IF(B38="Y",MIN(E38,IF(F38<S38,S38,F38))))),IF(B38="N",MIN(G38,S38),IF(E38>S38,F38,E38))) | W38: =IF(V38-U38>0,U38-V38,0) | X38: =IF(A38=0,0,IF($R$10="N",IF(W38<0,MIN(G38+1,$Y$11),"No aplica"),"No aplica")) | Y38: =IFERROR(IF(X38-U38>0,U38-X38,0),0)
E39: =+$D39*0.7 | F39: =+$D39*0.6 | G39: =+$D39*0.5 | H39: =+$D39*0.4 | M39: =SUM(I39:L39) | N39: =IFERROR(M39/SUM($M$30:$M$59),0) | O39: =MIN(I39,$D$10*N39) | P39: =MIN($D$11*N39,J39) | Q39: =MIN(K39,($D$12+$K$11)*N39) | R39: =MIN(($K$12+$D$13)*N39,L39) | S39: =SUM(O39:R39) | T39: =($K$14+$K$15)*N39 | U39: =S39+T39 | V39: =IF($R$10="Y",IF(A39=0,0,IF(B39="N",MIN(G39,IF(H39<S39,S39,H39)),IF(B39="Y",MIN(E39,IF(F39<S39,S39,F39))))),IF(B39="N",MIN(G39,S39),IF(E39>S39,F39,E39))) | W39: =IF(V39-U39>0,U39-V39,0) | X39: =IF(A39=0,0,IF($R$10="N",IF(W39<0,MIN(G39+1,$Y$11),"No aplica"),"No aplica")) | Y39: =IFERROR(IF(X39-U39>0,U39-X39,0),0)
E40: =+$D40*0.7 | F40: =+$D40*0.6 | G40: =+$D40*0.5 | H40: =+$D40*0.4 | M40: =SUM(I40:L40) | N40: =IFERROR(M40/SUM($M$30:$M$59),0) | O40: =MIN(I40,$D$10*N40) | P40: =MIN($D$11*N40,J40) | Q40: =MIN(K40,($D$12+$K$11)*N40) | R40: =MIN(($K$12+$D$13)*N40,L40) | S40: =SUM(O40:R40) | T40: =($K$14+$K$15)*N40 | U40: =S40+T40 | V40: =IF($R$10="Y",IF(A40=0,0,IF(B40="N",MIN(G40,IF(H40<S40,S40,H40)),IF(B40="Y",MIN(E40,IF(F40<S40,S40,F40))))),IF(B40="N",MIN(G40,S40),IF(E40>S40,F40,E40))) | W40: =IF(V40-U40>0,U40-V40,0) | X40: =IF(A40=0,0,IF($R$10="N",IF(W40<0,MIN(G40+1,$Y$11),"No aplica"),"No aplica")) | Y40: =IFERROR(IF(X40-U40>0,U40-X40,0),0)
E41: =+$D41*0.7 | F41: =+$D41*0.6 | G41: =+$D41*0.5 | H41: =+$D41*0.4 | M41: =SUM(I41:L41) | N41: =IFERROR(M41/SUM($M$30:$M$59),0) | O41: =MIN(I41,$D$10*N41) | P41: =MIN($D$11*N41,J41) | Q41: =MIN(K41,($D$12+$K$11)*N41) | R41: =MIN(($K$12+$D$13)*N41,L41) | S41: =SUM(O41:R41) | T41: =($K$14+$K$15)*N41 | U41: =S41+T41 | V41: =IF($R$10="Y",IF(A41=0,0,IF(B41="N",MIN(G41,IF(H41<S41,S41,H41)),IF(B41="Y",MIN(E41,IF(F41<S41,S41,F41))))),IF(B41="N",MIN(G41,S41),IF(E41>S41,F41,E41))) | W41: =IF(V41-U41>0,U41-V41,0) | X41: =IF(A41=0,0,IF($R$10="N",IF(W41<0,MIN(G41+1,$Y$11),"No aplica"),"No aplica")) | Y41: =IFERROR(IF(X41-U41>0,U41-X41,0),0)
... E59: =+$D59*0.7 | F59: =+$D59*0.6 | G59: =+$D59*0.5 | H59: =+$D59*0.4 | M59: =SUM(I59:L59) | N59: =IFERROR(M59/SUM($M$30:$M$59),0) | O59: =MIN(I59,$D$10*N59) | P59: =MIN($D$11*N59,J59) | Q59: =MIN(K59,($D$12+$K$11)*N59) | R59: =MIN(($K$12+$D$13)*N59,L59) | S59: =SUM(O59:R59) | T59: =($K$14+$K$15)*N59 | U59: =S59+T59 | V59: =IF($R$10="Y",IF(A59=0,0,IF(B59="N",MIN(G59,IF(H59<S59,S59,H59)),IF(B59="Y",MIN(E59,IF(F59<S59,S59,F59))))),IF(B59="N",MIN(G59,S59),IF(E59>S59,F59,E59))) | W59: =IF(V59-U59>0,U59-V59,0) | X59: =IF(A59=0,0,IF($R$10="N",IF(W59<0,MIN(G59+1,$Y$11),"No aplica"),"No aplica")) | Y59: =IFERROR(IF(X59-U59>0,U59-X59,0),0)
A60: TOTALES | D60: =SUBTOTAL(9,D30:D59) | E60: =SUBTOTAL(9,E30:E59) | F60: =SUBTOTAL(9,F30:F59) | G60: =SUBTOTAL(9,G30:G59) | I60: =SUBTOTAL(9,I30:I59) | J60: =SUBTOTAL(9,J30:J59) | K60: =SUBTOTAL(9,K30:K59) | L60: =SUBTOTAL(9,L30:L59) | M60: =SUBTOTAL(9,M30:M59) | O60: =SUBTOTAL(9,O30:O59) | P60: =SUBTOTAL(9,P30:P59) | Q60: =SUBTOTAL(9,Q30:Q59) | R60: =SUBTOTAL(9,R30:R59) | S60: =SUBTOTAL(9,S30:S59) | T60: =SUBTOTAL(9,T30:T59) | U60: =SUBTOTAL(9,U30:U59) | V60: =SUBTOTAL(9,V30:V59) | ... Y60: =SUBTOTAL(9,Y30:Y59)

Sheet Comparativa Tipos
B1: COMPARATIVA DE TIPOS — misma deuda, 4 escenarios
B2: Datos en «Informe Subasta»; aquí se calculan los 4 escenarios a la vez.
B4: Escenario | C4: Tipo / base | D4: Interés devengado (€) | E4: TOTAL DEUDA (€) | F4: Tipo medio
B5: Fijo — CONSUMIDOR | C5: InterestApplicableRate | D5: =('Informe Subasta'!$D$16-'Informe Subasta'!$D$15)*'Informe Subasta'!$D$22*'Informe Subasta'!$D$10/365 | E5: ='Informe Subasta'!$K$10+D5+IF('Informe Subasta'!$D$17>0,'Informe Subasta'!$K$12,'Informe Subasta'!$D$14) | F5: =IFERROR(D5*36500/('Informe Subasta'!$D$10*('Informe Subasta'!$D$16-'Informe Subasta'!$D$15)),0)
B6: Fijo — NO consumidor | C6: PenaltyInterestApplicableRate | D6: =('Informe Subasta'!$D$16-'Informe Subasta'!$D$15)*'Informe Subasta'!$D$23*'Informe Subasta'!$D$10/365 | E6: ='Informe Subasta'!$K$10+D6+IF('Informe Subasta'!$D$17>0,'Informe Subasta'!$K$12,'Informe Subasta'!$D$14) | F6: =IFERROR(D6*36500/('Informe Subasta'!$D$10*('Informe Subasta'!$D$16-'Informe Subasta'!$D$15)),0)
B7: Variable | C7: ReferenceRate + DifferentialRate | D7: =SUM('CI Variable'!$O$5:$O$304) | E7: ='Informe Subasta'!$K$10+D7+IF('Informe Subasta'!$D$17>0,'Informe Subasta'!$K$12,'Informe Subasta'!$D$14) | F7: =IFERROR(D7*36500/('Informe Subasta'!$D$10*('Informe Subasta'!$D$16-'Informe Subasta'!$D$15)),0)
B8: Variable +3% | C8: Ref + Diff + 3 puntos | D8: =SUM('CI Variable +3%'!$O$5:$O$304) | E8: ='Informe Subasta'!$K$10+D8+IF('Informe Subasta'!$D$17>0,'Informe Subasta'!$K$12,'Informe Subasta'!$D$14) | F8: =IFERROR(D8*36500/('Informe Subasta'!$D$10*('Informe Subasta'!$D$16-'Informe Subasta'!$D$15)),0)

Sheet Cálculo Intereses
A1: CÁLCULO AUTOMÁTICO DE INTERESES (por tramos)
A2: Interés simple, Actual/365 = capital × tipo% × días ÷ 36.500. Datos enlazados desde «Informe Subasta» (no editar aquí).
A4: PARÁMETROS (enlazados) | G4: Nº | H4: Fecha inicio | I4: Fecha fin | J4: Días | K4: Fecha ref. tipo | L4: Tipo base (%) | M4: Diferencial (%) | N4: Tipo aplicado (%) | O4: Intereses (€) | P4: Deuda acumulada (€)
A5: Principal (€) | D5: ='Informe Subasta'!$D$10 | G5: =IF(H5="","",ROW()-4) | H5: =IF($D$8="FIJO","",$D$6) | I5: =IF(H5="","",MIN(IF($D$18="LEGAL",DATE(YEAR(H5)+1,1,1),EDATE($D$12,$D$11*(INT((((YEAR(H5)-YEAR($D$12))*12+(MONTH(H5)-MONTH($D$12))-IF(DAY(H5)<DAY($D$12),1,0))/$D$11))+1))),$D$7)) | J5: =IF(H5="","",I5-H5) | K5: =IF(H5="","",IF($D$18="LEGAL",H5,EDATE($D$12,-$D$13))) | L5: =IF(H5="","",IFERROR(INDEX('Tipos BdE'!$B$7:$M$336,MATCH(DATE(YEAR(K5),MONTH(K5),1),'Tipos BdE'!$A$7:$A$336,1),MATCH($D$9,'Tipos BdE'!$B$6:$M$6,0)),0)) | M5: =IF(H5="","",IF($D$18="LEGAL",0,$D$10)) | N5: =IF(H5="","",IF(AND($D$14="Sí",(L5+M5)<0),0,L5+M5)) | O5: =IF(H5="","",$D$5*N5*J5/36500) | P5: =IF(H5="","",$D$5+SUM($O$5:O5))
A6: AccountClosureDate (cierre) | D6: ='Informe Subasta'!$D$15 | G6: =IF(H6="","",ROW()-4) | H6: =IF(OR(I5="",I5>=$D$7),"",I5) | I6: =IF(H6="","",MIN(IF($D$18="LEGAL",DATE(YEAR(H6)+1,1,1),EDATE($D$12,$D$11*(INT((((YEAR(H6)-YEAR($D$12))*12+(MONTH(H6)-MONTH($D$12))-IF(DAY(H6)<DAY($D$12),1,0))/$D$11))+1))),$D$7)) | J6: =IF(H6="","",I6-H6) | K6: =IF(H6="","",IF($D$18="LEGAL",H6,EDATE(H6,-$D$13))) | L6: =IF(H6="","",IFERROR(INDEX('Tipos BdE'!$B$7:$M$336,MATCH(DATE(YEAR(K6),MONTH(K6),1),'Tipos BdE'!$A$7:$A$336,1),MATCH($D$9,'Tipos BdE'!$B$6:$M$6,0)),0)) | M6: =IF(H6="","",IF($D$18="LEGAL",0,$D$10)) | N6: =IF(H6="","",IF(AND($D$14="Sí",(L6+M6)<0),0,L6+M6)) | O6: =IF(H6="","",$D$5*N6*J6/36500) | P6: =IF(H6="","",$D$5+SUM($O$5:O6))
A7: CalculationDate | D7: ='Informe Subasta'!$D$16 | G7: =IF(H7="","",ROW()-4) | H7: =IF(OR(I6="",I6>=$D$7),"",I6) | I7: =IF(H7="","",MIN(IF($D$18="LEGAL",DATE(YEAR(H7)+1,1,1),EDATE($D$12,$D$11*(INT((((YEAR(H7)-YEAR($D$12))*12+(MONTH(H7)-MONTH($D$12))-IF(DAY(H7)<DAY($D$12),1,0))/$D$11))+1))),$D$7)) | J7: =IF(H7="","",I7-H7) | K7: =IF(H7="","",IF($D$18="LEGAL",H7,EDATE(H7,-$D$13))) | L7: =IF(H7="","",IFERROR(INDEX('Tipos BdE'!$B$7:$M$336,MATCH(DATE(YEAR(K7),MONTH(K7),1),'Tipos BdE'!$A$7:$A$336,1),MATCH($D$9,'Tipos BdE'!$B$6:$M$6,0)),0)) | M7: =IF(H7="","",IF($D$18="LEGAL",0,$D$10)) | N7: =IF(H7="","",IF(AND($D$14="Sí",(L7+M7)<0),0,L7+M7)) | O7: =IF(H7="","",$D$5*N7*J7/36500) | P7: =IF(H7="","",$D$5+SUM($O$5:O7))
A8: Mode | D8: ='Informe Subasta'!$D$20 | G8: =IF(H8="","",ROW()-4) | H8: =IF(OR(I7="",I7>=$D$7),"",I7) | I8: =IF(H8="","",MIN(IF($D$18="LEGAL",DATE(YEAR(H8)+1,1,1),EDATE($D$12,$D$11*(INT((((YEAR(H8)-YEAR($D$12))*12+(MONTH(H8)-MONTH($D$12))-IF(DAY(H8)<DAY($D$12),1,0))/$D$11))+1))),$D$7)) | J8: =IF(H8="","",I8-H8) | K8: =IF(H8="","",IF($D$18="LEGAL",H8,EDATE(H8,-$D$13))) | L8: =IF(H8="","",IFERROR(INDEX('Tipos BdE'!$B$7:$M$336,MATCH(DATE(YEAR(K8),MONTH(K8),1),'Tipos BdE'!$A$7:$A$336,1),MATCH($D$9,'Tipos BdE'!$B$6:$M$6,0)),0)) | M8: =IF(H8="","",IF($D$18="LEGAL",0,$D$10)) | N8: =IF(H8="","",IF(AND($D$14="Sí",(L8+M8)<0),0,L8+M8)) | O8: =IF(H8="","",$D$5*N8*J8/36500) | P8: =IF(H8="","",$D$5+SUM($O$5:O8))
A9: ReferenceRate (BdE) | D9: ='Informe Subasta'!$K$20 | G9: =IF(H9="","",ROW()-4) | H9: =IF(OR(I8="",I8>=$D$7),"",I8) | I9: =IF(H9="","",MIN(IF($D$18="LEGAL",DATE(YEAR(H9)+1,1,1),EDATE($D$12,$D$11*(INT((((YEAR(H9)-YEAR($D$12))*12+(MONTH(H9)-MONTH($D$12))-IF(DAY(H9)<DAY($D$12),1,0))/$D$11))+1))),$D$7)) | J9: =IF(H9="","",I9-H9) | K9: =IF(H9="","",IF($D$18="LEGAL",H9,EDATE(H9,-$D$13))) | L9: =IF(H9="","",IFERROR(INDEX('Tipos BdE'!$B$7:$M$336,MATCH(DATE(YEAR(K9),MONTH(K9),1),'Tipos BdE'!$A$7:$A$336,1),MATCH($D$9,'Tipos BdE'!$B$6:$M$6,0)),0)) | M9: =IF(H9="","",IF($D$18="LEGAL",0,$D$10)) | N9: =IF(H9="","",IF(AND($D$14="Sí",(L9+M9)<0),0,L9+M9)) | O9: =IF(H9="","",$D$5*N9*J9/36500) | P9: =IF(H9="","",$D$5+SUM($O$5:O9))
A10: DifferentialRate (puntos) | D10: ='Informe Subasta'!$K$21 | G10: =IF(H10="","",ROW()-4) | H10: =IF(OR(I9="",I9>=$D$7),"",I9) | I10: =IF(H10="","",MIN(IF($D$18="LEGAL",DATE(YEAR(H10)+1,1,1),EDATE($D$12,$D$11*(INT((((YEAR(H10)-YEAR($D$12))*12+(MONTH(H10)-MONTH($D$12))-IF(DAY(H10)<DAY($D$12),1,0))/$D$11))+1))),$D$7)) | J10: =IF(H10="","",I10-H10) | K10: =IF(H10="","",IF($D$18="LEGAL",H10,EDATE(H10,-$D$13))) | L10: =IF(H10="","",IFERROR(INDEX('Tipos BdE'!$B$7:$M$336,MATCH(DATE(YEAR(K10),MONTH(K10),1),'Tipos BdE'!$A$7:$A$336,1),MATCH($D$9,'Tipos BdE'!$B$6:$M$6,0)),0)) | M10: =IF(H10="","",IF($D$18="LEGAL",0,$D$10)) | N10: =IF(H10="","",IF(AND($D$14="Sí",(L10+M10)<0),0,L10+M10)) | O10: =IF(H10="","",$D$5*N10*J10/36500) | P10: =IF(H10="","",$D$5+SUM($O$5:O10))
A11: UpdateRateFrequency (meses) | D11: ='Informe Subasta'!$K$22 | G11: =IF(H11="","",ROW()-4) | H11: =IF(OR(I10="",I10>=$D$7),"",I10) | I11: =IF(H11="","",MIN(IF($D$18="LEGAL",DATE(YEAR(H11)+1,1,1),EDATE($D$12,$D$11*(INT((((YEAR(H11)-YEAR($D$12))*12+(MONTH(H11)-MONTH($D$12))-IF(DAY(H11)<DAY($D$12),1,0))/$D$11))+1))),$D$7)) | J11: =IF(H11="","",I11-H11) | K11: =IF(H11="","",IF($D$18="LEGAL",H11,EDATE(H11,-$D$13))) | L11: =IF(H11="","",IFERROR(INDEX('Tipos BdE'!$B$7:$M$336,MATCH(DATE(YEAR(K11),MONTH(K11),1),'Tipos BdE'!$A$7:$A$336,1),MATCH($D$9,'Tipos BdE'!$B$6:$M$6,0)),0)) | M11: =IF(H11="","",IF($D$18="LEGAL",0,$D$10)) | N11: =IF(H11="","",IF(AND($D$14="Sí",(L11+M11)<0),0,L11+M11)) | O11: =IF(H11="","",$D$5*N11*J11/36500) | P11: =IF(H11="","",$D$5+SUM($O$5:O11))
A12: LastRateUpdateDate | D12: ='Informe Subasta'!$K$23 | G12: =IF(H12="","",ROW()-4) | H12: =IF(OR(I11="",I11>=$D$7),"",I11) | I12: =IF(H12="","",MIN(IF($D$18="LEGAL",DATE(YEAR(H12)+1,1,1),EDATE($D$12,$D$11*(INT((((YEAR(H12)-YEAR($D$12))*12+(MONTH(H12)-MONTH($D$12))-IF(DAY(H12)<DAY($D$12),1,0))/$D$11))+1))),$D$7)) | J12: =IF(H12="","",I12-H12) | K12: =IF(H12="","",IF($D$18="LEGAL",H12,EDATE(H12,-$D$13))) | L12: =IF(H12="","",IFERROR(INDEX('Tipos BdE'!$B$7:$M$336,MATCH(DATE(YEAR(K12),MONTH(K12),1),'Tipos BdE'!$A$7:$A$336,1),MATCH($D$9,'Tipos BdE'!$B$6:$M$6,0)),0)) | M12: =IF(H12="","",IF($D$18="LEGAL",0,$D$10)) | N12: =IF(H12="","",IF(AND($D$14="Sí",(L12+M12)<0),0,L12+M12)) | O12: =IF(H12="","",$D$5*N12*J12/36500) | P12: =IF(H12="","",$D$5+SUM($O$5:O12))
A13: RateDelay (meses) | D13: ='Informe Subasta'!$K$24 | G13: =IF(H13="","",ROW()-4) | H13: =IF(OR(I12="",I12>=$D$7),"",I12) | I13: =IF(H13="","",MIN(IF($D$18="LEGAL",DATE(YEAR(H13)+1,1,1),EDATE($D$12,$D$11*(INT((((YEAR(H13)-YEAR($D$12))*12+(MONTH(H13)-MONTH($D$12))-IF(DAY(H13)<DAY($D$12),1,0))/$D$11))+1))),$D$7)) | J13: =IF(H13="","",I13-H13) | K13: =IF(H13="","",IF($D$18="LEGAL",H13,EDATE(H13,-$D$13))) | L13: =IF(H13="","",IFERROR(INDEX('Tipos BdE'!$B$7:$M$336,MATCH(DATE(YEAR(K13),MONTH(K13),1),'Tipos BdE'!$A$7:$A$336,1),MATCH($D$9,'Tipos BdE'!$B$6:$M$6,0)),0)) | M13: =IF(H13="","",IF($D$18="LEGAL",0,$D$10)) | N13: =IF(H13="","",IF(AND($D$14="Sí",(L13+M13)<0),0,L13+M13)) | O13: =IF(H13="","",$D$5*N13*J13/36500) | P13: =IF(H13="","",$D$5+SUM($O$5:O13))
A14: NegativeRatesToZero | D14: ='Informe Subasta'!$D$24 | G14: =IF(H14="","",ROW()-4) | H14: =IF(OR(I13="",I13>=$D$7),"",I13) | I14: =IF(H14="","",MIN(IF($D$18="LEGAL",DATE(YEAR(H14)+1,1,1),EDATE($D$12,$D$11*(INT((((YEAR(H14)-YEAR($D$12))*12+(MONTH(H14)-MONTH($D$12))-IF(DAY(H14)<DAY($D$12),1,0))/$D$11))+1))),$D$7)) | J14: =IF(H14="","",I14-H14) | K14: =IF(H14="","",IF($D$18="LEGAL",H14,EDATE(H14,-$D$13))) | L14: =IF(H14="","",IFERROR(INDEX('Tipos BdE'!$B$7:$M$336,MATCH(DATE(YEAR(K14),MONTH(K14),1),'Tipos BdE'!$A$7:$A$336,1),MATCH($D$9,'Tipos BdE'!$B$6:$M$6,0)),0)) | M14: =IF(H14="","",IF($D$18="LEGAL",0,$D$10)) | N14: =IF(H14="","",IF(AND($D$14="Sí",(L14+M14)<0),0,L14+M14)) | O14: =IF(H14="","",$D$5*N14*J14/36500) | P14: =IF(H14="","",$D$5+SUM($O$5:O14))
A15: IsConsumer | D15: ='Informe Subasta'!$D$21 | G15: =IF(H15="","",ROW()-4) | H15: =IF(OR(I14="",I14>=$D$7),"",I14) | I15: =IF(H15="","",MIN(IF($D$18="LEGAL",DATE(YEAR(H15)+1,1,1),EDATE($D$12,$D$11*(INT((((YEAR(H15)-YEAR($D$12))*12+(MONTH(H15)-MONTH($D$12))-IF(DAY(H15)<DAY($D$12),1,0))/$D$11))+1))),$D$7)) | J15: =IF(H15="","",I15-H15) | K15: =IF(H15="","",IF($D$18="LEGAL",H15,EDATE(H15,-$D$13))) | L15: =IF(H15="","",IFERROR(INDEX('Tipos BdE'!$B$7:$M$336,MATCH(DATE(YEAR(K15),MONTH(K15),1),'Tipos BdE'!$A$7:$A$336,1),MATCH($D$9,'Tipos BdE'!$B$6:$M$6,0)),0)) | M15: =IF(H15="","",IF($D$18="LEGAL",0,$D$10)) | N15: =IF(H15="","",IF(AND($D$14="Sí",(L15+M15)<0),0,L15+M15)) | O15: =IF(H15="","",$D$5*N15*J15/36500) | P15: =IF(H15="","",$D$5+SUM($O$5:O15))
A16: InterestApplicableRate | D16: ='Informe Subasta'!$D$22 | G16: =IF(H16="","",ROW()-4) | H16: =IF(OR(I15="",I15>=$D$7),"",I15) | I16: =IF(H16="","",MIN(IF($D$18="LEGAL",DATE(YEAR(H16)+1,1,1),EDATE($D$12,$D$11*(INT((((YEAR(H16)-YEAR($D$12))*12+(MONTH(H16)-MONTH($D$12))-IF(DAY(H16)<DAY($D$12),1,0))/$D$11))+1))),$D$7)) | J16: =IF(H16="","",I16-H16) | K16: =IF(H16="","",IF($D$18="LEGAL",H16,EDATE(H16,-$D$13))) | L16: =IF(H16="","",IFERROR(INDEX('Tipos BdE'!$B$7:$M$336,MATCH(DATE(YEAR(K16),MONTH(K16),1),'Tipos BdE'!$A$7:$A$336,1),MATCH($D$9,'Tipos BdE'!$B$6:$M$6,0)),0)) | M16: =IF(H16="","",IF($D$18="LEGAL",0,$D$10)) | N16: =IF(H16="","",IF(AND($D$14="Sí",(L16+M16)<0),0,L16+M16)) | O16: =IF(H16="","",$D$5*N16*J16/36500) | P16: =IF(H16="","",$D$5+SUM($O$5:O16))
A17: PenaltyInterestApplicableRate | D17: ='Informe Subasta'!$D$23 | G17: =IF(H17="","",ROW()-4) | H17: =IF(OR(I16="",I16>=$D$7),"",I16) | I17: =IF(H17="","",MIN(IF($D$18="LEGAL",DATE(YEAR(H17)+1,1,1),EDATE($D$12,$D$11*(INT((((YEAR(H17)-YEAR($D$12))*12+(MONTH(H17)-MONTH($D$12))-IF(DAY(H17)<DAY($D$12),1,0))/$D$11))+1))),$D$7)) | J17: =IF(H17="","",I17-H17) | K17: =IF(H17="","",IF($D$18="LEGAL",H17,EDATE(H17,-$D$13))) | L17: =IF(H17="","",IFERROR(INDEX('Tipos BdE'!$B$7:$M$336,MATCH(DATE(YEAR(K17),MONTH(K17),1),'Tipos BdE'!$A$7:$A$336,1),MATCH($D$9,'Tipos BdE'!$B$6:$M$6,0)),0)) | M17: =IF(H17="","",IF($D$18="LEGAL",0,$D$10)) | N17: =IF(H17="","",IF(AND($D$14="Sí",(L17+M17)<0),0,L17+M17)) | O17: =IF(H17="","",$D$5*N17*J17/36500) | P17: =IF(H17="","",$D$5+SUM($O$5:O17))
A18: Régimen (automático) | D18: =IF(OR(ISNUMBER(SEARCH("legal",$D$9)),ISNUMBER(SEARCH("demora",$D$9)),ISNUMBER(SEARCH("mora procesal",$D$9)),ISNUMBER(SEARCH("576",$D$9))),"LEGAL","VARIABLE") | G18: =IF(H18="","",ROW()-4) | H18: =IF(OR(I17="",I17>=$D$7),"",I17) | I18: =IF(H18="","",MIN(IF($D$18="LEGAL",DATE(YEAR(H18)+1,1,1),EDATE($D$12,$D$11*(INT((((YEAR(H18)-YEAR($D$12))*12+(MONTH(H18)-MONTH($D$12))-IF(DAY(H18)<DAY($D$12),1,0))/$D$11))+1))),$D$7)) | J18: =IF(H18="","",I18-H18) | K18: =IF(H18="","",IF($D$18="LEGAL",H18,EDATE(H18,-$D$13))) | L18: =IF(H18="","",IFERROR(INDEX('Tipos BdE'!$B$7:$M$336,MATCH(DATE(YEAR(K18),MONTH(K18),1),'Tipos BdE'!$A$7:$A$336,1),MATCH($D$9,'Tipos BdE'!$B$6:$M$6,0)),0)) | M18: =IF(H18="","",IF($D$18="LEGAL",0,$D$10)) | N18: =IF(H18="","",IF(AND($D$14="Sí",(L18+M18)<0),0,L18+M18)) | O18: =IF(H18="","",$D$5*N18*J18/36500) | P18: =IF(H18="","",$D$5+SUM($O$5:O18))
G19: =IF(H19="","",ROW()-4) | H19: =IF(OR(I18="",I18>=$D$7),"",I18) | I19: =IF(H19="","",MIN(IF($D$18="LEGAL",DATE(YEAR(H19)+1,1,1),EDATE($D$12,$D$11*(INT((((YEAR(H19)-YEAR($D$12))*12+(MONTH(H19)-MONTH($D$12))-IF(DAY(H19)<DAY($D$12),1,0))/$D$11))+1))),$D$7)) | J19: =IF(H19="","",I19-H19) | K19: =IF(H19="","",IF($D$18="LEGAL",H19,EDATE(H19,-$D$13))) | L19: =IF(H19="","",IFERROR(INDEX('Tipos BdE'!$B$7:$M$336,MATCH(DATE(YEAR(K19),MONTH(K19),1),'Tipos BdE'!$A$7:$A$336,1),MATCH($D$9,'Tipos BdE'!$B$6:$M$6,0)),0)) | M19: =IF(H19="","",IF($D$18="LEGAL",0,$D$10)) | N19: =IF(H19="","",IF(AND($D$14="Sí",(L19+M19)<0),0,L19+M19)) | O19: =IF(H19="","",$D$5*N19*J19/36500) | P19: =IF(H19="","",$D$5+SUM($O$5:O19))
A20: RESULTADO | G20: =IF(H20="","",ROW()-4) | H20: =IF(OR(I19="",I19>=$D$7),"",I19) | I20: =IF(H20="","",MIN(IF($D$18="LEGAL",DATE(YEAR(H20)+1,1,1),EDATE($D$12,$D$11*(INT((((YEAR(H20)-YEAR($D$12))*12+(MONTH(H20)-MONTH($D$12))-IF(DAY(H20)<DAY($D$12),1,0))/$D$11))+1))),$D$7)) | J20: =IF(H20="","",I20-H20) | K20: =IF(H20="","",IF($D$18="LEGAL",H20,EDATE(H20,-$D$13))) | L20: =IF(H20="","",IFERROR(INDEX('Tipos BdE'!$B$7:$M$336,MATCH(DATE(YEAR(K20),MONTH(K20),1),'Tipos BdE'!$A$7:$A$336,1),MATCH($D$9,'Tipos BdE'!$B$6:$M$6,0)),0)) | M20: =IF(H20="","",IF($D$18="LEGAL",0,$D$10)) | N20: =IF(H20="","",IF(AND($D$14="Sí",(L20+M20)<0),0,L20+M20)) | O20: =IF(H20="","",$D$5*N20*J20/36500) | P20: =IF(H20="","",$D$5+SUM($O$5:O20))
A21: TOTAL INTERÉS ACTUALIZADO (€) | D21: =IF($D$8="FIJO",($D$7-$D$6)*IF($D$15="Y",$D$16,$D$17)*$D$5/365,SUM($O$5:$O$304)) | G21: =IF(H21="","",ROW()-4) | H21: =IF(OR(I20="",I20>=$D$7),"",I20) | I21: =IF(H21="","",MIN(IF($D$18="LEGAL",DATE(YEAR(H21)+1,1,1),EDATE($D$12,$D$11*(INT((((YEAR(H21)-YEAR($D$12))*12+(MONTH(H21)-MONTH($D$12))-IF(DAY(H21)<DAY($D$12),1,0))/$D$11))+1))),$D$7)) | J21: =IF(H21="","",I21-H21) | K21: =IF(H21="","",IF($D$18="LEGAL",H21,EDATE(H21,-$D$13))) | L21: =IF(H21="","",IFERROR(INDEX('Tipos BdE'!$B$7:$M$336,MATCH(DATE(YEAR(K21),MONTH(K21),1),'Tipos BdE'!$A$7:$A$336,1),MATCH($D$9,'Tipos BdE'!$B$6:$M$6,0)),0)) | M21: =IF(H21="","",IF($D$18="LEGAL",0,$D$10)) | N21: =IF(H21="","",IF(AND($D$14="Sí",(L21+M21)<0),0,L21+M21)) | O21: =IF(H21="","",$D$5*N21*J21/36500) | P21: =IF(H21="","",$D$5+SUM($O$5:O21))
G22: =IF(H22="","",ROW()-4) | H22: =IF(OR(I21="",I21>=$D$7),"",I21) | I22: =IF(H22="","",MIN(IF($D$18="LEGAL",DATE(YEAR(H22)+1,1,1),EDATE($D$12,$D$11*(INT((((YEAR(H22)-YEAR($D$12))*12+(MONTH(H22)-MONTH($D$12))-IF(DAY(H22)<DAY($D$12),1,0))/$D$11))+1))),$D$7)) | J22: =IF(H22="","",I22-H22) | K22: =IF(H22="","",IF($D$18="LEGAL",H22,EDATE(H22,-$D$13))) | L22: =IF(H22="","",IFERROR(INDEX('Tipos BdE'!$B$7:$M$336,MATCH(DATE(YEAR(K22),MONTH(K22),1),'Tipos BdE'!$A$7:$A$336,1),MATCH($D$9,'Tipos BdE'!$B$6:$M$6,0)),0)) | M22: =IF(H22="","",IF($D$18="LEGAL",0,$D$10)) | N22: =IF(H22="","",IF(AND($D$14="Sí",(L22+M22)<0),0,L22+M22)) | O22: =IF(H22="","",$D$5*N22*J22/36500) | P22: =IF(H22="","",$D$5+SUM($O$5:O22))
A23: Nº de tramos | D23: =COUNT($J$5:$J$304) | G23: =IF(H23="","",ROW()-4) | H23: =IF(OR(I22="",I22>=$D$7),"",I22) | I23: =IF(H23="","",MIN(IF($D$18="LEGAL",DATE(YEAR(H23)+1,1,1),EDATE($D$12,$D$11*(INT((((YEAR(H23)-YEAR($D$12))*12+(MONTH(H23)-MONTH($D$12))-IF(DAY(H23)<DAY($D$12),1,0))/$D$11))+1))),$D$7)) | J23: =IF(H23="","",I23-H23) | K23: =IF(H23="","",IF($D$18="LEGAL",H23,EDATE(H23,-$D$13))) | L23: =IF(H23="","",IFERROR(INDEX('Tipos BdE'!$B$7:$M$336,MATCH(DATE(YEAR(K23),MONTH(K23),1),'Tipos BdE'!$A$7:$A$336,1),MATCH($D$9,'Tipos BdE'!$B$6:$M$6,0)),0)) | M23: =IF(H23="","",IF($D$18="LEGAL",0,$D$10)) | N23: =IF(H23="","",IF(AND($D$14="Sí",(L23+M23)<0),0,L23+M23)) | O23: =IF(H23="","",$D$5*N23*J23/36500) | P23: =IF(H23="","",$D$5+SUM($O$5:O23))
A24: Tipo medio aplicado (ponderado) | D24: =IFERROR($D$21*36500/($D$5*IF($D$8="FIJO",$D$7-$D$6,SUM($J$5:$J$304))),0) | G24: =IF(H24="","",ROW()-4) | H24: =IF(OR(I23="",I23>=$D$7),"",I23) | I24: =IF(H24="","",MIN(IF($D$18="LEGAL",DATE(YEAR(H24)+1,1,1),EDATE($D$12,$D$11*(INT((((YEAR(H24)-YEAR($D$12))*12+(MONTH(H24)-MONTH($D$12))-IF(DAY(H24)<DAY($D$12),1,0))/$D$11))+1))),$D$7)) | J24: =IF(H24="","",I24-H24) | K24: =IF(H24="","",IF($D$18="LEGAL",H24,EDATE(H24,-$D$13))) | L24: =IF(H24="","",IFERROR(INDEX('Tipos BdE'!$B$7:$M$336,MATCH(DATE(YEAR(K24),MONTH(K24),1),'Tipos BdE'!$A$7:$A$336,1),MATCH($D$9,'Tipos BdE'!$B$6:$M$6,0)),0)) | M24: =IF(H24="","",IF($D$18="LEGAL",0,$D$10)) | N24: =IF(H24="","",IF(AND($D$14="Sí",(L24+M24)<0),0,L24+M24)) | O24: =IF(H24="","",$D$5*N24*J24/36500) | P24: =IF(H24="","",$D$5+SUM($O$5:O24))
G25: =IF(H25="","",ROW()-4) | H25: =IF(OR(I24="",I24>=$D$7),"",I24) | I25: =IF(H25="","",MIN(IF($D$18="LEGAL",DATE(YEAR(H25)+1,1,1),EDATE($D$12,$D$11*(INT((((YEAR(H25)-YEAR($D$12))*12+(MONTH(H25)-MONTH($D$12))-IF(DAY(H25)<DAY($D$12),1,0))/$D$11))+1))),$D$7)) | J25: =IF(H25="","",I25-H25) | K25: =IF(H25="","",IF($D$18="LEGAL",H25,EDATE(H25,-$D$13))) | L25: =IF(H25="","",IFERROR(INDEX('Tipos BdE'!$B$7:$M$336,MATCH(DATE(YEAR(K25),MONTH(K25),1),'Tipos BdE'!$A$7:$A$336,1),MATCH($D$9,'Tipos BdE'!$B$6:$M$6,0)),0)) | M25: =IF(H25="","",IF($D$18="LEGAL",0,$D$10)) | N25: =IF(H25="","",IF(AND($D$14="Sí",(L25+M25)<0),0,L25+M25)) | O25: =IF(H25="","",$D$5*N25*J25/36500) | P25: =IF(H25="","",$D$5+SUM($O$5:O25))
G26: =IF(H26="","",ROW()-4) | H26: =IF(OR(I25="",I25>=$D$7),"",I25) | I26: =IF(H26="","",MIN(IF($D$18="LEGAL",DATE(YEAR(H26)+1,1,1),EDATE($D$12,$D$11*(INT((((YEAR(H26)-YEAR($D$12))*12+(MONTH(H26)-MONTH($D$12))-IF(DAY(H26)<DAY($D$12),1,0))/$D$11))+1))),$D$7)) | J26: =IF(H26="","",I26-H26) | K26: =IF(H26="","",IF($D$18="LEGAL",H26,EDATE(H26,-$D$13))) | L26: =IF(H26="","",IFERROR(INDEX('Tipos BdE'!$B$7:$M$336,MATCH(DATE(YEAR(K26),MONTH(K26),1),'Tipos BdE'!$A$7:$A$336,1),MATCH($D$9,'Tipos BdE'!$B$6:$M$6,0)),0)) | M26: =IF(H26="","",IF($D$18="LEGAL",0,$D$10)) | N26: =IF(H26="","",IF(AND($D$14="Sí",(L26+M26)<0),0,L26+M26)) | O26: =IF(H26="","",$D$5*N26*J26/36500) | P26: =IF(H26="","",$D$5+SUM($O$5:O26))
G27: =IF(H27="","",ROW()-4) | H27: =IF(OR(I26="",I26>=$D$7),"",I26) | I27: =IF(H27="","",MIN(IF($D$18="LEGAL",DATE(YEAR(H27)+1,1,1),EDATE($D$12,$D$11*(INT((((YEAR(H27)-YEAR($D$12))*12+(MONTH(H27)-MONTH($D$12))-IF(DAY(H27)<DAY($D$12),1,0))/$D$11))+1))),$D$7)) | J27: =IF(H27="","",I27-H27) | K27: =IF(H27="","",IF($D$18="LEGAL",H27,EDATE(H27,-$D$13))) | L27: =IF(H27="","",IFERROR(INDEX('Tipos BdE'!$B$7:$M$336,MATCH(DATE(YEAR(K27),MONTH(K27),1),'Tipos BdE'!$A$7:$A$336,1),MATCH($D$9,'Tipos BdE'!$B$6:$M$6,0)),0)) | M27: =IF(H27="","",IF($D$18="LEGAL",0,$D$10)) | N27: =IF(H27="","",IF(AND($D$14="Sí",(L27+M27)<0),0,L27+M27)) | O27: =IF(H27="","",$D$5*N27*J27/36500) | P27: =IF(H27="","",$D$5+SUM($O$5:O27))
G28: =IF(H28="","",ROW()-4) | H28: =IF(OR(I27="",I27>=$D$7),"",I27) | I28: =IF(H28="","",MIN(IF($D$18="LEGAL",DATE(YEAR(H28)+1,1,1),EDATE($D$12,$D$11*(INT((((YEAR(H28)-YEAR($D$12))*12+(MONTH(H28)-MONTH($D$12))-IF(DAY(H28)<DAY($D$12),1,0))/$D$11))+1))),$D$7)) | J28: =IF(H28="","",I28-H28) | K28: =IF(H28="","",IF($D$18="LEGAL",H28,EDATE(H28,-$D$13))) | L28: =IF(H28="","",IFERROR(INDEX('Tipos BdE'!$B$7:$M$336,MATCH(DATE(YEAR(K28),MONTH(K28),1),'Tipos BdE'!$A$7:$A$336,1),MATCH($D$9,'Tipos BdE'!$B$6:$M$6,0)),0)) | M28: =IF(H28="","",IF($D$18="LEGAL",0,$D$10)) | N28: =IF(H28="","",IF(AND($D$14="Sí",(L28+M28)<0),0,L28+M28)) | O28: =IF(H28="","",$D$5*N28*J28/36500) | P28: =IF(H28="","",$D$5+SUM($O$5:O28))
G29: =IF(H29="","",ROW()-4) | H29: =IF(OR(I28="",I28>=$D$7),"",I28) | I29: =IF(H29="","",MIN(IF($D$18="LEGAL",DATE(YEAR(H29)+1,1,1),EDATE($D$12,$D$11*(INT((((YEAR(H29)-YEAR($D$12))*12+(MONTH(H29)-MONTH($D$12))-IF(DAY(H29)<DAY($D$12),1,0))/$D$11))+1))),$D$7)) | J29: =IF(H29="","",I29-H29) | K29: =IF(H29="","",IF($D$18="LEGAL",H29,EDATE(H29,-$D$13))) | L29: =IF(H29="","",IFERROR(INDEX('Tipos BdE'!$B$7:$M$336,MATCH(DATE(YEAR(K29),MONTH(K29),1),'Tipos BdE'!$A$7:$A$336,1),MATCH($D$9,'Tipos BdE'!$B$6:$M$6,0)),0)) | M29: =IF(H29="","",IF($D$18="LEGAL",0,$D$10)) | N29: =IF(H29="","",IF(AND($D$14="Sí",(L29+M29)<0),0,L29+M29)) | O29: =IF(H29="","",$D$5*N29*J29/36500) | P29: =IF(H29="","",$D$5+SUM($O$5:O29))
G30: =IF(H30="","",ROW()-4) | H30: =IF(OR(I29="",I29>=$D$7),"",I29) | I30: =IF(H30="","",MIN(IF($D$18="LEGAL",DATE(YEAR(H30)+1,1,1),EDATE($D$12,$D$11*(INT((((YEAR(H30)-YEAR($D$12))*12+(MONTH(H30)-MONTH($D$12))-IF(DAY(H30)<DAY($D$12),1,0))/$D$11))+1))),$D$7)) | J30: =IF(H30="","",I30-H30) | K30: =IF(H30="","",IF($D$18="LEGAL",H30,EDATE(H30,-$D$13))) | L30: =IF(H30="","",IFERROR(INDEX('Tipos BdE'!$B$7:$M$336,MATCH(DATE(YEAR(K30),MONTH(K30),1),'Tipos BdE'!$A$7:$A$336,1),MATCH($D$9,'Tipos BdE'!$B$6:$M$6,0)),0)) | M30: =IF(H30="","",IF($D$18="LEGAL",0,$D$10)) | N30: =IF(H30="","",IF(AND($D$14="Sí",(L30+M30)<0),0,L30+M30)) | O30: =IF(H30="","",$D$5*N30*J30/36500) | P30: =IF(H30="","",$D$5+SUM($O$5:O30))
G31: =IF(H31="","",ROW()-4) | H31: =IF(OR(I30="",I30>=$D$7),"",I30) | I31: =IF(H31="","",MIN(IF($D$18="LEGAL",DATE(YEAR(H31)+1,1,1),EDATE($D$12,$D$11*(INT((((YEAR(H31)-YEAR($D$12))*12+(MONTH(H31)-MONTH($D$12))-IF(DAY(H31)<DAY($D$12),1,0))/$D$11))+1))),$D$7)) | J31: =IF(H31="","",I31-H31) | K31: =IF(H31="","",IF($D$18="LEGAL",H31,EDATE(H31,-$D$13))) | L31: =IF(H31="","",IFERROR(INDEX('Tipos BdE'!$B$7:$M$336,MATCH(DATE(YEAR(K31),MONTH(K31),1),'Tipos BdE'!$A$7:$A$336,1),MATCH($D$9,'Tipos BdE'!$B$6:$M$6,0)),0)) | M31: =IF(H31="","",IF($D$18="LEGAL",0,$D$10)) | N31: =IF(H31="","",IF(AND($D$14="Sí",(L31+M31)<0),0,L31+M31)) | O31: =IF(H31="","",$D$5*N31*J31/36500) | P31: =IF(H31="","",$D$5+SUM($O$5:O31))
G32: =IF(H32="","",ROW()-4) | H32: =IF(OR(I31="",I31>=$D$7),"",I31) | I32: =IF(H32="","",MIN(IF($D$18="LEGAL",DATE(YEAR(H32)+1,1,1),EDATE($D$12,$D$11*(INT((((YEAR(H32)-YEAR($D$12))*12+(MONTH(H32)-MONTH($D$12))-IF(DAY(H32)<DAY($D$12),1,0))/$D$11))+1))),$D$7)) | J32: =IF(H32="","",I32-H32) | K32: =IF(H32="","",IF($D$18="LEGAL",H32,EDATE(H32,-$D$13))) | L32: =IF(H32="","",IFERROR(INDEX('Tipos BdE'!$B$7:$M$336,MATCH(DATE(YEAR(K32),MONTH(K32),1),'Tipos BdE'!$A$7:$A$336,1),MATCH($D$9,'Tipos BdE'!$B$6:$M$6,0)),0)) | M32: =IF(H32="","",IF($D$18="LEGAL",0,$D$10)) | N32: =IF(H32="","",IF(AND($D$14="Sí",(L32+M32)<0),0,L32+M32)) | O32: =IF(H32="","",$D$5*N32*J32/36500) | P32: =IF(H32="","",$D$5+SUM($O$5:O32))
G33: =IF(H33="","",ROW()-4) | H33: =IF(OR(I32="",I32>=$D$7),"",I32) | I33: =IF(H33="","",MIN(IF($D$18="LEGAL",DATE(YEAR(H33)+1,1,1),EDATE($D$12,$D$11*(INT((((YEAR(H33)-YEAR($D$12))*12+(MONTH(H33)-MONTH($D$12))-IF(DAY(H33)<DAY($D$12),1,0))/$D$11))+1))),$D$7)) | J33: =IF(H33="","",I33-H33) | K33: =IF(H33="","",IF($D$18="LEGAL",H33,EDATE(H33,-$D$13))) | L33: =IF(H33="","",IFERROR(INDEX('Tipos BdE'!$B$7:$M$336,MATCH(DATE(YEAR(K33),MONTH(K33),1),'Tipos BdE'!$A$7:$A$336,1),MATCH($D$9,'Tipos BdE'!$B$6:$M$6,0)),0)) | M33: =IF(H33="","",IF($D$18="LEGAL",0,$D$10)) | N33: =IF(H33="","",IF(AND($D$14="Sí",(L33+M33)<0),0,L33+M33)) | O33: =IF(H33="","",$D$5*N33*J33/36500) | P33: =IF(H33="","",$D$5+SUM($O$5:O33))
G34: =IF(H34="","",ROW()-4) | H34: =IF(OR(I33="",I33>=$D$7),"",I33) | I34: =IF(H34="","",MIN(IF($D$18="LEGAL",DATE(YEAR(H34)+1,1,1),EDATE($D$12,$D$11*(INT((((YEAR(H34)-YEAR($D$12))*12+(MONTH(H34)-MONTH($D$12))-IF(DAY(H34)<DAY($D$12),1,0))/$D$11))+1))),$D$7)) | J34: =IF(H34="","",I34-H34) | K34: =IF(H34="","",IF($D$18="LEGAL",H34,EDATE(H34,-$D$13))) | L34: =IF(H34="","",IFERROR(INDEX('Tipos BdE'!$B$7:$M$336,MATCH(DATE(YEAR(K34),MONTH(K34),1),'Tipos BdE'!$A$7:$A$336,1),MATCH($D$9,'Tipos BdE'!$B$6:$M$6,0)),0)) | M34: =IF(H34="","",IF($D$18="LEGAL",0,$D$10)) | N34: =IF(H34="","",IF(AND($D$14="Sí",(L34+M34)<0),0,L34+M34)) | O34: =IF(H34="","",$D$5*N34*J34/36500) | P34: =IF(H34="","",$D$5+SUM($O$5:O34))
G35: =IF(H35="","",ROW()-4) | H35: =IF(OR(I34="",I34>=$D$7),"",I34) | I35: =IF(H35="","",MIN(IF($D$18="LEGAL",DATE(YEAR(H35)+1,1,1),EDATE($D$12,$D$11*(INT((((YEAR(H35)-YEAR($D$12))*12+(MONTH(H35)-MONTH($D$12))-IF(DAY(H35)<DAY($D$12),1,0))/$D$11))+1))),$D$7)) | J35: =IF(H35="","",I35-H35) | K35: =IF(H35="","",IF($D$18="LEGAL",H35,EDATE(H35,-$D$13))) | L35: =IF(H35="","",IFERROR(INDEX('Tipos BdE'!$B$7:$M$336,MATCH(DATE(YEAR(K35),MONTH(K35),1),'Tipos BdE'!$A$7:$A$336,1),MATCH($D$9,'Tipos BdE'!$B$6:$M$6,0)),0)) | M35: =IF(H35="","",IF($D$18="LEGAL",0,$D$10)) | N35: =IF(H35="","",IF(AND($D$14="Sí",(L35+M35)<0),0,L35+M35)) | O35: =IF(H35="","",$D$5*N35*J35/36500) | P35: =IF(H35="","",$D$5+SUM($O$5:O35))
G36: =IF(H36="","",ROW()-4) | H36: =IF(OR(I35="",I35>=$D$7),"",I35) | I36: =IF(H36="","",MIN(IF($D$18="LEGAL",DATE(YEAR(H36)+1,1,1),EDATE($D$12,$D$11*(INT((((YEAR(H36)-YEAR($D$12))*12+(MONTH(H36)-MONTH($D$12))-IF(DAY(H36)<DAY($D$12),1,0))/$D$11))+1))),$D$7)) | J36: =IF(H36="","",I36-H36) | K36: =IF(H36="","",IF($D$18="LEGAL",H36,EDATE(H36,-$D$13))) | L36: =IF(H36="","",IFERROR(INDEX('Tipos BdE'!$B$7:$M$336,MATCH(DATE(YEAR(K36),MONTH(K36),1),'Tipos BdE'!$A$7:$A$336,1),MATCH($D$9,'Tipos BdE'!$B$6:$M$6,0)),0)) | M36: =IF(H36="","",IF($D$18="LEGAL",0,$D$10)) | N36: =IF(H36="","",IF(AND($D$14="Sí",(L36+M36)<0),0,L36+M36)) | O36: =IF(H36="","",$D$5*N36*J36/36500) | P36: =IF(H36="","",$D$5+SUM($O$5:O36))
... G304: =IF(H304="","",ROW()-4) | H304: =IF(OR(I303="",I303>=$D$7),"",I303) | I304: =IF(H304="","",MIN(IF($D$18="LEGAL",DATE(YEAR(H304)+1,1,1),EDATE($D$12,$D$11*(INT((((YEAR(H304)-YEAR($D$12))*12+(MONTH(H304)-MONTH($D$12))-IF(DAY(H304)<DAY($D$12),1,0))/$D$11))+1))),$D$7)) | J304: =IF(H304="","",I304-H304) | K304: =IF(H304="","",IF($D$18="LEGAL",H304,EDATE(H304,-$D$13))) | L304: =IF(H304="","",IFERROR(INDEX('Tipos BdE'!$B$7:$M$336,MATCH(DATE(YEAR(K304),MONTH(K304),1),'Tipos BdE'!$A$7:$A$336,1),MATCH($D$9,'Tipos BdE'!$B$6:$M$6,0)),0)) | M304: =IF(H304="","",IF($D$18="LEGAL",0,$D$10)) | N304: =IF(H304="","",IF(AND($D$14="Sí",(L304+M304)<0),0,L304+M304)) | O304: =IF(H304="","",$D$5*N304*J304/36500) | P304: =IF(H304="","",$D$5+SUM($O$5:O304))

Sheet Tipos BdE
A1: TIPOS DE INTERÉS DE REFERENCIA — BANCO DE ESPAÑA (be1901)
A2: Último mes con dato: | B2: 2026-06
A3: Fuente: | B3: https://www.bde.es/webbe/es/estadisticas/compartido/datos/xlsx/be1901.xlsx
A4: Actualización: | B4: Actualizado el 20/07/2026 desde bde.es (be1901).
A6: Fecha | B6: Euríbor a 12 meses | C6: Euríbor a 6 meses | D6: Euríbor a 3 meses | E6: Euríbor a 1 mes | F6: Euríbor a 1 semana | G6: IRPH Conjunto de entidades (vivienda libre) | H6: MIBOR a 1 año | I6: €STR (ESTR) | J6: Interés legal del dinero | K6: Interés de mora procesal (art. 576 LEC) | L6: Interés de demora tributario | M6: Interés de demora en operaciones comerciales
A7: 36161 | B7: 3.062 | G7: 5.131 | H7: 3.065 | J7: 4.25 | K7: 6.25 | L7: 5.5
A8: 36192 | B8: 3.03 | G8: 4.95 | H8: 3.035 | J8: 4.25 | K8: 6.25 | L8: 5.5
A9: 36220 | B9: 3.046 | G9: 4.816 | H9: 3.031 | J9: 4.25 | K9: 6.25 | L9: 5.5
A10: 36251 | B10: 2.756 | G10: 4.787 | H10: 2.709 | J10: 4.25 | K10: 6.25 | L10: 5.5
A11: 36281 | B11: 2.683 | G11: 4.644 | H11: 2.656 | J11: 4.25 | K11: 6.25 | L11: 5.5
A12: 36312 | B12: 2.836 | G12: 4.502 | H12: 2.78 | J12: 4.25 | K12: 6.25 | L12: 5.5
A13: 36342 | B13: 3.03 | G13: 4.435 | H13: 3.018 | J13: 4.25 | K13: 6.25 | L13: 5.5
A14: 36373 | B14: 3.237 | G14: 4.471 | H14: 3.233 | J14: 4.25 | K14: 6.25 | L14: 5.5
A15: 36404 | B15: 3.301 | G15: 4.545 | H15: 3.26 | J15: 4.25 | K15: 6.25 | L15: 5.5
A16: 36434 | B16: 3.684 | G16: 4.665 | H16: 3.607 | J16: 4.25 | K16: 6.25 | L16: 5.5
A17: 36465 | B17: 3.689 | G17: 4.807 | H17: 3.659 | J17: 4.25 | K17: 6.25 | L17: 5.5
A18: 36495 | B18: 3.826 | G18: 4.94 | H18: 3.806 | J18: 4.25 | K18: 6.25 | L18: 5.5
... A48: 37408 | B48: 3.869 | G48: 4.995 | H48: 3.862 | J48: 4.25 | K48: 6.25 | L48: 5.5
A49: 37438 | B49: 3.645 | G49: 5.009 | H49: 3.643 | J49: 4.25 | K49: 6.25 | L49: 5.5 | M49: 10.35
A50: 37469 | B50: 3.44 | G50: 4.999 | H50: 3.437 | J50: 4.25 | K50: 6.25 | L50: 5.5 | M50: 10.35
A51: 37500 | B51: 3.236 | G51: 4.818 | H51: 3.241 | J51: 4.25 | K51: 6.25 | L51: 5.5 | M51: 10.35
A52: 37530 | B52: 3.126 | G52: 4.69 | H52: 3.127 | J52: 4.25 | K52: 6.25 | L52: 5.5 | M52: 10.35
A53: 37561 | B53: 3.017 | G53: 4.517 | H53: 3.02 | J53: 4.25 | K53: 6.25 | L53: 5.5 | M53: 10.35
A54: 37591 | B54: 2.873 | G54: 4.38 | H54: 2.878 | J54: 4.25 | K54: 6.25 | L54: 5.5 | M54: 10.35
A55: 37622 | B55: 2.705 | G55: 4.252 | H55: 2.703 | J55: 4.25 | K55: 6.25 | L55: 5.5 | M55: 9.85
A56: 37653 | B56: 2.504 | G56: 4.146 | H56: 2.513 | J56: 4.25 | K56: 6.25 | L56: 5.5 | M56: 9.85
A57: 37681 | B57: 2.411 | G57: 3.976 | H57: 2.42 | J57: 4.25 | K57: 6.25 | L57: 5.5 | M57: 9.85
A58: 37712 | B58: 2.447 | G58: 3.886 | H58: 2.458 | J58: 4.25 | K58: 6.25 | L58: 5.5 | M58: 9.85
A59: 37742 | B59: 2.252 | G59: 3.823 | H59: 2.253 | J59: 4.25 | K59: 6.25 | L59: 5.5 | M59: 9.85
A60: 37773 | B60: 2.014 | G60: 3.707 | H60: 2.033 | J60: 4.25 | K60: 6.25 | L60: 5.5 | M60: 9.85
... A267: 44075 | B267: -0.415 | G267: 1.7 | H267: -0.415 | J267: 3 | K267: 5 | L267: 3.75 | M267: 8
A268: 44105 | B268: -0.466 | G268: 1.663 | H268: -0.466 | I268: -0.553 | J268: 3 | K268: 5 | L268: 3.75 | M268: 8
A269: 44136 | B269: -0.481 | G269: 1.661 | H269: -0.481 | I269: -0.556 | J269: 3 | K269: 5 | L269: 3.75 | M269: 8
A270: 44166 | B270: -0.497 | G270: 1.563 | H270: -0.497 | I270: -0.555 | J270: 3 | K270: 5 | L270: 3.75 | M270: 8
A271: 44197 | B271: -0.505 | C271: -0.529 | D271: -0.547 | E271: -0.562 | F271: -0.568 | G271: 1.558 | H271: -0.505 | I271: -0.561 | J271: 3 | K271: 5 | L271: 3.75 | M271: 8
A272: 44228 | B272: -0.501 | C272: -0.521 | D272: -0.541 | E272: -0.553 | F272: -0.566 | G272: 1.565 | H272: -0.501 | I272: -0.564 | J272: 3 | K272: 5 | L272: 3.75 | M272: 8
A273: 44256 | B273: -0.487 | C273: -0.516 | D273: -0.539 | E273: -0.553 | F273: -0.565 | G273: 1.571 | H273: -0.487 | I273: -0.567 | J273: 3 | K273: 5 | L273: 3.75 | M273: 8
A274: 44287 | B274: -0.484 | C274: -0.516 | D274: -0.538 | E274: -0.555 | F274: -0.564 | G274: 1.48 | H274: -0.484 | J274: 3 | K274: 5 | L274: 3.75 | M274: 8
A275: 44317 | B275: -0.481 | C275: -0.513 | D275: -0.54 | E275: -0.558 | F275: -0.565 | G275: 1.507 | H275: -0.481 | I275: -0.565 | J275: 3 | K275: 5 | L275: 3.75 | M275: 8
A276: 44348 | B276: -0.484 | C276: -0.515 | D276: -0.543 | E276: -0.555 | F276: -0.567 | G276: 1.527 | H276: -0.484 | I276: -0.565 | J276: 3 | K276: 5 | L276: 3.75 | M276: 8
A277: 44378 | B277: -0.491 | C277: -0.516 | D277: -0.545 | E277: -0.556 | F277: -0.566 | G277: 1.485 | H277: -0.491 | I277: -0.566 | J277: 3 | K277: 5 | L277: 3.75 | M277: 8
A278: 44409 | B278: -0.498 | C278: -0.527 | D278: -0.548 | E278: -0.56 | F278: -0.571 | G278: 1.529 | H278: -0.498 | I278: -0.568 | J278: 3 | K278: 5 | L278: 3.75 | M278: 8
A279: 44440 | B279: -0.492 | C279: -0.522 | D279: -0.545 | E279: -0.558 | F279: -0.57 | G279: 1.489 | H279: -0.492 | I279: -0.57 | J279: 3 | K279: 5 | L279: 3.75 | M279: 8
A280: 44470 | B280: -0.477 | C280: -0.527 | D280: -0.55 | E280: -0.56 | F280: -0.57 | G280: 1.467 | H280: -0.477 | I280: -0.571 | J280: 3 | K280: 5 | L280: 3.75 | M280: 8
A281: 44501 | B281: -0.487 | C281: -0.534 | D281: -0.567 | E281: -0.565 | F281: -0.573 | G281: 1.412 | H281: -0.487 | I281: -0.573 | J281: 3 | K281: 5 | L281: 3.75 | M281: 8
A282: 44531 | B282: -0.502 | C282: -0.545 | D282: -0.582 | E282: -0.596 | F282: -0.58 | G282: 1.448 | H282: -0.502 | I282: -0.578 | J282: 3 | K282: 5 | L282: 3.75 | M282: 8
A283: 44562 | B283: -0.477 | C283: -0.527 | D283: -0.56 | E283: -0.565 | F283: -0.576 | G283: 1.485 | H283: -0.477 | I283: -0.575 | J283: 3 | K283: 5 | L283: 3.75 | M283: 8
A284: 44593 | B284: -0.335 | C284: -0.476 | D284: -0.532 | E284: -0.553 | F284: -0.571 | G284: 1.481 | H284: -0.335 | I284: -0.575 | J284: 3 | K284: 5 | L284: 3.75 | M284: 8
A285: 44621 | B285: -0.237 | C285: -0.418 | D285: -0.495 | E285: -0.544 | F285: -0.569 | G285: 1.513 | H285: -0.237 | I285: -0.58 | J285: 3 | K285: 5 | L285: 3.75 | M285: 8
A286: 44652 | B286: 0.013 | C286: -0.311 | D286: -0.448 | E286: -0.537 | F286: -0.569 | G286: 1.54 | H286: 0.013 | I286: -0.583 | J286: 3 | K286: 5 | L286: 3.75 | M286: 8
... A336: 46174 | B336: 2.798 | C336: 2.596 | D336: 2.339 | E336: 2.146 | F336: 1.992 | G336: 3.049 | H336: 2.798 | I336: 2.182 | J336: 3.25 | K336: 5.25 | L336: 4.0625 | M336: 10.15

Sheet Formato Cliente HO
B2: FECHA CÁLCULO | C2: ='Informe Subasta'!$D$16 | D2: ** AFS = Acta fijación de saldo | F2: Amarillo = poblado desde «Informe Subasta»
D3: ** ADE = Auto despachando ejecución | F3: Blanco = campo formulado
B5: Intereses demora AFS | C5: ='Informe Subasta'!$D$12 | F5: Principal reclamado | G5: =$C$7+$C$8+$C$5+$C$13
B6: DEUDA LEGAL ACTUALIZADA | D6: LIMITE RESPONSABILIDAD HIPOTECARIA SEGÚN ESCRITURA | F6: DEUDA LIMITADA A RESPONSABILIDAD
B7: Capital en AFS | C7: ='Informe Subasta'!$D$10 | D7: Capital | E7: =$D$51 | F7: Capital | G7: =MIN(C7,E7)
B8: Int. Ordinarios en AFS | C8: ='Informe Subasta'!$D$11 | D8: Int. Ordinarios | E8: =$E$51 | F8: Int. Ordinarios | G8: =MIN(C8,E8)
B9: Int. Moratorios a fecha de cálculo | C9: =$C$5+'Informe Subasta'!$K$11 | D9: Int. Moratorios | E9: =$F$51 | F9: Int. Moratorios | G9: =MIN(C9,E9)
B10: Gastos y costas | C10: =SUM(C11:C13) | D10: Gastos y costas | E10: =$G$51 | F10: Gastos y costas limitadas al 5% V.H. | G10: =MIN(C10,E10)
B11: - Abogado | C11: =+'Informe Subasta'!$K$12 | D11: - Abogado | F11: - Abogado | G11: =MIN(C11,E11)
B12: - Procurador | D12: - Procurador | F12: - Procurador | G12: =MIN(C12,E12)
B13: - Comisiones en AFS | C13: ='Informe Subasta'!$D$13 | D13: - Comisiones en AFS | F13: - Comisiones en AFS | G13: =MIN(C13,E13)
B14: Entregas a cuenta | C14: 0 | D14: Entregas a cuenta | E14: 0 | F14: Entregas a cuenta | G14: =C14
B15: TOTAL | C15: =SUM(C7:C10)-C14 | D15: TOTAL | E15: =SUM(E7:E10)-E14 | F15: TOTAL | G15: =SUM(G7:G10)-G14
B17: Si solo hay una finca no completar nada abajo: ↓
B18: Distribución en caso de varias fincas:
D19: LIMITE RESPONSABILIDAD HIPOTECARIA | J19: TOTAL DEUDA REAL DISTRIBUIDA | P19: TOTAL DEUDA LIMITADA DISTRIBUIDA
B20: ASSET ID HOIST | C20: Nº FINCA REGISTRAL | D20: Capital | E20: I. Ordinarios | F20: I. Moratorios | G20: Gastos y Costas | H20: Total R.H. | I20: % LRH Finca | J20: Capital | K20: Int. Ordinarios | L20: Int. Moratorios | M20: Gastos y Costas | N20: Entregas a cuenta | O20: TOTAL DEUDA | P20: Capital | Q20: Int. Ordinarios | R20: Int. Moratorios | S20: Gastos y Costas | T20: Entregas a cuenta | U20: TOTAL DEUDA
C21: =IF('Informe Subasta'!$A$30="","",'Informe Subasta'!$A$30) | D21: =IF($C21="","",'Informe Subasta'!$I$30) | E21: =IF($C21="","",'Informe Subasta'!$J$30) | F21: =IF($C21="","",'Informe Subasta'!$K$30) | G21: =IF($C21="","",'Informe Subasta'!$L$30) | H21: =IF($C21="","",SUM(D21:G21)) | I21: =IF($C21="","",H21/$H$51) | J21: =IF($C21="","",$C$7*$I21) | K21: =IF($C21="","",$C$8*$I21) | L21: =IF($C21="","",$C$9*$I21) | M21: =IF($C21="","",$C$10*$I21) | N21: =IF($C21="","",$C$14*$I21) | O21: =IF($C21="","",SUM(J21:N21)) | P21: =IF($C21="","",$G$7*$I21) | Q21: =IF($C21="","",$G$8*$I21) | R21: =IF($C21="","",$G$9*$I21) | S21: =IF($C21="","",$G$10*$I21) | T21: =IF($C21="","",$G$14*$I21) | U21: =IF($C21="","",SUM(P21:T21))
C22: =IF('Informe Subasta'!$A$31="","",'Informe Subasta'!$A$31) | D22: =IF($C22="","",'Informe Subasta'!$I$31) | E22: =IF($C22="","",'Informe Subasta'!$J$31) | F22: =IF($C22="","",'Informe Subasta'!$K$31) | G22: =IF($C22="","",'Informe Subasta'!$L$31) | H22: =IF($C22="","",SUM(D22:G22)) | I22: =IF($C22="","",H22/$H$51) | J22: =IF($C22="","",$C$7*$I22) | K22: =IF($C22="","",$C$8*$I22) | L22: =IF($C22="","",$C$9*$I22) | M22: =IF($C22="","",$C$10*$I22) | N22: =IF($C22="","",$C$14*$I22) | O22: =IF($C22="","",SUM(J22:N22)) | P22: =IF($C22="","",$G$7*$I22) | Q22: =IF($C22="","",$G$8*$I22) | R22: =IF($C22="","",$G$9*$I22) | S22: =IF($C22="","",$G$10*$I22) | T22: =IF($C22="","",$G$14*$I22) | U22: =IF($C22="","",SUM(P22:T22))
C23: =IF('Informe Subasta'!$A$32="","",'Informe Subasta'!$A$32) | D23: =IF($C23="","",'Informe Subasta'!$I$32) | E23: =IF($C23="","",'Informe Subasta'!$J$32) | F23: =IF($C23="","",'Informe Subasta'!$K$32) | G23: =IF($C23="","",'Informe Subasta'!$L$32) | H23: =IF($C23="","",SUM(D23:G23)) | I23: =IF($C23="","",H23/$H$51) | J23: =IF($C23="","",$C$7*$I23) | K23: =IF($C23="","",$C$8*$I23) | L23: =IF($C23="","",$C$9*$I23) | M23: =IF($C23="","",$C$10*$I23) | N23: =IF($C23="","",$C$14*$I23) | O23: =IF($C23="","",SUM(J23:N23)) | P23: =IF($C23="","",$G$7*$I23) | Q23: =IF($C23="","",$G$8*$I23) | R23: =IF($C23="","",$G$9*$I23) | S23: =IF($C23="","",$G$10*$I23) | T23: =IF($C23="","",$G$14*$I23) | U23: =IF($C23="","",SUM(P23:T23))
C24: =IF('Informe Subasta'!$A$33="","",'Informe Subasta'!$A$33) | D24: =IF($C24="","",'Informe Subasta'!$I$33) | E24: =IF($C24="","",'Informe Subasta'!$J$33) | F24: =IF($C24="","",'Informe Subasta'!$K$33) | G24: =IF($C24="","",'Informe Subasta'!$L$33) | H24: =IF($C24="","",SUM(D24:G24)) | I24: =IF($C24="","",H24/$H$51) | J24: =IF($C24="","",$C$7*$I24) | K24: =IF($C24="","",$C$8*$I24) | L24: =IF($C24="","",$C$9*$I24) | M24: =IF($C24="","",$C$10*$I24) | N24: =IF($C24="","",$C$14*$I24) | O24: =IF($C24="","",SUM(J24:N24)) | P24: =IF($C24="","",$G$7*$I24) | Q24: =IF($C24="","",$G$8*$I24) | R24: =IF($C24="","",$G$9*$I24) | S24: =IF($C24="","",$G$10*$I24) | T24: =IF($C24="","",$G$14*$I24) | U24: =IF($C24="","",SUM(P24:T24))
C25: =IF('Informe Subasta'!$A$34="","",'Informe Subasta'!$A$34) | D25: =IF($C25="","",'Informe Subasta'!$I$34) | E25: =IF($C25="","",'Informe Subasta'!$J$34) | F25: =IF($C25="","",'Informe Subasta'!$K$34) | G25: =IF($C25="","",'Informe Subasta'!$L$34) | H25: =IF($C25="","",SUM(D25:G25)) | I25: =IF($C25="","",H25/$H$51) | J25: =IF($C25="","",$C$7*$I25) | K25: =IF($C25="","",$C$8*$I25) | L25: =IF($C25="","",$C$9*$I25) | M25: =IF($C25="","",$C$10*$I25) | N25: =IF($C25="","",$C$14*$I25) | O25: =IF($C25="","",SUM(J25:N25)) | P25: =IF($C25="","",$G$7*$I25) | Q25: =IF($C25="","",$G$8*$I25) | R25: =IF($C25="","",$G$9*$I25) | S25: =IF($C25="","",$G$10*$I25) | T25: =IF($C25="","",$G$14*$I25) | U25: =IF($C25="","",SUM(P25:T25))
C26: =IF('Informe Subasta'!$A$35="","",'Informe Subasta'!$A$35) | D26: =IF($C26="","",'Informe Subasta'!$I$35) | E26: =IF($C26="","",'Informe Subasta'!$J$35) | F26: =IF($C26="","",'Informe Subasta'!$K$35) | G26: =IF($C26="","",'Informe Subasta'!$L$35) | H26: =IF($C26="","",SUM(D26:G26)) | I26: =IF($C26="","",H26/$H$51) | J26: =IF($C26="","",$C$7*$I26) | K26: =IF($C26="","",$C$8*$I26) | L26: =IF($C26="","",$C$9*$I26) | M26: =IF($C26="","",$C$10*$I26) | N26: =IF($C26="","",$C$14*$I26) | O26: =IF($C26="","",SUM(J26:N26)) | P26: =IF($C26="","",$G$7*$I26) | Q26: =IF($C26="","",$G$8*$I26) | R26: =IF($C26="","",$G$9*$I26) | S26: =IF($C26="","",$G$10*$I26) | T26: =IF($C26="","",$G$14*$I26) | U26: =IF($C26="","",SUM(P26:T26))
C27: =IF('Informe Subasta'!$A$36="","",'Informe Subasta'!$A$36) | D27: =IF($C27="","",'Informe Subasta'!$I$36) | E27: =IF($C27="","",'Informe Subasta'!$J$36) | F27: =IF($C27="","",'Informe Subasta'!$K$36) | G27: =IF($C27="","",'Informe Subasta'!$L$36) | H27: =IF($C27="","",SUM(D27:G27)) | I27: =IF($C27="","",H27/$H$51) | J27: =IF($C27="","",$C$7*$I27) | K27: =IF($C27="","",$C$8*$I27) | L27: =IF($C27="","",$C$9*$I27) | M27: =IF($C27="","",$C$10*$I27) | N27: =IF($C27="","",$C$14*$I27) | O27: =IF($C27="","",SUM(J27:N27)) | P27: =IF($C27="","",$G$7*$I27) | Q27: =IF($C27="","",$G$8*$I27) | R27: =IF($C27="","",$G$9*$I27) | S27: =IF($C27="","",$G$10*$I27) | T27: =IF($C27="","",$G$14*$I27) | U27: =IF($C27="","",SUM(P27:T27))
C28: =IF('Informe Subasta'!$A$37="","",'Informe Subasta'!$A$37) | D28: =IF($C28="","",'Informe Subasta'!$I$37) | E28: =IF($C28="","",'Informe Subasta'!$J$37) | F28: =IF($C28="","",'Informe Subasta'!$K$37) | G28: =IF($C28="","",'Informe Subasta'!$L$37) | H28: =IF($C28="","",SUM(D28:G28)) | I28: =IF($C28="","",H28/$H$51) | J28: =IF($C28="","",$C$7*$I28) | K28: =IF($C28="","",$C$8*$I28) | L28: =IF($C28="","",$C$9*$I28) | M28: =IF($C28="","",$C$10*$I28) | N28: =IF($C28="","",$C$14*$I28) | O28: =IF($C28="","",SUM(J28:N28)) | P28: =IF($C28="","",$G$7*$I28) | Q28: =IF($C28="","",$G$8*$I28) | R28: =IF($C28="","",$G$9*$I28) | S28: =IF($C28="","",$G$10*$I28) | T28: =IF($C28="","",$G$14*$I28) | U28: =IF($C28="","",SUM(P28:T28))
C29: =IF('Informe Subasta'!$A$38="","",'Informe Subasta'!$A$38) | D29: =IF($C29="","",'Informe Subasta'!$I$38) | E29: =IF($C29="","",'Informe Subasta'!$J$38) | F29: =IF($C29="","",'Informe Subasta'!$K$38) | G29: =IF($C29="","",'Informe Subasta'!$L$38) | H29: =IF($C29="","",SUM(D29:G29)) | I29: =IF($C29="","",H29/$H$51) | J29: =IF($C29="","",$C$7*$I29) | K29: =IF($C29="","",$C$8*$I29) | L29: =IF($C29="","",$C$9*$I29) | M29: =IF($C29="","",$C$10*$I29) | N29: =IF($C29="","",$C$14*$I29) | O29: =IF($C29="","",SUM(J29:N29)) | P29: =IF($C29="","",$G$7*$I29) | Q29: =IF($C29="","",$G$8*$I29) | R29: =IF($C29="","",$G$9*$I29) | S29: =IF($C29="","",$G$10*$I29) | T29: =IF($C29="","",$G$14*$I29) | U29: =IF($C29="","",SUM(P29:T29))
C30: =IF('Informe Subasta'!$A$39="","",'Informe Subasta'!$A$39) | D30: =IF($C30="","",'Informe Subasta'!$I$39) | E30: =IF($C30="","",'Informe Subasta'!$J$39) | F30: =IF($C30="","",'Informe Subasta'!$K$39) | G30: =IF($C30="","",'Informe Subasta'!$L$39) | H30: =IF($C30="","",SUM(D30:G30)) | I30: =IF($C30="","",H30/$H$51) | J30: =IF($C30="","",$C$7*$I30) | K30: =IF($C30="","",$C$8*$I30) | L30: =IF($C30="","",$C$9*$I30) | M30: =IF($C30="","",$C$10*$I30) | N30: =IF($C30="","",$C$14*$I30) | O30: =IF($C30="","",SUM(J30:N30)) | P30: =IF($C30="","",$G$7*$I30) | Q30: =IF($C30="","",$G$8*$I30) | R30: =IF($C30="","",$G$9*$I30) | S30: =IF($C30="","",$G$10*$I30) | T30: =IF($C30="","",$G$14*$I30) | U30: =IF($C30="","",SUM(P30:T30))
C31: =IF('Informe Subasta'!$A$40="","",'Informe Subasta'!$A$40) | D31: =IF($C31="","",'Informe Subasta'!$I$40) | E31: =IF($C31="","",'Informe Subasta'!$J$40) | F31: =IF($C31="","",'Informe Subasta'!$K$40) | G31: =IF($C31="","",'Informe Subasta'!$L$40) | H31: =IF($C31="","",SUM(D31:G31)) | I31: =IF($C31="","",H31/$H$51) | J31: =IF($C31="","",$C$7*$I31) | K31: =IF($C31="","",$C$8*$I31) | L31: =IF($C31="","",$C$9*$I31) | M31: =IF($C31="","",$C$10*$I31) | N31: =IF($C31="","",$C$14*$I31) | O31: =IF($C31="","",SUM(J31:N31)) | P31: =IF($C31="","",$G$7*$I31) | Q31: =IF($C31="","",$G$8*$I31) | R31: =IF($C31="","",$G$9*$I31) | S31: =IF($C31="","",$G$10*$I31) | T31: =IF($C31="","",$G$14*$I31) | U31: =IF($C31="","",SUM(P31:T31))
C32: =IF('Informe Subasta'!$A$41="","",'Informe Subasta'!$A$41) | D32: =IF($C32="","",'Informe Subasta'!$I$41) | E32: =IF($C32="","",'Informe Subasta'!$J$41) | F32: =IF($C32="","",'Informe Subasta'!$K$41) | G32: =IF($C32="","",'Informe Subasta'!$L$41) | H32: =IF($C32="","",SUM(D32:G32)) | I32: =IF($C32="","",H32/$H$51) | J32: =IF($C32="","",$C$7*$I32) | K32: =IF($C32="","",$C$8*$I32) | L32: =IF($C32="","",$C$9*$I32) | M32: =IF($C32="","",$C$10*$I32) | N32: =IF($C32="","",$C$14*$I32) | O32: =IF($C32="","",SUM(J32:N32)) | P32: =IF($C32="","",$G$7*$I32) | Q32: =IF($C32="","",$G$8*$I32) | R32: =IF($C32="","",$G$9*$I32) | S32: =IF($C32="","",$G$10*$I32) | T32: =IF($C32="","",$G$14*$I32) | U32: =IF($C32="","",SUM(P32:T32))
C33: =IF('Informe Subasta'!$A$42="","",'Informe Subasta'!$A$42) | D33: =IF($C33="","",'Informe Subasta'!$I$42) | E33: =IF($C33="","",'Informe Subasta'!$J$42) | F33: =IF($C33="","",'Informe Subasta'!$K$42) | G33: =IF($C33="","",'Informe Subasta'!$L$42) | H33: =IF($C33="","",SUM(D33:G33)) | I33: =IF($C33="","",H33/$H$51) | J33: =IF($C33="","",$C$7*$I33) | K33: =IF($C33="","",$C$8*$I33) | L33: =IF($C33="","",$C$9*$I33) | M33: =IF($C33="","",$C$10*$I33) | N33: =IF($C33="","",$C$14*$I33) | O33: =IF($C33="","",SUM(J33:N33)) | P33: =IF($C33="","",$G$7*$I33) | Q33: =IF($C33="","",$G$8*$I33) | R33: =IF($C33="","",$G$9*$I33) | S33: =IF($C33="","",$G$10*$I33) | T33: =IF($C33="","",$G$14*$I33) | U33: =IF($C33="","",SUM(P33:T33))
C34: =IF('Informe Subasta'!$A$43="","",'Informe Subasta'!$A$43) | D34: =IF($C34="","",'Informe Subasta'!$I$43) | E34: =IF($C34="","",'Informe Subasta'!$J$43) | F34: =IF($C34="","",'Informe Subasta'!$K$43) | G34: =IF($C34="","",'Informe Subasta'!$L$43) | H34: =IF($C34="","",SUM(D34:G34)) | I34: =IF($C34="","",H34/$H$51) | J34: =IF($C34="","",$C$7*$I34) | K34: =IF($C34="","",$C$8*$I34) | L34: =IF($C34="","",$C$9*$I34) | M34: =IF($C34="","",$C$10*$I34) | N34: =IF($C34="","",$C$14*$I34) | O34: =IF($C34="","",SUM(J34:N34)) | P34: =IF($C34="","",$G$7*$I34) | Q34: =IF($C34="","",$G$8*$I34) | R34: =IF($C34="","",$G$9*$I34) | S34: =IF($C34="","",$G$10*$I34) | T34: =IF($C34="","",$G$14*$I34) | U34: =IF($C34="","",SUM(P34:T34))
C35: =IF('Informe Subasta'!$A$44="","",'Informe Subasta'!$A$44) | D35: =IF($C35="","",'Informe Subasta'!$I$44) | E35: =IF($C35="","",'Informe Subasta'!$J$44) | F35: =IF($C35="","",'Informe Subasta'!$K$44) | G35: =IF($C35="","",'Informe Subasta'!$L$44) | H35: =IF($C35="","",SUM(D35:G35)) | I35: =IF($C35="","",H35/$H$51) | J35: =IF($C35="","",$C$7*$I35) | K35: =IF($C35="","",$C$8*$I35) | L35: =IF($C35="","",$C$9*$I35) | M35: =IF($C35="","",$C$10*$I35) | N35: =IF($C35="","",$C$14*$I35) | O35: =IF($C35="","",SUM(J35:N35)) | P35: =IF($C35="","",$G$7*$I35) | Q35: =IF($C35="","",$G$8*$I35) | R35: =IF($C35="","",$G$9*$I35) | S35: =IF($C35="","",$G$10*$I35) | T35: =IF($C35="","",$G$14*$I35) | U35: =IF($C35="","",SUM(P35:T35))
C36: =IF('Informe Subasta'!$A$45="","",'Informe Subasta'!$A$45) | D36: =IF($C36="","",'Informe Subasta'!$I$45) | E36: =IF($C36="","",'Informe Subasta'!$J$45) | F36: =IF($C36="","",'Informe Subasta'!$K$45) | G36: =IF($C36="","",'Informe Subasta'!$L$45) | H36: =IF($C36="","",SUM(D36:G36)) | I36: =IF($C36="","",H36/$H$51) | J36: =IF($C36="","",$C$7*$I36) | K36: =IF($C36="","",$C$8*$I36) | L36: =IF($C36="","",$C$9*$I36) | M36: =IF($C36="","",$C$10*$I36) | N36: =IF($C36="","",$C$14*$I36) | O36: =IF($C36="","",SUM(J36:N36)) | P36: =IF($C36="","",$G$7*$I36) | Q36: =IF($C36="","",$G$8*$I36) | R36: =IF($C36="","",$G$9*$I36) | S36: =IF($C36="","",$G$10*$I36) | T36: =IF($C36="","",$G$14*$I36) | U36: =IF($C36="","",SUM(P36:T36))
C37: =IF('Informe Subasta'!$A$46="","",'Informe Subasta'!$A$46) | D37: =IF($C37="","",'Informe Subasta'!$I$46) | E37: =IF($C37="","",'Informe Subasta'!$J$46) | F37: =IF($C37="","",'Informe Subasta'!$K$46) | G37: =IF($C37="","",'Informe Subasta'!$L$46) | H37: =IF($C37="","",SUM(D37:G37)) | I37: =IF($C37="","",H37/$H$51) | J37: =IF($C37="","",$C$7*$I37) | K37: =IF($C37="","",$C$8*$I37) | L37: =IF($C37="","",$C$9*$I37) | M37: =IF($C37="","",$C$10*$I37) | N37: =IF($C37="","",$C$14*$I37) | O37: =IF($C37="","",SUM(J37:N37)) | P37: =IF($C37="","",$G$7*$I37) | Q37: =IF($C37="","",$G$8*$I37) | R37: =IF($C37="","",$G$9*$I37) | S37: =IF($C37="","",$G$10*$I37) | T37: =IF($C37="","",$G$14*$I37) | U37: =IF($C37="","",SUM(P37:T37))
C38: =IF('Informe Subasta'!$A$47="","",'Informe Subasta'!$A$47) | D38: =IF($C38="","",'Informe Subasta'!$I$47) | E38: =IF($C38="","",'Informe Subasta'!$J$47) | F38: =IF($C38="","",'Informe Subasta'!$K$47) | G38: =IF($C38="","",'Informe Subasta'!$L$47) | H38: =IF($C38="","",SUM(D38:G38)) | I38: =IF($C38="","",H38/$H$51) | J38: =IF($C38="","",$C$7*$I38) | K38: =IF($C38="","",$C$8*$I38) | L38: =IF($C38="","",$C$9*$I38) | M38: =IF($C38="","",$C$10*$I38) | N38: =IF($C38="","",$C$14*$I38) | O38: =IF($C38="","",SUM(J38:N38)) | P38: =IF($C38="","",$G$7*$I38) | Q38: =IF($C38="","",$G$8*$I38) | R38: =IF($C38="","",$G$9*$I38) | S38: =IF($C38="","",$G$10*$I38) | T38: =IF($C38="","",$G$14*$I38) | U38: =IF($C38="","",SUM(P38:T38))
C39: =IF('Informe Subasta'!$A$48="","",'Informe Subasta'!$A$48) | D39: =IF($C39="","",'Informe Subasta'!$I$48) | E39: =IF($C39="","",'Informe Subasta'!$J$48) | F39: =IF($C39="","",'Informe Subasta'!$K$48) | G39: =IF($C39="","",'Informe Subasta'!$L$48) | H39: =IF($C39="","",SUM(D39:G39)) | I39: =IF($C39="","",H39/$H$51) | J39: =IF($C39="","",$C$7*$I39) | K39: =IF($C39="","",$C$8*$I39) | L39: =IF($C39="","",$C$9*$I39) | M39: =IF($C39="","",$C$10*$I39) | N39: =IF($C39="","",$C$14*$I39) | O39: =IF($C39="","",SUM(J39:N39)) | P39: =IF($C39="","",$G$7*$I39) | Q39: =IF($C39="","",$G$8*$I39) | R39: =IF($C39="","",$G$9*$I39) | S39: =IF($C39="","",$G$10*$I39) | T39: =IF($C39="","",$G$14*$I39) | U39: =IF($C39="","",SUM(P39:T39))
C40: =IF('Informe Subasta'!$A$49="","",'Informe Subasta'!$A$49) | D40: =IF($C40="","",'Informe Subasta'!$I$49) | E40: =IF($C40="","",'Informe Subasta'!$J$49) | F40: =IF($C40="","",'Informe Subasta'!$K$49) | G40: =IF($C40="","",'Informe Subasta'!$L$49) | H40: =IF($C40="","",SUM(D40:G40)) | I40: =IF($C40="","",H40/$H$51) | J40: =IF($C40="","",$C$7*$I40) | K40: =IF($C40="","",$C$8*$I40) | L40: =IF($C40="","",$C$9*$I40) | M40: =IF($C40="","",$C$10*$I40) | N40: =IF($C40="","",$C$14*$I40) | O40: =IF($C40="","",SUM(J40:N40)) | P40: =IF($C40="","",$G$7*$I40) | Q40: =IF($C40="","",$G$8*$I40) | R40: =IF($C40="","",$G$9*$I40) | S40: =IF($C40="","",$G$10*$I40) | T40: =IF($C40="","",$G$14*$I40) | U40: =IF($C40="","",SUM(P40:T40))
C41: =IF('Informe Subasta'!$A$50="","",'Informe Subasta'!$A$50) | D41: =IF($C41="","",'Informe Subasta'!$I$50) | E41: =IF($C41="","",'Informe Subasta'!$J$50) | F41: =IF($C41="","",'Informe Subasta'!$K$50) | G41: =IF($C41="","",'Informe Subasta'!$L$50) | H41: =IF($C41="","",SUM(D41:G41)) | I41: =IF($C41="","",H41/$H$51) | J41: =IF($C41="","",$C$7*$I41) | K41: =IF($C41="","",$C$8*$I41) | L41: =IF($C41="","",$C$9*$I41) | M41: =IF($C41="","",$C$10*$I41) | N41: =IF($C41="","",$C$14*$I41) | O41: =IF($C41="","",SUM(J41:N41)) | P41: =IF($C41="","",$G$7*$I41) | Q41: =IF($C41="","",$G$8*$I41) | R41: =IF($C41="","",$G$9*$I41) | S41: =IF($C41="","",$G$10*$I41) | T41: =IF($C41="","",$G$14*$I41) | U41: =IF($C41="","",SUM(P41:T41))
C42: =IF('Informe Subasta'!$A$51="","",'Informe Subasta'!$A$51) | D42: =IF($C42="","",'Informe Subasta'!$I$51) | E42: =IF($C42="","",'Informe Subasta'!$J$51) | F42: =IF($C42="","",'Informe Subasta'!$K$51) | G42: =IF($C42="","",'Informe Subasta'!$L$51) | H42: =IF($C42="","",SUM(D42:G42)) | I42: =IF($C42="","",H42/$H$51) | J42: =IF($C42="","",$C$7*$I42) | K42: =IF($C42="","",$C$8*$I42) | L42: =IF($C42="","",$C$9*$I42) | M42: =IF($C42="","",$C$10*$I42) | N42: =IF($C42="","",$C$14*$I42) | O42: =IF($C42="","",SUM(J42:N42)) | P42: =IF($C42="","",$G$7*$I42) | Q42: =IF($C42="","",$G$8*$I42) | R42: =IF($C42="","",$G$9*$I42) | S42: =IF($C42="","",$G$10*$I42) | T42: =IF($C42="","",$G$14*$I42) | U42: =IF($C42="","",SUM(P42:T42))
C43: =IF('Informe Subasta'!$A$52="","",'Informe Subasta'!$A$52) | D43: =IF($C43="","",'Informe Subasta'!$I$52) | E43: =IF($C43="","",'Informe Subasta'!$J$52) | F43: =IF($C43="","",'Informe Subasta'!$K$52) | G43: =IF($C43="","",'Informe Subasta'!$L$52) | H43: =IF($C43="","",SUM(D43:G43)) | I43: =IF($C43="","",H43/$H$51) | J43: =IF($C43="","",$C$7*$I43) | K43: =IF($C43="","",$C$8*$I43) | L43: =IF($C43="","",$C$9*$I43) | M43: =IF($C43="","",$C$10*$I43) | N43: =IF($C43="","",$C$14*$I43) | O43: =IF($C43="","",SUM(J43:N43)) | P43: =IF($C43="","",$G$7*$I43) | Q43: =IF($C43="","",$G$8*$I43) | R43: =IF($C43="","",$G$9*$I43) | S43: =IF($C43="","",$G$10*$I43) | T43: =IF($C43="","",$G$14*$I43) | U43: =IF($C43="","",SUM(P43:T43))
C44: =IF('Informe Subasta'!$A$53="","",'Informe Subasta'!$A$53) | D44: =IF($C44="","",'Informe Subasta'!$I$53) | E44: =IF($C44="","",'Informe Subasta'!$J$53) | F44: =IF($C44="","",'Informe Subasta'!$K$53) | G44: =IF($C44="","",'Informe Subasta'!$L$53) | H44: =IF($C44="","",SUM(D44:G44)) | I44: =IF($C44="","",H44/$H$51) | J44: =IF($C44="","",$C$7*$I44) | K44: =IF($C44="","",$C$8*$I44) | L44: =IF($C44="","",$C$9*$I44) | M44: =IF($C44="","",$C$10*$I44) | N44: =IF($C44="","",$C$14*$I44) | O44: =IF($C44="","",SUM(J44:N44)) | P44: =IF($C44="","",$G$7*$I44) | Q44: =IF($C44="","",$G$8*$I44) | R44: =IF($C44="","",$G$9*$I44) | S44: =IF($C44="","",$G$10*$I44) | T44: =IF($C44="","",$G$14*$I44) | U44: =IF($C44="","",SUM(P44:T44))
C45: =IF('Informe Subasta'!$A$54="","",'Informe Subasta'!$A$54) | D45: =IF($C45="","",'Informe Subasta'!$I$54) | E45: =IF($C45="","",'Informe Subasta'!$J$54) | F45: =IF($C45="","",'Informe Subasta'!$K$54) | G45: =IF($C45="","",'Informe Subasta'!$L$54) | H45: =IF($C45="","",SUM(D45:G45)) | I45: =IF($C45="","",H45/$H$51) | J45: =IF($C45="","",$C$7*$I45) | K45: =IF($C45="","",$C$8*$I45) | L45: =IF($C45="","",$C$9*$I45) | M45: =IF($C45="","",$C$10*$I45) | N45: =IF($C45="","",$C$14*$I45) | O45: =IF($C45="","",SUM(J45:N45)) | P45: =IF($C45="","",$G$7*$I45) | Q45: =IF($C45="","",$G$8*$I45) | R45: =IF($C45="","",$G$9*$I45) | S45: =IF($C45="","",$G$10*$I45) | T45: =IF($C45="","",$G$14*$I45) | U45: =IF($C45="","",SUM(P45:T45))
C46: =IF('Informe Subasta'!$A$55="","",'Informe Subasta'!$A$55) | D46: =IF($C46="","",'Informe Subasta'!$I$55) | E46: =IF($C46="","",'Informe Subasta'!$J$55) | F46: =IF($C46="","",'Informe Subasta'!$K$55) | G46: =IF($C46="","",'Informe Subasta'!$L$55) | H46: =IF($C46="","",SUM(D46:G46)) | I46: =IF($C46="","",H46/$H$51) | J46: =IF($C46="","",$C$7*$I46) | K46: =IF($C46="","",$C$8*$I46) | L46: =IF($C46="","",$C$9*$I46) | M46: =IF($C46="","",$C$10*$I46) | N46: =IF($C46="","",$C$14*$I46) | O46: =IF($C46="","",SUM(J46:N46)) | P46: =IF($C46="","",$G$7*$I46) | Q46: =IF($C46="","",$G$8*$I46) | R46: =IF($C46="","",$G$9*$I46) | S46: =IF($C46="","",$G$10*$I46) | T46: =IF($C46="","",$G$14*$I46) | U46: =IF($C46="","",SUM(P46:T46))
C47: =IF('Informe Subasta'!$A$56="","",'Informe Subasta'!$A$56) | D47: =IF($C47="","",'Informe Subasta'!$I$56) | E47: =IF($C47="","",'Informe Subasta'!$J$56) | F47: =IF($C47="","",'Informe Subasta'!$K$56) | G47: =IF($C47="","",'Informe Subasta'!$L$56) | H47: =IF($C47="","",SUM(D47:G47)) | I47: =IF($C47="","",H47/$H$51) | J47: =IF($C47="","",$C$7*$I47) | K47: =IF($C47="","",$C$8*$I47) | L47: =IF($C47="","",$C$9*$I47) | M47: =IF($C47="","",$C$10*$I47) | N47: =IF($C47="","",$C$14*$I47) | O47: =IF($C47="","",SUM(J47:N47)) | P47: =IF($C47="","",$G$7*$I47) | Q47: =IF($C47="","",$G$8*$I47) | R47: =IF($C47="","",$G$9*$I47) | S47: =IF($C47="","",$G$10*$I47) | T47: =IF($C47="","",$G$14*$I47) | U47: =IF($C47="","",SUM(P47:T47))
C48: =IF('Informe Subasta'!$A$57="","",'Informe Subasta'!$A$57) | D48: =IF($C48="","",'Informe Subasta'!$I$57) | E48: =IF($C48="","",'Informe Subasta'!$J$57) | F48: =IF($C48="","",'Informe Subasta'!$K$57) | G48: =IF($C48="","",'Informe Subasta'!$L$57) | H48: =IF($C48="","",SUM(D48:G48)) | I48: =IF($C48="","",H48/$H$51) | J48: =IF($C48="","",$C$7*$I48) | K48: =IF($C48="","",$C$8*$I48) | L48: =IF($C48="","",$C$9*$I48) | M48: =IF($C48="","",$C$10*$I48) | N48: =IF($C48="","",$C$14*$I48) | O48: =IF($C48="","",SUM(J48:N48)) | P48: =IF($C48="","",$G$7*$I48) | Q48: =IF($C48="","",$G$8*$I48) | R48: =IF($C48="","",$G$9*$I48) | S48: =IF($C48="","",$G$10*$I48) | T48: =IF($C48="","",$G$14*$I48) | U48: =IF($C48="","",SUM(P48:T48))
C49: =IF('Informe Subasta'!$A$58="","",'Informe Subasta'!$A$58) | D49: =IF($C49="","",'Informe Subasta'!$I$58) | E49: =IF($C49="","",'Informe Subasta'!$J$58) | F49: =IF($C49="","",'Informe Subasta'!$K$58) | G49: =IF($C49="","",'Informe Subasta'!$L$58) | H49: =IF($C49="","",SUM(D49:G49)) | I49: =IF($C49="","",H49/$H$51) | J49: =IF($C49="","",$C$7*$I49) | K49: =IF($C49="","",$C$8*$I49) | L49: =IF($C49="","",$C$9*$I49) | M49: =IF($C49="","",$C$10*$I49) | N49: =IF($C49="","",$C$14*$I49) | O49: =IF($C49="","",SUM(J49:N49)) | P49: =IF($C49="","",$G$7*$I49) | Q49: =IF($C49="","",$G$8*$I49) | R49: =IF($C49="","",$G$9*$I49) | S49: =IF($C49="","",$G$10*$I49) | T49: =IF($C49="","",$G$14*$I49) | U49: =IF($C49="","",SUM(P49:T49))
C50: =IF('Informe Subasta'!$A$59="","",'Informe Subasta'!$A$59) | D50: =IF($C50="","",'Informe Subasta'!$I$59) | E50: =IF($C50="","",'Informe Subasta'!$J$59) | F50: =IF($C50="","",'Informe Subasta'!$K$59) | G50: =IF($C50="","",'Informe Subasta'!$L$59) | H50: =IF($C50="","",SUM(D50:G50)) | I50: =IF($C50="","",H50/$H$51) | J50: =IF($C50="","",$C$7*$I50) | K50: =IF($C50="","",$C$8*$I50) | L50: =IF($C50="","",$C$9*$I50) | M50: =IF($C50="","",$C$10*$I50) | N50: =IF($C50="","",$C$14*$I50) | O50: =IF($C50="","",SUM(J50:N50)) | P50: =IF($C50="","",$G$7*$I50) | Q50: =IF($C50="","",$G$8*$I50) | R50: =IF($C50="","",$G$9*$I50) | S50: =IF($C50="","",$G$10*$I50) | T50: =IF($C50="","",$G$14*$I50) | U50: =IF($C50="","",SUM(P50:T50))
B51: TOTALES | C51: TOTALES | D51: =SUM(D21:D50) | E51: =SUM(E21:E50) | F51: =SUM(F21:F50) | G51: =SUM(G21:G50) | H51: =SUM(H21:H50) | I51: =SUM(I21:I50) | J51: =SUM(J21:J50) | K51: =SUM(K21:K50) | ... U51: =SUM(U21:U50)

Sheet Formato Cliente CES
B4: Conection ID | C4: # Loans | D4: Original Number | E4: Loans | F4: Total UPB | G4: # Properties | H4: Properties | I4: Total REV
B7: # Loans | C7: Loans | D7: Original Number | E7: Principal | F7: Ordinary Interest | G7: Default Interest | H7: Judicial expenses | I7: Total | J7: Proposal Included
E8: ='Informe Subasta'!$D$10 | F8: ='Informe Subasta'!$D$11 | G8: ='Informe Subasta'!$D$12+'Informe Subasta'!$K$11 | H8: ='Informe Subasta'!$D$13+IF('Informe Subasta'!$D$17>0,'Informe Subasta'!$K$12,'Informe Subasta'!$D$14) | J8: Yes
N11: Responsabilidad hipotecaria máxima
B12: # Properties | C12: Property | D12: Code | E12: Principal | F12: Ordinary Interest | G12: Default Interest | H12: Judicial expenses | I12: Total | J12: REV | K12: LTV (Principal) | L12: LTV (Claim Amount) | M12: Proposal Included | N12: Principal (MR) | O12: Ordinary Interest (MR) | P12: Default Interest (MR) | Q12: Judicial expenses (MR) | R12: Total (MR)
M13: =IF('Informe Subasta'!$A$30="","","Yes") | N13: =IF('Informe Subasta'!$A$30="","",'Informe Subasta'!$I$30) | O13: =IF('Informe Subasta'!$A$30="","",'Informe Subasta'!$J$30) | P13: =IF('Informe Subasta'!$A$30="","",'Informe Subasta'!$K$30) | Q13: =IF('Informe Subasta'!$A$30="","",'Informe Subasta'!$L$30)
M14: =IF('Informe Subasta'!$A$31="","","Yes") | N14: =IF('Informe Subasta'!$A$31="","",'Informe Subasta'!$I$31) | O14: =IF('Informe Subasta'!$A$31="","",'Informe Subasta'!$J$31) | P14: =IF('Informe Subasta'!$A$31="","",'Informe Subasta'!$K$31) | Q14: =IF('Informe Subasta'!$A$31="","",'Informe Subasta'!$L$31)
M15: =IF('Informe Subasta'!$A$32="","","Yes") | N15: =IF('Informe Subasta'!$A$32="","",'Informe Subasta'!$I$32) | O15: =IF('Informe Subasta'!$A$32="","",'Informe Subasta'!$J$32) | P15: =IF('Informe Subasta'!$A$32="","",'Informe Subasta'!$K$32) | Q15: =IF('Informe Subasta'!$A$32="","",'Informe Subasta'!$L$32)
M16: =IF('Informe Subasta'!$A$33="","","Yes") | N16: =IF('Informe Subasta'!$A$33="","",'Informe Subasta'!$I$33) | O16: =IF('Informe Subasta'!$A$33="","",'Informe Subasta'!$J$33) | P16: =IF('Informe Subasta'!$A$33="","",'Informe Subasta'!$K$33) | Q16: =IF('Informe Subasta'!$A$33="","",'Informe Subasta'!$L$33)
M17: =IF('Informe Subasta'!$A$34="","","Yes") | N17: =IF('Informe Subasta'!$A$34="","",'Informe Subasta'!$I$34) | O17: =IF('Informe Subasta'!$A$34="","",'Informe Subasta'!$J$34) | P17: =IF('Informe Subasta'!$A$34="","",'Informe Subasta'!$K$34) | Q17: =IF('Informe Subasta'!$A$34="","",'Informe Subasta'!$L$34)
M18: =IF('Informe Subasta'!$A$35="","","Yes") | N18: =IF('Informe Subasta'!$A$35="","",'Informe Subasta'!$I$35) | O18: =IF('Informe Subasta'!$A$35="","",'Informe Subasta'!$J$35) | P18: =IF('Informe Subasta'!$A$35="","",'Informe Subasta'!$K$35) | Q18: =IF('Informe Subasta'!$A$35="","",'Informe Subasta'!$L$35)
M19: =IF('Informe Subasta'!$A$36="","","Yes") | N19: =IF('Informe Subasta'!$A$36="","",'Informe Subasta'!$I$36) | O19: =IF('Informe Subasta'!$A$36="","",'Informe Subasta'!$J$36) | P19: =IF('Informe Subasta'!$A$36="","",'Informe Subasta'!$K$36) | Q19: =IF('Informe Subasta'!$A$36="","",'Informe Subasta'!$L$36)
M20: =IF('Informe Subasta'!$A$37="","","Yes") | N20: =IF('Informe Subasta'!$A$37="","",'Informe Subasta'!$I$37) | O20: =IF('Informe Subasta'!$A$37="","",'Informe Subasta'!$J$37) | P20: =IF('Informe Subasta'!$A$37="","",'Informe Subasta'!$K$37) | Q20: =IF('Informe Subasta'!$A$37="","",'Informe Subasta'!$L$37)
M21: =IF('Informe Subasta'!$A$38="","","Yes") | N21: =IF('Informe Subasta'!$A$38="","",'Informe Subasta'!$I$38) | O21: =IF('Informe Subasta'!$A$38="","",'Informe Subasta'!$J$38) | P21: =IF('Informe Subasta'!$A$38="","",'Informe Subasta'!$K$38) | Q21: =IF('Informe Subasta'!$A$38="","",'Informe Subasta'!$L$38)
M22: =IF('Informe Subasta'!$A$39="","","Yes") | N22: =IF('Informe Subasta'!$A$39="","",'Informe Subasta'!$I$39) | O22: =IF('Informe Subasta'!$A$39="","",'Informe Subasta'!$J$39) | P22: =IF('Informe Subasta'!$A$39="","",'Informe Subasta'!$K$39) | Q22: =IF('Informe Subasta'!$A$39="","",'Informe Subasta'!$L$39)
M23: =IF('Informe Subasta'!$A$40="","","Yes") | N23: =IF('Informe Subasta'!$A$40="","",'Informe Subasta'!$I$40) | O23: =IF('Informe Subasta'!$A$40="","",'Informe Subasta'!$J$40) | P23: =IF('Informe Subasta'!$A$40="","",'Informe Subasta'!$K$40) | Q23: =IF('Informe Subasta'!$A$40="","",'Informe Subasta'!$L$40)
M24: =IF('Informe Subasta'!$A$41="","","Yes") | N24: =IF('Informe Subasta'!$A$41="","",'Informe Subasta'!$I$41) | O24: =IF('Informe Subasta'!$A$41="","",'Informe Subasta'!$J$41) | P24: =IF('Informe Subasta'!$A$41="","",'Informe Subasta'!$K$41) | Q24: =IF('Informe Subasta'!$A$41="","",'Informe Subasta'!$L$41)
M25: =IF('Informe Subasta'!$A$42="","","Yes") | N25: =IF('Informe Subasta'!$A$42="","",'Informe Subasta'!$I$42) | O25: =IF('Informe Subasta'!$A$42="","",'Informe Subasta'!$J$42) | P25: =IF('Informe Subasta'!$A$42="","",'Informe Subasta'!$K$42) | Q25: =IF('Informe Subasta'!$A$42="","",'Informe Subasta'!$L$42)
M26: =IF('Informe Subasta'!$A$43="","","Yes") | N26: =IF('Informe Subasta'!$A$43="","",'Informe Subasta'!$I$43) | O26: =IF('Informe Subasta'!$A$43="","",'Informe Subasta'!$J$43) | P26: =IF('Informe Subasta'!$A$43="","",'Informe Subasta'!$K$43) | Q26: =IF('Informe Subasta'!$A$43="","",'Informe Subasta'!$L$43)
M27: =IF('Informe Subasta'!$A$44="","","Yes") | N27: =IF('Informe Subasta'!$A$44="","",'Informe Subasta'!$I$44) | O27: =IF('Informe Subasta'!$A$44="","",'Informe Subasta'!$J$44) | P27: =IF('Informe Subasta'!$A$44="","",'Informe Subasta'!$K$44) | Q27: =IF('Informe Subasta'!$A$44="","",'Informe Subasta'!$L$44)
M28: =IF('Informe Subasta'!$A$45="","","Yes") | N28: =IF('Informe Subasta'!$A$45="","",'Informe Subasta'!$I$45) | O28: =IF('Informe Subasta'!$A$45="","",'Informe Subasta'!$J$45) | P28: =IF('Informe Subasta'!$A$45="","",'Informe Subasta'!$K$45) | Q28: =IF('Informe Subasta'!$A$45="","",'Informe Subasta'!$L$45)
M29: =IF('Informe Subasta'!$A$46="","","Yes") | N29: =IF('Informe Subasta'!$A$46="","",'Informe Subasta'!$I$46) | O29: =IF('Informe Subasta'!$A$46="","",'Informe Subasta'!$J$46) | P29: =IF('Informe Subasta'!$A$46="","",'Informe Subasta'!$K$46) | Q29: =IF('Informe Subasta'!$A$46="","",'Informe Subasta'!$L$46)
M30: =IF('Informe Subasta'!$A$47="","","Yes") | N30: =IF('Informe Subasta'!$A$47="","",'Informe Subasta'!$I$47) | O30: =IF('Informe Subasta'!$A$47="","",'Informe Subasta'!$J$47) | P30: =IF('Informe Subasta'!$A$47="","",'Informe Subasta'!$K$47) | Q30: =IF('Informe Subasta'!$A$47="","",'Informe Subasta'!$L$47)
M31: =IF('Informe Subasta'!$A$48="","","Yes") | N31: =IF('Informe Subasta'!$A$48="","",'Informe Subasta'!$I$48) | O31: =IF('Informe Subasta'!$A$48="","",'Informe Subasta'!$J$48) | P31: =IF('Informe Subasta'!$A$48="","",'Informe Subasta'!$K$48) | Q31: =IF('Informe Subasta'!$A$48="","",'Informe Subasta'!$L$48)
M32: =IF('Informe Subasta'!$A$49="","","Yes") | N32: =IF('Informe Subasta'!$A$49="","",'Informe Subasta'!$I$49) | O32: =IF('Informe Subasta'!$A$49="","",'Informe Subasta'!$J$49) | P32: =IF('Informe Subasta'!$A$49="","",'Informe Subasta'!$K$49) | Q32: =IF('Informe Subasta'!$A$49="","",'Informe Subasta'!$L$49)
M33: =IF('Informe Subasta'!$A$50="","","Yes") | N33: =IF('Informe Subasta'!$A$50="","",'Informe Subasta'!$I$50) | O33: =IF('Informe Subasta'!$A$50="","",'Informe Subasta'!$J$50) | P33: =IF('Informe Subasta'!$A$50="","",'Informe Subasta'!$K$50) | Q33: =IF('Informe Subasta'!$A$50="","",'Informe Subasta'!$L$50)
M34: =IF('Informe Subasta'!$A$51="","","Yes") | N34: =IF('Informe Subasta'!$A$51="","",'Informe Subasta'!$I$51) | O34: =IF('Informe Subasta'!$A$51="","",'Informe Subasta'!$J$51) | P34: =IF('Informe Subasta'!$A$51="","",'Informe Subasta'!$K$51) | Q34: =IF('Informe Subasta'!$A$51="","",'Informe Subasta'!$L$51)
M35: =IF('Informe Subasta'!$A$52="","","Yes") | N35: =IF('Informe Subasta'!$A$52="","",'Informe Subasta'!$I$52) | O35: =IF('Informe Subasta'!$A$52="","",'Informe Subasta'!$J$52) | P35: =IF('Informe Subasta'!$A$52="","",'Informe Subasta'!$K$52) | Q35: =IF('Informe Subasta'!$A$52="","",'Informe Subasta'!$L$52)
M36: =IF('Informe Subasta'!$A$53="","","Yes") | N36: =IF('Informe Subasta'!$A$53="","",'Informe Subasta'!$I$53) | O36: =IF('Informe Subasta'!$A$53="","",'Informe Subasta'!$J$53) | P36: =IF('Informe Subasta'!$A$53="","",'Informe Subasta'!$K$53) | Q36: =IF('Informe Subasta'!$A$53="","",'Informe Subasta'!$L$53)
M37: =IF('Informe Subasta'!$A$54="","","Yes") | N37: =IF('Informe Subasta'!$A$54="","",'Informe Subasta'!$I$54) | O37: =IF('Informe Subasta'!$A$54="","",'Informe Subasta'!$J$54) | P37: =IF('Informe Subasta'!$A$54="","",'Informe Subasta'!$K$54) | Q37: =IF('Informe Subasta'!$A$54="","",'Informe Subasta'!$L$54)
M38: =IF('Informe Subasta'!$A$55="","","Yes") | N38: =IF('Informe Subasta'!$A$55="","",'Informe Subasta'!$I$55) | O38: =IF('Informe Subasta'!$A$55="","",'Informe Subasta'!$J$55) | P38: =IF('Informe Subasta'!$A$55="","",'Informe Subasta'!$K$55) | Q38: =IF('Informe Subasta'!$A$55="","",'Informe Subasta'!$L$55)
M39: =IF('Informe Subasta'!$A$56="","","Yes") | N39: =IF('Informe Subasta'!$A$56="","",'Informe Subasta'!$I$56) | O39: =IF('Informe Subasta'!$A$56="","",'Informe Subasta'!$J$56) | P39: =IF('Informe Subasta'!$A$56="","",'Informe Subasta'!$K$56) | Q39: =IF('Informe Subasta'!$A$56="","",'Informe Subasta'!$L$56)
M40: =IF('Informe Subasta'!$A$57="","","Yes") | N40: =IF('Informe Subasta'!$A$57="","",'Informe Subasta'!$I$57) | O40: =IF('Informe Subasta'!$A$57="","",'Informe Subasta'!$J$57) | P40: =IF('Informe Subasta'!$A$57="","",'Informe Subasta'!$K$57) | Q40: =IF('Informe Subasta'!$A$57="","",'Informe Subasta'!$L$57)
M41: =IF('Informe Subasta'!$A$58="","","Yes") | N41: =IF('Informe Subasta'!$A$58="","",'Informe Subasta'!$I$58) | O41: =IF('Informe Subasta'!$A$58="","",'Informe Subasta'!$J$58) | P41: =IF('Informe Subasta'!$A$58="","",'Informe Subasta'!$K$58) | Q41: =IF('Informe Subasta'!$A$58="","",'Informe Subasta'!$L$58)
M42: =IF('Informe Subasta'!$A$59="","","Yes") | N42: =IF('Informe Subasta'!$A$59="","",'Informe Subasta'!$I$59) | O42: =IF('Informe Subasta'!$A$59="","",'Informe Subasta'!$J$59) | P42: =IF('Informe Subasta'!$A$59="","",'Informe Subasta'!$K$59) | Q42: =IF('Informe Subasta'!$A$59="","",'Informe Subasta'!$L$59)

Sheet Formato Cliente
B2: AI / Extracted/Manual Fields
B3: Formulas
B4: Debt Calculation Output
F5: Initial Claim Amount | G5: =+C7+C8+C9+C12
B6: TOTAL UPDATED DEBT | D6: MAXIMUM SECURED AMOUNT | F6: DEUDA LIMITADA A RESPONSABILIDAD
B7: Capital/Principal | C7: ='Informe Subasta'!$D$10 | D7: Capital/Principal | E7: =+$C$25 | F7: Capital | G7: =+$C$41
B8: Interest | C8: ='Informe Subasta'!$D$11 | D8: Interest | E8: =+$D$25 | F8: Int. Ordinarios | G8: =+$D$41
B9: Penalty Interest | C9: ='Informe Subasta'!$D$12 | D9: Penalty Interest | E9: =+$E$25 | F9: Penalty Interest + Updated Interest | G9: =+$E$41 | H9: We are considering "Updated Interest" as "Penalty Interest"
B10: Updated Interest (Penalty) | C10: =G17
B11: Judicial Costs | C11: =+I17 | D11: Judicial Costs | E11: =+$F$25 | F11: Judicial Costs | G11: =+$F$41
B12: Other Expenses | C12: ='Informe Subasta'!$D$13 | D12: Other Expenses | E12: =+$G$25 | F12: Other Expenses | G12: =+$G$41
B13: TOTAL | C13: =SUM(C7:C11) | D13: TOTAL | E13: =SUM(E7:E11) | F13: TOTAL | G13: =SUM(G7:G12)
B15: DEBT CALCULATION (UPDATED INTEREST & JUDICIAL COSTS) | J15: *If any property is "First Residence", "Judicial Costs" are calculated and capped at 5% of the "Initial Claim Amount". Otherwise, the user must be able to enter the value manually | K15: Datos y modo se gestionan en «Informe Subasta». Vista enlazada (formato cliente).
B16: Account Closure Date | C16: Calculation Date | D16: Interest Applicable Rate (%) | E16: Penalty Interest Applicable Rate (%) | F16: Consumer | G16: Updated Interest (€) | H16: First Residence | I16: Judicial Costs*
B17: ='Informe Subasta'!$D$15 | C17: ='Informe Subasta'!$D$16 | D17: ='Informe Subasta'!$D$22 | E17: ='Informe Subasta'!$D$23 | F17: ='Informe Subasta'!$D$21 | G17: ='Cálculo Intereses'!$D$21 | H17: =IF('Informe Subasta'!$D$17>0,"Y","N") | I17: =+IF($H$17="Y",($C$7+$C$8+$C$9+$C$12)*0.05,0)
B19: MAXIMUM SECURED AMOUNT
B20: Property_ID | C20: Principal Maximum Secured Amount | D20: Interest Maximum Secured Amount | E20: Penalty Interest Maximum Secured Amount | F20: Judicial Costs Maximum Secured Amount | G20: Other Expenses Maximum Secured Amount | H20: Total R.H. | I20: % Property Weight
B21: ='Informe Subasta'!A30 | C21: ='Informe Subasta'!I30 | D21: ='Informe Subasta'!J30 | E21: ='Informe Subasta'!K30 | F21: ='Informe Subasta'!L30 | G21: 0 | H21: =+SUM(C21:F21) | I21: =+H21/$H$25
B22: ='Informe Subasta'!A31 | C22: ='Informe Subasta'!I31 | D22: ='Informe Subasta'!J31 | E22: ='Informe Subasta'!K31 | F22: ='Informe Subasta'!L31 | G22: 0 | H22: =+SUM(C22:F22) | I22: =+H22/$H$25
B23: ='Informe Subasta'!A32 | C23: ='Informe Subasta'!I32 | D23: ='Informe Subasta'!J32 | E23: ='Informe Subasta'!K32 | F23: ='Informe Subasta'!L32 | G23: 0 | H23: =+SUM(C23:F23) | I23: =+H23/$H$25
B24: ='Informe Subasta'!A33 | C24: ='Informe Subasta'!I33 | D24: ='Informe Subasta'!J33 | E24: ='Informe Subasta'!K33 | F24: ='Informe Subasta'!L33 | G24: 0 | H24: =+SUM(C24:F24) | I24: =+H24/$H$25
B25: TOTALES | C25: =+SUM(C$21:C$24) | D25: =+SUM(D$21:D$24) | E25: =+SUM(E$21:E$24) | F25: =+SUM(F$21:F$24) | G25: =+SUM(G$21:G$24) | H25: =+SUM(H$21:H$24) | I25: =+SUM(I$21:I$24)
B27: TOTAL UPDATED DEBT DISTRIBUTED BY (%)
B28: Property_ID | C28: Capital/Principal | D28: Interest | E28: Penalty Interest | F28: Judicial Costs | G28: Other Expenses | H28: TOTAL DEBT
B29: 1 | C29: =$C$7*$I21 | D29: =$C$8*I21 | E29: =($C$9+$C$10)*$I21 | F29: =$C$11*$I21 | G29: =$C$12*$I21 | H29: =SUM(C29:G29)
B30: 2 | C30: =$C$7*$I22 | D30: =$C$8*I22 | E30: =($C$9+$C$10)*$I22 | F30: =$C$11*$I22 | G30: =$C$12*$I22 | H30: =SUM(C30:G30)
B31: 3 | C31: =$C$7*$I23 | D31: =$C$8*I23 | E31: =($C$9+$C$10)*$I23 | F31: =$C$11*$I23 | G31: =$C$12*$I23 | H31: =SUM(C31:G31)
B32: 4 | C32: =$C$7*$I24 | D32: =$C$8*I24 | E32: =($C$9+$C$10)*$I24 | F32: =$C$11*$I24 | G32: =$C$12*$I24 | H32: =SUM(C32:G32)
B33: TOTALES | C33: =+SUM(C$29:C$32) | D33: =+SUM(D$29:D$32) | E33: =+SUM(E$29:E$32) | F33: =+SUM(F$29:F$32) | G33: =+SUM(G$29:G$32) | H33: =+SUM(H$29:H$32)
B35: TOTAL LIMITED UPDATED DEBT DISTRIBUTED BY %
B36: Property_ID | C36: Capital/Principal | D36: Interest | E36: Penalty Interest | F36: Judicial Costs | G36: Other Expenses | H36: TOTAL DEBT
B37: 1 | C37: =MIN(($C$7*$I21),$C21) | D37: =MIN(($C$8*$I21),$D21) | E37: =MIN((($C$9+$C$10)*$I21),$E21) | F37: =MIN(($C$11*$I21),$F21) | G37: =MIN(($C$12*$I21),$G21) | H37: =SUM(C37:G37)
B38: 2 | C38: =MIN(($C$7*$I22),$C22) | D38: =MIN(($C$8*$I22),$D22) | E38: =MIN((($C$9+$C$10)*$I22),$E22) | F38: =MIN(($C$11*$I22),$F22) | G38: =MIN(($C$12*$I22),$G22) | H38: =SUM(C38:G38)
B39: 3 | C39: =MIN(($C$7*$I23),$C23) | D39: =MIN(($C$8*$I23),$D23) | E39: =MIN((($C$9+$C$10)*$I23),$E23) | F39: =MIN(($C$11*$I23),$F23) | G39: =MIN(($C$12*$I23),$G23) | H39: =SUM(C39:G39)
B40: 4 | C40: =MIN(($C$7*$I24),$C24) | D40: =MIN(($C$8*$I24),$D24) | E40: =MIN((($C$9+$C$10)*$I24),$E24) | F40: =MIN(($C$11*$I24),$F24) | G40: =MIN(($C$12*$I24),$G24) | H40: =SUM(C40:G40)
B41: TOTALES | C41: =+SUM(C$37:C$40) | D41: =+SUM(D$37:D$40) | E41: =+SUM(E$37:E$40) | F41: =+SUM(F$37:F$40) | G41: =+SUM(G$37:G$40) | H41: =+SUM(H$37:H$40)

Sheet Guía
B2: CÁLCULO DE DEUDA E INFORME DE SUBASTA
B4: Todos los datos que usted introduce están en «Informe Subasta». Arriba un panel RESUMEN con KPIs; debajo los formularios en dos columnas y la tabla por finca.
B5: Pestañas
B6: • Informe Subasta — ÚNICA hoja de entrada. RESUMEN (dashboard) + formularios (izq: deuda e interés; dcha: subasta, devengo y check-list) + tabla por finca con límites registrales, distribución y pujas.
B7: • Cálculo Intereses — cálculo automático por tramos (fijo/variable/legal) + mini-gráfico; enlazado, no se edita.
B8: • Formato cliente — el mismo cálculo en formato cliente, enlazado.
B9: • Tipos BdE — tipos del Banco de España (actualícelos con «Actualizar_Tipos_BdE.bat»).
B10: Código de colores
B11: Azul = entrada · Verde = enlace (no editar) · Morado = interruptor · Amarillo = total · Blanco = fórmula.
B12: Lógica
B13: Interés simple Actual/365 = capital × tipo% × días ÷ 36.500.
B15: Criterios de adjudicación (valor mínimo - Previo Ley 1/2025):
... B20: (Régimen POST Ley 1/2025: suelos 40/50/60/70% según vivienda habitual.)

Sheet BBDD Guardados
A1: FechaGuardado | B1: LegalID | C1: LoanID | D1: LoanNumber | E1: OriginalLoanNumber | F1: Principal | G1: Interest | H1: PenaltyInterest | I1: Expenses | J1: JudicialCostsAmount | K1: AccountClosureDate | L1: CalculationDate | M1: Mode | N1: IsConsumer | O1: InterestApplicableRate(%) | P1: PenaltyInterestApplicableRate(%) | Q1: ReferenceRate | R1: DifferentialRate | S1: UpdateRateFrequency | T1: LastRateUpdateDate | U1: RateDelay | V1: NegativeRatesToZero | W1: Law12025Regime | X1: ExecutionOrderAmount | Y1: BudgetAmount | Z1: SecondLienAmount | AA1: ThirdLienAmount | AB1: UpdatedInterestAmount | AC1: Total_ADE | AD1: Costas_aplicada | AE1: TOTAL_DEUDA | AF1: TOTAL_DEUDAS_cargas | AG1: Dias | AH1: Tipo_medio | AI1: Puja_LOANCO | AJ1: Puja_REOCO | AK1: Cobertura | AL1: Cash_out

Sheet BBDD Guardados Fincas
A1: LegalID | B1: LoanID | C1: PropertyID | D1: IsFirstResidence | E1: LoancoReoco | F1: BaseAmount | G1: CapitalMSA | H1: InterestMSA | I1: PenaltyInterestMSA | J1: OtherExp+JudCosts MSA | K1: CadastralReference | L1: LandRegistry | M1: TomoLibroFolio | N1: Peso | O1: Capital_deuda | P1: Ordinarios_deuda | Q1: Moratorios_deuda | R1: Costas_deuda | S1: TOTAL_DEBT | T1: Cargas | U1: TOTAL_cargas | V1: Puja_LOANCO | W1: Cash_out_LOANCO | X1: Puja_REOCO | Y1: Cash_out_REOCO

Sheet CI Variable
A1: CÁLCULO AUTOMÁTICO DE INTERESES (por tramos)
A2: Interés simple, Actual/365 = capital × tipo% × días ÷ 36.500. Datos enlazados desde «Informe Subasta» (no editar aquí).
A4: PARÁMETROS (enlazados) | G4: Nº | H4: Fecha inicio | I4: Fecha fin | J4: Días | K4: Fecha ref. tipo | L4: Tipo base (%) | M4: Diferencial (%) | N4: Tipo aplicado (%) | O4: Intereses (€) | P4: Deuda acumulada (€)
A5: Principal (€) | D5: ='Informe Subasta'!$D$10 | G5: =IF(H5="","",ROW()-4) | H5: =$D$6 | I5: =IF(H5="","",MIN(IF($D$18="LEGAL",DATE(YEAR(H5)+1,1,1),EDATE($D$12,$D$11*(INT((((YEAR(H5)-YEAR($D$12))*12+(MONTH(H5)-MONTH($D$12))-IF(DAY(H5)<DAY($D$12),1,0))/$D$11))+1))),$D$7)) | J5: =IF(H5="","",I5-H5) | K5: =IF(H5="","",IF($D$18="LEGAL",H5,EDATE($D$12,-$D$13))) | L5: =IF(H5="","",IFERROR(INDEX('Tipos BdE'!$B$7:$M$336,MATCH(DATE(YEAR(K5),MONTH(K5),1),'Tipos BdE'!$A$7:$A$336,1),MATCH($D$9,'Tipos BdE'!$B$6:$M$6,0)),0)) | M5: =IF(H5="","",IF($D$18="LEGAL",0,$D$10)) | N5: =IF(H5="","",IF(AND($D$14="Sí",(L5+M5)<0),0,L5+M5)) | O5: =IF(H5="","",$D$5*N5*J5/36500) | P5: =IF(H5="","",$D$5+SUM($O$5:O5))
A6: AccountClosureDate (cierre) | D6: ='Informe Subasta'!$D$15 | G6: =IF(H6="","",ROW()-4) | H6: =IF(OR(I5="",I5>=$D$7),"",I5) | I6: =IF(H6="","",MIN(IF($D$18="LEGAL",DATE(YEAR(H6)+1,1,1),EDATE($D$12,$D$11*(INT((((YEAR(H6)-YEAR($D$12))*12+(MONTH(H6)-MONTH($D$12))-IF(DAY(H6)<DAY($D$12),1,0))/$D$11))+1))),$D$7)) | J6: =IF(H6="","",I6-H6) | K6: =IF(H6="","",IF($D$18="LEGAL",H6,EDATE(H6,-$D$13))) | L6: =IF(H6="","",IFERROR(INDEX('Tipos BdE'!$B$7:$M$336,MATCH(DATE(YEAR(K6),MONTH(K6),1),'Tipos BdE'!$A$7:$A$336,1),MATCH($D$9,'Tipos BdE'!$B$6:$M$6,0)),0)) | M6: =IF(H6="","",IF($D$18="LEGAL",0,$D$10)) | N6: =IF(H6="","",IF(AND($D$14="Sí",(L6+M6)<0),0,L6+M6)) | O6: =IF(H6="","",$D$5*N6*J6/36500) | P6: =IF(H6="","",$D$5+SUM($O$5:O6))
A7: CalculationDate | D7: ='Informe Subasta'!$D$16 | G7: =IF(H7="","",ROW()-4) | H7: =IF(OR(I6="",I6>=$D$7),"",I6) | I7: =IF(H7="","",MIN(IF($D$18="LEGAL",DATE(YEAR(H7)+1,1,1),EDATE($D$12,$D$11*(INT((((YEAR(H7)-YEAR($D$12))*12+(MONTH(H7)-MONTH($D$12))-IF(DAY(H7)<DAY($D$12),1,0))/$D$11))+1))),$D$7)) | J7: =IF(H7="","",I7-H7) | K7: =IF(H7="","",IF($D$18="LEGAL",H7,EDATE(H7,-$D$13))) | L7: =IF(H7="","",IFERROR(INDEX('Tipos BdE'!$B$7:$M$336,MATCH(DATE(YEAR(K7),MONTH(K7),1),'Tipos BdE'!$A$7:$A$336,1),MATCH($D$9,'Tipos BdE'!$B$6:$M$6,0)),0)) | M7: =IF(H7="","",IF($D$18="LEGAL",0,$D$10)) | N7: =IF(H7="","",IF(AND($D$14="Sí",(L7+M7)<0),0,L7+M7)) | O7: =IF(H7="","",$D$5*N7*J7/36500) | P7: =IF(H7="","",$D$5+SUM($O$5:O7))
A8: Mode | D8: ='Informe Subasta'!$D$20 | G8: =IF(H8="","",ROW()-4) | H8: =IF(OR(I7="",I7>=$D$7),"",I7) | I8: =IF(H8="","",MIN(IF($D$18="LEGAL",DATE(YEAR(H8)+1,1,1),EDATE($D$12,$D$11*(INT((((YEAR(H8)-YEAR($D$12))*12+(MONTH(H8)-MONTH($D$12))-IF(DAY(H8)<DAY($D$12),1,0))/$D$11))+1))),$D$7)) | J8: =IF(H8="","",I8-H8) | K8: =IF(H8="","",IF($D$18="LEGAL",H8,EDATE(H8,-$D$13))) | L8: =IF(H8="","",IFERROR(INDEX('Tipos BdE'!$B$7:$M$336,MATCH(DATE(YEAR(K8),MONTH(K8),1),'Tipos BdE'!$A$7:$A$336,1),MATCH($D$9,'Tipos BdE'!$B$6:$M$6,0)),0)) | M8: =IF(H8="","",IF($D$18="LEGAL",0,$D$10)) | N8: =IF(H8="","",IF(AND($D$14="Sí",(L8+M8)<0),0,L8+M8)) | O8: =IF(H8="","",$D$5*N8*J8/36500) | P8: =IF(H8="","",$D$5+SUM($O$5:O8))
A9: ReferenceRate (BdE) | D9: ='Informe Subasta'!$K$20 | G9: =IF(H9="","",ROW()-4) | H9: =IF(OR(I8="",I8>=$D$7),"",I8) | I9: =IF(H9="","",MIN(IF($D$18="LEGAL",DATE(YEAR(H9)+1,1,1),EDATE($D$12,$D$11*(INT((((YEAR(H9)-YEAR($D$12))*12+(MONTH(H9)-MONTH($D$12))-IF(DAY(H9)<DAY($D$12),1,0))/$D$11))+1))),$D$7)) | J9: =IF(H9="","",I9-H9) | K9: =IF(H9="","",IF($D$18="LEGAL",H9,EDATE(H9,-$D$13))) | L9: =IF(H9="","",IFERROR(INDEX('Tipos BdE'!$B$7:$M$336,MATCH(DATE(YEAR(K9),MONTH(K9),1),'Tipos BdE'!$A$7:$A$336,1),MATCH($D$9,'Tipos BdE'!$B$6:$M$6,0)),0)) | M9: =IF(H9="","",IF($D$18="LEGAL",0,$D$10)) | N9: =IF(H9="","",IF(AND($D$14="Sí",(L9+M9)<0),0,L9+M9)) | O9: =IF(H9="","",$D$5*N9*J9/36500) | P9: =IF(H9="","",$D$5+SUM($O$5:O9))
A10: DifferentialRate (puntos) | D10: ='Informe Subasta'!$K$21 | G10: =IF(H10="","",ROW()-4) | H10: =IF(OR(I9="",I9>=$D$7),"",I9) | I10: =IF(H10="","",MIN(IF($D$18="LEGAL",DATE(YEAR(H10)+1,1,1),EDATE($D$12,$D$11*(INT((((YEAR(H10)-YEAR($D$12))*12+(MONTH(H10)-MONTH($D$12))-IF(DAY(H10)<DAY($D$12),1,0))/$D$11))+1))),$D$7)) | J10: =IF(H10="","",I10-H10) | K10: =IF(H10="","",IF($D$18="LEGAL",H10,EDATE(H10,-$D$13))) | L10: =IF(H10="","",IFERROR(INDEX('Tipos BdE'!$B$7:$M$336,MATCH(DATE(YEAR(K10),MONTH(K10),1),'Tipos BdE'!$A$7:$A$336,1),MATCH($D$9,'Tipos BdE'!$B$6:$M$6,0)),0)) | M10: =IF(H10="","",IF($D$18="LEGAL",0,$D$10)) | N10: =IF(H10="","",IF(AND($D$14="Sí",(L10+M10)<0),0,L10+M10)) | O10: =IF(H10="","",$D$5*N10*J10/36500) | P10: =IF(H10="","",$D$5+SUM($O$5:O10))
A11: UpdateRateFrequency (meses) | D11: ='Informe Subasta'!$K$22 | G11: =IF(H11="","",ROW()-4) | H11: =IF(OR(I10="",I10>=$D$7),"",I10) | I11: =IF(H11="","",MIN(IF($D$18="LEGAL",DATE(YEAR(H11)+1,1,1),EDATE($D$12,$D$11*(INT((((YEAR(H11)-YEAR($D$12))*12+(MONTH(H11)-MONTH($D$12))-IF(DAY(H11)<DAY($D$12),1,0))/$D$11))+1))),$D$7)) | J11: =IF(H11="","",I11-H11) | K11: =IF(H11="","",IF($D$18="LEGAL",H11,EDATE(H11,-$D$13))) | L11: =IF(H11="","",IFERROR(INDEX('Tipos BdE'!$B$7:$M$336,MATCH(DATE(YEAR(K11),MONTH(K11),1),'Tipos BdE'!$A$7:$A$336,1),MATCH($D$9,'Tipos BdE'!$B$6:$M$6,0)),0)) | M11: =IF(H11="","",IF($D$18="LEGAL",0,$D$10)) | N11: =IF(H11="","",IF(AND($D$14="Sí",(L11+M11)<0),0,L11+M11)) | O11: =IF(H11="","",$D$5*N11*J11/36500) | P11: =IF(H11="","",$D$5+SUM($O$5:O11))
A12: LastRateUpdateDate | D12: ='Informe Subasta'!$K$23 | G12: =IF(H12="","",ROW()-4) | H12: =IF(OR(I11="",I11>=$D$7),"",I11) | I12: =IF(H12="","",MIN(IF($D$18="LEGAL",DATE(YEAR(H12)+1,1,1),EDATE($D$12,$D$11*(INT((((YEAR(H12)-YEAR($D$12))*12+(MONTH(H12)-MONTH($D$12))-IF(DAY(H12)<DAY($D$12),1,0))/$D$11))+1))),$D$7)) | J12: =IF(H12="","",I12-H12) | K12: =IF(H12="","",IF($D$18="LEGAL",H12,EDATE(H12,-$D$13))) | L12: =IF(H12="","",IFERROR(INDEX('Tipos BdE'!$B$7:$M$336,MATCH(DATE(YEAR(K12),MONTH(K12),1),'Tipos BdE'!$A$7:$A$336,1),MATCH($D$9,'Tipos BdE'!$B$6:$M$6,0)),0)) | M12: =IF(H12="","",IF($D$18="LEGAL",0,$D$10)) | N12: =IF(H12="","",IF(AND($D$14="Sí",(L12+M12)<0),0,L12+M12)) | O12: =IF(H12="","",$D$5*N12*J12/36500) | P12: =IF(H12="","",$D$5+SUM($O$5:O12))
A13: RateDelay (meses) | D13: ='Informe Subasta'!$K$24 | G13: =IF(H13="","",ROW()-4) | H13: =IF(OR(I12="",I12>=$D$7),"",I12) | I13: =IF(H13="","",MIN(IF($D$18="LEGAL",DATE(YEAR(H13)+1,1,1),EDATE($D$12,$D$11*(INT((((YEAR(H13)-YEAR($D$12))*12+(MONTH(H13)-MONTH($D$12))-IF(DAY(H13)<DAY($D$12),1,0))/$D$11))+1))),$D$7)) | J13: =IF(H13="","",I13-H13) | K13: =IF(H13="","",IF($D$18="LEGAL",H13,EDATE(H13,-$D$13))) | L13: =IF(H13="","",IFERROR(INDEX('Tipos BdE'!$B$7:$M$336,MATCH(DATE(YEAR(K13),MONTH(K13),1),'Tipos BdE'!$A$7:$A$336,1),MATCH($D$9,'Tipos BdE'!$B$6:$M$6,0)),0)) | M13: =IF(H13="","",IF($D$18="LEGAL",0,$D$10)) | N13: =IF(H13="","",IF(AND($D$14="Sí",(L13+M13)<0),0,L13+M13)) | O13: =IF(H13="","",$D$5*N13*J13/36500) | P13: =IF(H13="","",$D$5+SUM($O$5:O13))
A14: NegativeRatesToZero | D14: ='Informe Subasta'!$D$24 | G14: =IF(H14="","",ROW()-4) | H14: =IF(OR(I13="",I13>=$D$7),"",I13) | I14: =IF(H14="","",MIN(IF($D$18="LEGAL",DATE(YEAR(H14)+1,1,1),EDATE($D$12,$D$11*(INT((((YEAR(H14)-YEAR($D$12))*12+(MONTH(H14)-MONTH($D$12))-IF(DAY(H14)<DAY($D$12),1,0))/$D$11))+1))),$D$7)) | J14: =IF(H14="","",I14-H14) | K14: =IF(H14="","",IF($D$18="LEGAL",H14,EDATE(H14,-$D$13))) | L14: =IF(H14="","",IFERROR(INDEX('Tipos BdE'!$B$7:$M$336,MATCH(DATE(YEAR(K14),MONTH(K14),1),'Tipos BdE'!$A$7:$A$336,1),MATCH($D$9,'Tipos BdE'!$B$6:$M$6,0)),0)) | M14: =IF(H14="","",IF($D$18="LEGAL",0,$D$10)) | N14: =IF(H14="","",IF(AND($D$14="Sí",(L14+M14)<0),0,L14+M14)) | O14: =IF(H14="","",$D$5*N14*J14/36500) | P14: =IF(H14="","",$D$5+SUM($O$5:O14))
A15: IsConsumer | D15: ='Informe Subasta'!$D$21 | G15: =IF(H15="","",ROW()-4) | H15: =IF(OR(I14="",I14>=$D$7),"",I14) | I15: =IF(H15="","",MIN(IF($D$18="LEGAL",DATE(YEAR(H15)+1,1,1),EDATE($D$12,$D$11*(INT((((YEAR(H15)-YEAR($D$12))*12+(MONTH(H15)-MONTH($D$12))-IF(DAY(H15)<DAY($D$12),1,0))/$D$11))+1))),$D$7)) | J15: =IF(H15="","",I15-H15) | K15: =IF(H15="","",IF($D$18="LEGAL",H15,EDATE(H15,-$D$13))) | L15: =IF(H15="","",IFERROR(INDEX('Tipos BdE'!$B$7:$M$336,MATCH(DATE(YEAR(K15),MONTH(K15),1),'Tipos BdE'!$A$7:$A$336,1),MATCH($D$9,'Tipos BdE'!$B$6:$M$6,0)),0)) | M15: =IF(H15="","",IF($D$18="LEGAL",0,$D$10)) | N15: =IF(H15="","",IF(AND($D$14="Sí",(L15+M15)<0),0,L15+M15)) | O15: =IF(H15="","",$D$5*N15*J15/36500) | P15: =IF(H15="","",$D$5+SUM($O$5:O15))
A16: InterestApplicableRate | D16: ='Informe Subasta'!$D$22 | G16: =IF(H16="","",ROW()-4) | H16: =IF(OR(I15="",I15>=$D$7),"",I15) | I16: =IF(H16="","",MIN(IF($D$18="LEGAL",DATE(YEAR(H16)+1,1,1),EDATE($D$12,$D$11*(INT((((YEAR(H16)-YEAR($D$12))*12+(MONTH(H16)-MONTH($D$12))-IF(DAY(H16)<DAY($D$12),1,0))/$D$11))+1))),$D$7)) | J16: =IF(H16="","",I16-H16) | K16: =IF(H16="","",IF($D$18="LEGAL",H16,EDATE(H16,-$D$13))) | L16: =IF(H16="","",IFERROR(INDEX('Tipos BdE'!$B$7:$M$336,MATCH(DATE(YEAR(K16),MONTH(K16),1),'Tipos BdE'!$A$7:$A$336,1),MATCH($D$9,'Tipos BdE'!$B$6:$M$6,0)),0)) | M16: =IF(H16="","",IF($D$18="LEGAL",0,$D$10)) | N16: =IF(H16="","",IF(AND($D$14="Sí",(L16+M16)<0),0,L16+M16)) | O16: =IF(H16="","",$D$5*N16*J16/36500) | P16: =IF(H16="","",$D$5+SUM($O$5:O16))
A17: PenaltyInterestApplicableRate | D17: ='Informe Subasta'!$D$23 | G17: =IF(H17="","",ROW()-4) | H17: =IF(OR(I16="",I16>=$D$7),"",I16) | I17: =IF(H17="","",MIN(IF($D$18="LEGAL",DATE(YEAR(H17)+1,1,1),EDATE($D$12,$D$11*(INT((((YEAR(H17)-YEAR($D$12))*12+(MONTH(H17)-MONTH($D$12))-IF(DAY(H17)<DAY($D$12),1,0))/$D$11))+1))),$D$7)) | J17: =IF(H17="","",I17-H17) | K17: =IF(H17="","",IF($D$18="LEGAL",H17,EDATE(H17,-$D$13))) | L17: =IF(H17="","",IFERROR(INDEX('Tipos BdE'!$B$7:$M$336,MATCH(DATE(YEAR(K17),MONTH(K17),1),'Tipos BdE'!$A$7:$A$336,1),MATCH($D$9,'Tipos BdE'!$B$6:$M$6,0)),0)) | M17: =IF(H17="","",IF($D$18="LEGAL",0,$D$10)) | N17: =IF(H17="","",IF(AND($D$14="Sí",(L17+M17)<0),0,L17+M17)) | O17: =IF(H17="","",$D$5*N17*J17/36500) | P17: =IF(H17="","",$D$5+SUM($O$5:O17))
A18: Régimen (automático) | D18: =IF(OR(ISNUMBER(SEARCH("legal",$D$9)),ISNUMBER(SEARCH("demora",$D$9)),ISNUMBER(SEARCH("mora procesal",$D$9)),ISNUMBER(SEARCH("576",$D$9))),"LEGAL","VARIABLE") | G18: =IF(H18="","",ROW()-4) | H18: =IF(OR(I17="",I17>=$D$7),"",I17) | I18: =IF(H18="","",MIN(IF($D$18="LEGAL",DATE(YEAR(H18)+1,1,1),EDATE($D$12,$D$11*(INT((((YEAR(H18)-YEAR($D$12))*12+(MONTH(H18)-MONTH($D$12))-IF(DAY(H18)<DAY($D$12),1,0))/$D$11))+1))),$D$7)) | J18: =IF(H18="","",I18-H18) | K18: =IF(H18="","",IF($D$18="LEGAL",H18,EDATE(H18,-$D$13))) | L18: =IF(H18="","",IFERROR(INDEX('Tipos BdE'!$B$7:$M$336,MATCH(DATE(YEAR(K18),MONTH(K18),1),'Tipos BdE'!$A$7:$A$336,1),MATCH($D$9,'Tipos BdE'!$B$6:$M$6,0)),0)) | M18: =IF(H18="","",IF($D$18="LEGAL",0,$D$10)) | N18: =IF(H18="","",IF(AND($D$14="Sí",(L18+M18)<0),0,L18+M18)) | O18: =IF(H18="","",$D$5*N18*J18/36500) | P18: =IF(H18="","",$D$5+SUM($O$5:O18))
G19: =IF(H19="","",ROW()-4) | H19: =IF(OR(I18="",I18>=$D$7),"",I18) | I19: =IF(H19="","",MIN(IF($D$18="LEGAL",DATE(YEAR(H19)+1,1,1),EDATE($D$12,$D$11*(INT((((YEAR(H19)-YEAR($D$12))*12+(MONTH(H19)-MONTH($D$12))-IF(DAY(H19)<DAY($D$12),1,0))/$D$11))+1))),$D$7)) | J19: =IF(H19="","",I19-H19) | K19: =IF(H19="","",IF($D$18="LEGAL",H19,EDATE(H19,-$D$13))) | L19: =IF(H19="","",IFERROR(INDEX('Tipos BdE'!$B$7:$M$336,MATCH(DATE(YEAR(K19),MONTH(K19),1),'Tipos BdE'!$A$7:$A$336,1),MATCH($D$9,'Tipos BdE'!$B$6:$M$6,0)),0)) | M19: =IF(H19="","",IF($D$18="LEGAL",0,$D$10)) | N19: =IF(H19="","",IF(AND($D$14="Sí",(L19+M19)<0),0,L19+M19)) | O19: =IF(H19="","",$D$5*N19*J19/36500) | P19: =IF(H19="","",$D$5+SUM($O$5:O19))
A20: RESULTADO | G20: =IF(H20="","",ROW()-4) | H20: =IF(OR(I19="",I19>=$D$7),"",I19) | I20: =IF(H20="","",MIN(IF($D$18="LEGAL",DATE(YEAR(H20)+1,1,1),EDATE($D$12,$D$11*(INT((((YEAR(H20)-YEAR($D$12))*12+(MONTH(H20)-MONTH($D$12))-IF(DAY(H20)<DAY($D$12),1,0))/$D$11))+1))),$D$7)) | J20: =IF(H20="","",I20-H20) | K20: =IF(H20="","",IF($D$18="LEGAL",H20,EDATE(H20,-$D$13))) | L20: =IF(H20="","",IFERROR(INDEX('Tipos BdE'!$B$7:$M$336,MATCH(DATE(YEAR(K20),MONTH(K20),1),'Tipos BdE'!$A$7:$A$336,1),MATCH($D$9,'Tipos BdE'!$B$6:$M$6,0)),0)) | M20: =IF(H20="","",IF($D$18="LEGAL",0,$D$10)) | N20: =IF(H20="","",IF(AND($D$14="Sí",(L20+M20)<0),0,L20+M20)) | O20: =IF(H20="","",$D$5*N20*J20/36500) | P20: =IF(H20="","",$D$5+SUM($O$5:O20))
A21: TOTAL INTERÉS ACTUALIZADO (€) | D21: =IF($D$8="FIJO",($D$7-$D$6)*IF($D$15="Y",$D$16,$D$17)*$D$5/365,SUM($O$5:$O$304)) | G21: =IF(H21="","",ROW()-4) | H21: =IF(OR(I20="",I20>=$D$7),"",I20) | I21: =IF(H21="","",MIN(IF($D$18="LEGAL",DATE(YEAR(H21)+1,1,1),EDATE($D$12,$D$11*(INT((((YEAR(H21)-YEAR($D$12))*12+(MONTH(H21)-MONTH($D$12))-IF(DAY(H21)<DAY($D$12),1,0))/$D$11))+1))),$D$7)) | J21: =IF(H21="","",I21-H21) | K21: =IF(H21="","",IF($D$18="LEGAL",H21,EDATE(H21,-$D$13))) | L21: =IF(H21="","",IFERROR(INDEX('Tipos BdE'!$B$7:$M$336,MATCH(DATE(YEAR(K21),MONTH(K21),1),'Tipos BdE'!$A$7:$A$336,1),MATCH($D$9,'Tipos BdE'!$B$6:$M$6,0)),0)) | M21: =IF(H21="","",IF($D$18="LEGAL",0,$D$10)) | N21: =IF(H21="","",IF(AND($D$14="Sí",(L21+M21)<0),0,L21+M21)) | O21: =IF(H21="","",$D$5*N21*J21/36500) | P21: =IF(H21="","",$D$5+SUM($O$5:O21))
G22: =IF(H22="","",ROW()-4) | H22: =IF(OR(I21="",I21>=$D$7),"",I21) | I22: =IF(H22="","",MIN(IF($D$18="LEGAL",DATE(YEAR(H22)+1,1,1),EDATE($D$12,$D$11*(INT((((YEAR(H22)-YEAR($D$12))*12+(MONTH(H22)-MONTH($D$12))-IF(DAY(H22)<DAY($D$12),1,0))/$D$11))+1))),$D$7)) | J22: =IF(H22="","",I22-H22) | K22: =IF(H22="","",IF($D$18="LEGAL",H22,EDATE(H22,-$D$13))) | L22: =IF(H22="","",IFERROR(INDEX('Tipos BdE'!$B$7:$M$336,MATCH(DATE(YEAR(K22),MONTH(K22),1),'Tipos BdE'!$A$7:$A$336,1),MATCH($D$9,'Tipos BdE'!$B$6:$M$6,0)),0)) | M22: =IF(H22="","",IF($D$18="LEGAL",0,$D$10)) | N22: =IF(H22="","",IF(AND($D$14="Sí",(L22+M22)<0),0,L22+M22)) | O22: =IF(H22="","",$D$5*N22*J22/36500) | P22: =IF(H22="","",$D$5+SUM($O$5:O22))
A23: Nº de tramos | D23: =COUNT($J$5:$J$304) | G23: =IF(H23="","",ROW()-4) | H23: =IF(OR(I22="",I22>=$D$7),"",I22) | I23: =IF(H23="","",MIN(IF($D$18="LEGAL",DATE(YEAR(H23)+1,1,1),EDATE($D$12,$D$11*(INT((((YEAR(H23)-YEAR($D$12))*12+(MONTH(H23)-MONTH($D$12))-IF(DAY(H23)<DAY($D$12),1,0))/$D$11))+1))),$D$7)) | J23: =IF(H23="","",I23-H23) | K23: =IF(H23="","",IF($D$18="LEGAL",H23,EDATE(H23,-$D$13))) | L23: =IF(H23="","",IFERROR(INDEX('Tipos BdE'!$B$7:$M$336,MATCH(DATE(YEAR(K23),MONTH(K23),1),'Tipos BdE'!$A$7:$A$336,1),MATCH($D$9,'Tipos BdE'!$B$6:$M$6,0)),0)) | M23: =IF(H23="","",IF($D$18="LEGAL",0,$D$10)) | N23: =IF(H23="","",IF(AND($D$14="Sí",(L23+M23)<0),0,L23+M23)) | O23: =IF(H23="","",$D$5*N23*J23/36500) | P23: =IF(H23="","",$D$5+SUM($O$5:O23))
A24: Tipo medio aplicado (ponderado) | D24: =IFERROR($D$21*36500/($D$5*IF($D$8="FIJO",$D$7-$D$6,SUM($J$5:$J$304))),0) | G24: =IF(H24="","",ROW()-4) | H24: =IF(OR(I23="",I23>=$D$7),"",I23) | I24: =IF(H24="","",MIN(IF($D$18="LEGAL",DATE(YEAR(H24)+1,1,1),EDATE($D$12,$D$11*(INT((((YEAR(H24)-YEAR($D$12))*12+(MONTH(H24)-MONTH($D$12))-IF(DAY(H24)<DAY($D$12),1,0))/$D$11))+1))),$D$7)) | J24: =IF(H24="","",I24-H24) | K24: =IF(H24="","",IF($D$18="LEGAL",H24,EDATE(H24,-$D$13))) | L24: =IF(H24="","",IFERROR(INDEX('Tipos BdE'!$B$7:$M$336,MATCH(DATE(YEAR(K24),MONTH(K24),1),'Tipos BdE'!$A$7:$A$336,1),MATCH($D$9,'Tipos BdE'!$B$6:$M$6,0)),0)) | M24: =IF(H24="","",IF($D$18="LEGAL",0,$D$10)) | N24: =IF(H24="","",IF(AND($D$14="Sí",(L24+M24)<0),0,L24+M24)) | O24: =IF(H24="","",$D$5*N24*J24/36500) | P24: =IF(H24="","",$D$5+SUM($O$5:O24))
G25: =IF(H25="","",ROW()-4) | H25: =IF(OR(I24="",I24>=$D$7),"",I24) | I25: =IF(H25="","",MIN(IF($D$18="LEGAL",DATE(YEAR(H25)+1,1,1),EDATE($D$12,$D$11*(INT((((YEAR(H25)-YEAR($D$12))*12+(MONTH(H25)-MONTH($D$12))-IF(DAY(H25)<DAY($D$12),1,0))/$D$11))+1))),$D$7)) | J25: =IF(H25="","",I25-H25) | K25: =IF(H25="","",IF($D$18="LEGAL",H25,EDATE(H25,-$D$13))) | L25: =IF(H25="","",IFERROR(INDEX('Tipos BdE'!$B$7:$M$336,MATCH(DATE(YEAR(K25),MONTH(K25),1),'Tipos BdE'!$A$7:$A$336,1),MATCH($D$9,'Tipos BdE'!$B$6:$M$6,0)),0)) | M25: =IF(H25="","",IF($D$18="LEGAL",0,$D$10)) | N25: =IF(H25="","",IF(AND($D$14="Sí",(L25+M25)<0),0,L25+M25)) | O25: =IF(H25="","",$D$5*N25*J25/36500) | P25: =IF(H25="","",$D$5+SUM($O$5:O25))
G26: =IF(H26="","",ROW()-4) | H26: =IF(OR(I25="",I25>=$D$7),"",I25) | I26: =IF(H26="","",MIN(IF($D$18="LEGAL",DATE(YEAR(H26)+1,1,1),EDATE($D$12,$D$11*(INT((((YEAR(H26)-YEAR($D$12))*12+(MONTH(H26)-MONTH($D$12))-IF(DAY(H26)<DAY($D$12),1,0))/$D$11))+1))),$D$7)) | J26: =IF(H26="","",I26-H26) | K26: =IF(H26="","",IF($D$18="LEGAL",H26,EDATE(H26,-$D$13))) | L26: =IF(H26="","",IFERROR(INDEX('Tipos BdE'!$B$7:$M$336,MATCH(DATE(YEAR(K26),MONTH(K26),1),'Tipos BdE'!$A$7:$A$336,1),MATCH($D$9,'Tipos BdE'!$B$6:$M$6,0)),0)) | M26: =IF(H26="","",IF($D$18="LEGAL",0,$D$10)) | N26: =IF(H26="","",IF(AND($D$14="Sí",(L26+M26)<0),0,L26+M26)) | O26: =IF(H26="","",$D$5*N26*J26/36500) | P26: =IF(H26="","",$D$5+SUM($O$5:O26))
G27: =IF(H27="","",ROW()-4) | H27: =IF(OR(I26="",I26>=$D$7),"",I26) | I27: =IF(H27="","",MIN(IF($D$18="LEGAL",DATE(YEAR(H27)+1,1,1),EDATE($D$12,$D$11*(INT((((YEAR(H27)-YEAR($D$12))*12+(MONTH(H27)-MONTH($D$12))-IF(DAY(H27)<DAY($D$12),1,0))/$D$11))+1))),$D$7)) | J27: =IF(H27="","",I27-H27) | K27: =IF(H27="","",IF($D$18="LEGAL",H27,EDATE(H27,-$D$13))) | L27: =IF(H27="","",IFERROR(INDEX('Tipos BdE'!$B$7:$M$336,MATCH(DATE(YEAR(K27),MONTH(K27),1),'Tipos BdE'!$A$7:$A$336,1),MATCH($D$9,'Tipos BdE'!$B$6:$M$6,0)),0)) | M27: =IF(H27="","",IF($D$18="LEGAL",0,$D$10)) | N27: =IF(H27="","",IF(AND($D$14="Sí",(L27+M27)<0),0,L27+M27)) | O27: =IF(H27="","",$D$5*N27*J27/36500) | P27: =IF(H27="","",$D$5+SUM($O$5:O27))
G28: =IF(H28="","",ROW()-4) | H28: =IF(OR(I27="",I27>=$D$7),"",I27) | I28: =IF(H28="","",MIN(IF($D$18="LEGAL",DATE(YEAR(H28)+1,1,1),EDATE($D$12,$D$11*(INT((((YEAR(H28)-YEAR($D$12))*12+(MONTH(H28)-MONTH($D$12))-IF(DAY(H28)<DAY($D$12),1,0))/$D$11))+1))),$D$7)) | J28: =IF(H28="","",I28-H28) | K28: =IF(H28="","",IF($D$18="LEGAL",H28,EDATE(H28,-$D$13))) | L28: =IF(H28="","",IFERROR(INDEX('Tipos BdE'!$B$7:$M$336,MATCH(DATE(YEAR(K28),MONTH(K28),1),'Tipos BdE'!$A$7:$A$336,1),MATCH($D$9,'Tipos BdE'!$B$6:$M$6,0)),0)) | M28: =IF(H28="","",IF($D$18="LEGAL",0,$D$10)) | N28: =IF(H28="","",IF(AND($D$14="Sí",(L28+M28)<0),0,L28+M28)) | O28: =IF(H28="","",$D$5*N28*J28/36500) | P28: =IF(H28="","",$D$5+SUM($O$5:O28))
G29: =IF(H29="","",ROW()-4) | H29: =IF(OR(I28="",I28>=$D$7),"",I28) | I29: =IF(H29="","",MIN(IF($D$18="LEGAL",DATE(YEAR(H29)+1,1,1),EDATE($D$12,$D$11*(INT((((YEAR(H29)-YEAR($D$12))*12+(MONTH(H29)-MONTH($D$12))-IF(DAY(H29)<DAY($D$12),1,0))/$D$11))+1))),$D$7)) | J29: =IF(H29="","",I29-H29) | K29: =IF(H29="","",IF($D$18="LEGAL",H29,EDATE(H29,-$D$13))) | L29: =IF(H29="","",IFERROR(INDEX('Tipos BdE'!$B$7:$M$336,MATCH(DATE(YEAR(K29),MONTH(K29),1),'Tipos BdE'!$A$7:$A$336,1),MATCH($D$9,'Tipos BdE'!$B$6:$M$6,0)),0)) | M29: =IF(H29="","",IF($D$18="LEGAL",0,$D$10)) | N29: =IF(H29="","",IF(AND($D$14="Sí",(L29+M29)<0),0,L29+M29)) | O29: =IF(H29="","",$D$5*N29*J29/36500) | P29: =IF(H29="","",$D$5+SUM($O$5:O29))
G30: =IF(H30="","",ROW()-4) | H30: =IF(OR(I29="",I29>=$D$7),"",I29) | I30: =IF(H30="","",MIN(IF($D$18="LEGAL",DATE(YEAR(H30)+1,1,1),EDATE($D$12,$D$11*(INT((((YEAR(H30)-YEAR($D$12))*12+(MONTH(H30)-MONTH($D$12))-IF(DAY(H30)<DAY($D$12),1,0))/$D$11))+1))),$D$7)) | J30: =IF(H30="","",I30-H30) | K30: =IF(H30="","",IF($D$18="LEGAL",H30,EDATE(H30,-$D$13))) | L30: =IF(H30="","",IFERROR(INDEX('Tipos BdE'!$B$7:$M$336,MATCH(DATE(YEAR(K30),MONTH(K30),1),'Tipos BdE'!$A$7:$A$336,1),MATCH($D$9,'Tipos BdE'!$B$6:$M$6,0)),0)) | M30: =IF(H30="","",IF($D$18="LEGAL",0,$D$10)) | N30: =IF(H30="","",IF(AND($D$14="Sí",(L30+M30)<0),0,L30+M30)) | O30: =IF(H30="","",$D$5*N30*J30/36500) | P30: =IF(H30="","",$D$5+SUM($O$5:O30))
G31: =IF(H31="","",ROW()-4) | H31: =IF(OR(I30="",I30>=$D$7),"",I30) | I31: =IF(H31="","",MIN(IF($D$18="LEGAL",DATE(YEAR(H31)+1,1,1),EDATE($D$12,$D$11*(INT((((YEAR(H31)-YEAR($D$12))*12+(MONTH(H31)-MONTH($D$12))-IF(DAY(H31)<DAY($D$12),1,0))/$D$11))+1))),$D$7)) | J31: =IF(H31="","",I31-H31) | K31: =IF(H31="","",IF($D$18="LEGAL",H31,EDATE(H31,-$D$13))) | L31: =IF(H31="","",IFERROR(INDEX('Tipos BdE'!$B$7:$M$336,MATCH(DATE(YEAR(K31),MONTH(K31),1),'Tipos BdE'!$A$7:$A$336,1),MATCH($D$9,'Tipos BdE'!$B$6:$M$6,0)),0)) | M31: =IF(H31="","",IF($D$18="LEGAL",0,$D$10)) | N31: =IF(H31="","",IF(AND($D$14="Sí",(L31+M31)<0),0,L31+M31)) | O31: =IF(H31="","",$D$5*N31*J31/36500) | P31: =IF(H31="","",$D$5+SUM($O$5:O31))
G32: =IF(H32="","",ROW()-4) | H32: =IF(OR(I31="",I31>=$D$7),"",I31) | I32: =IF(H32="","",MIN(IF($D$18="LEGAL",DATE(YEAR(H32)+1,1,1),EDATE($D$12,$D$11*(INT((((YEAR(H32)-YEAR($D$12))*12+(MONTH(H32)-MONTH($D$12))-IF(DAY(H32)<DAY($D$12),1,0))/$D$11))+1))),$D$7)) | J32: =IF(H32="","",I32-H32) | K32: =IF(H32="","",IF($D$18="LEGAL",H32,EDATE(H32,-$D$13))) | L32: =IF(H32="","",IFERROR(INDEX('Tipos BdE'!$B$7:$M$336,MATCH(DATE(YEAR(K32),MONTH(K32),1),'Tipos BdE'!$A$7:$A$336,1),MATCH($D$9,'Tipos BdE'!$B$6:$M$6,0)),0)) | M32: =IF(H32="","",IF($D$18="LEGAL",0,$D$10)) | N32: =IF(H32="","",IF(AND($D$14="Sí",(L32+M32)<0),0,L32+M32)) | O32: =IF(H32="","",$D$5*N32*J32/36500) | P32: =IF(H32="","",$D$5+SUM($O$5:O32))
G33: =IF(H33="","",ROW()-4) | H33: =IF(OR(I32="",I32>=$D$7),"",I32) | I33: =IF(H33="","",MIN(IF($D$18="LEGAL",DATE(YEAR(H33)+1,1,1),EDATE($D$12,$D$11*(INT((((YEAR(H33)-YEAR($D$12))*12+(MONTH(H33)-MONTH($D$12))-IF(DAY(H33)<DAY($D$12),1,0))/$D$11))+1))),$D$7)) | J33: =IF(H33="","",I33-H33) | K33: =IF(H33="","",IF($D$18="LEGAL",H33,EDATE(H33,-$D$13))) | L33: =IF(H33="","",IFERROR(INDEX('Tipos BdE'!$B$7:$M$336,MATCH(DATE(YEAR(K33),MONTH(K33),1),'Tipos BdE'!$A$7:$A$336,1),MATCH($D$9,'Tipos BdE'!$B$6:$M$6,0)),0)) | M33: =IF(H33="","",IF($D$18="LEGAL",0,$D$10)) | N33: =IF(H33="","",IF(AND($D$14="Sí",(L33+M33)<0),0,L33+M33)) | O33: =IF(H33="","",$D$5*N33*J33/36500) | P33: =IF(H33="","",$D$5+SUM($O$5:O33))
G34: =IF(H34="","",ROW()-4) | H34: =IF(OR(I33="",I33>=$D$7),"",I33) | I34: =IF(H34="","",MIN(IF($D$18="LEGAL",DATE(YEAR(H34)+1,1,1),EDATE($D$12,$D$11*(INT((((YEAR(H34)-YEAR($D$12))*12+(MONTH(H34)-MONTH($D$12))-IF(DAY(H34)<DAY($D$12),1,0))/$D$11))+1))),$D$7)) | J34: =IF(H34="","",I34-H34) | K34: =IF(H34="","",IF($D$18="LEGAL",H34,EDATE(H34,-$D$13))) | L34: =IF(H34="","",IFERROR(INDEX('Tipos BdE'!$B$7:$M$336,MATCH(DATE(YEAR(K34),MONTH(K34),1),'Tipos BdE'!$A$7:$A$336,1),MATCH($D$9,'Tipos BdE'!$B$6:$M$6,0)),0)) | M34: =IF(H34="","",IF($D$18="LEGAL",0,$D$10)) | N34: =IF(H34="","",IF(AND($D$14="Sí",(L34+M34)<0),0,L34+M34)) | O34: =IF(H34="","",$D$5*N34*J34/36500) | P34: =IF(H34="","",$D$5+SUM($O$5:O34))
G35: =IF(H35="","",ROW()-4) | H35: =IF(OR(I34="",I34>=$D$7),"",I34) | I35: =IF(H35="","",MIN(IF($D$18="LEGAL",DATE(YEAR(H35)+1,1,1),EDATE($D$12,$D$11*(INT((((YEAR(H35)-YEAR($D$12))*12+(MONTH(H35)-MONTH($D$12))-IF(DAY(H35)<DAY($D$12),1,0))/$D$11))+1))),$D$7)) | J35: =IF(H35="","",I35-H35) | K35: =IF(H35="","",IF($D$18="LEGAL",H35,EDATE(H35,-$D$13))) | L35: =IF(H35="","",IFERROR(INDEX('Tipos BdE'!$B$7:$M$336,MATCH(DATE(YEAR(K35),MONTH(K35),1),'Tipos BdE'!$A$7:$A$336,1),MATCH($D$9,'Tipos BdE'!$B$6:$M$6,0)),0)) | M35: =IF(H35="","",IF($D$18="LEGAL",0,$D$10)) | N35: =IF(H35="","",IF(AND($D$14="Sí",(L35+M35)<0),0,L35+M35)) | O35: =IF(H35="","",$D$5*N35*J35/36500) | P35: =IF(H35="","",$D$5+SUM($O$5:O35))
G36: =IF(H36="","",ROW()-4) | H36: =IF(OR(I35="",I35>=$D$7),"",I35) | I36: =IF(H36="","",MIN(IF($D$18="LEGAL",DATE(YEAR(H36)+1,1,1),EDATE($D$12,$D$11*(INT((((YEAR(H36)-YEAR($D$12))*12+(MONTH(H36)-MONTH($D$12))-IF(DAY(H36)<DAY($D$12),1,0))/$D$11))+1))),$D$7)) | J36: =IF(H36="","",I36-H36) | K36: =IF(H36="","",IF($D$18="LEGAL",H36,EDATE(H36,-$D$13))) | L36: =IF(H36="","",IFERROR(INDEX('Tipos BdE'!$B$7:$M$336,MATCH(DATE(YEAR(K36),MONTH(K36),1),'Tipos BdE'!$A$7:$A$336,1),MATCH($D$9,'Tipos BdE'!$B$6:$M$6,0)),0)) | M36: =IF(H36="","",IF($D$18="LEGAL",0,$D$10)) | N36: =IF(H36="","",IF(AND($D$14="Sí",(L36+M36)<0),0,L36+M36)) | O36: =IF(H36="","",$D$5*N36*J36/36500) | P36: =IF(H36="","",$D$5+SUM($O$5:O36))
... G304: =IF(H304="","",ROW()-4) | H304: =IF(OR(I303="",I303>=$D$7),"",I303) | I304: =IF(H304="","",MIN(IF($D$18="LEGAL",DATE(YEAR(H304)+1,1,1),EDATE($D$12,$D$11*(INT((((YEAR(H304)-YEAR($D$12))*12+(MONTH(H304)-MONTH($D$12))-IF(DAY(H304)<DAY($D$12),1,0))/$D$11))+1))),$D$7)) | J304: =IF(H304="","",I304-H304) | K304: =IF(H304="","",IF($D$18="LEGAL",H304,EDATE(H304,-$D$13))) | L304: =IF(H304="","",IFERROR(INDEX('Tipos BdE'!$B$7:$M$336,MATCH(DATE(YEAR(K304),MONTH(K304),1),'Tipos BdE'!$A$7:$A$336,1),MATCH($D$9,'Tipos BdE'!$B$6:$M$6,0)),0)) | M304: =IF(H304="","",IF($D$18="LEGAL",0,$D$10)) | N304: =IF(H304="","",IF(AND($D$14="Sí",(L304+M304)<0),0,L304+M304)) | O304: =IF(H304="","",$D$5*N304*J304/36500) | P304: =IF(H304="","",$D$5+SUM($O$5:O304))

Sheet CI Variable +3%
A1: CÁLCULO AUTOMÁTICO DE INTERESES (por tramos)
A2: Interés simple, Actual/365 = capital × tipo% × días ÷ 36.500. Datos enlazados desde «Informe Subasta» (no editar aquí).
A4: PARÁMETROS (enlazados) | G4: Nº | H4: Fecha inicio | I4: Fecha fin | J4: Días | K4: Fecha ref. tipo | L4: Tipo base (%) | M4: Diferencial (%) | N4: Tipo aplicado (%) | O4: Intereses (€) | P4: Deuda acumulada (€)
A5: Principal (€) | D5: ='Informe Subasta'!$D$10 | G5: =IF(H5="","",ROW()-4) | H5: =$D$6 | I5: =IF(H5="","",MIN(IF($D$18="LEGAL",DATE(YEAR(H5)+1,1,1),EDATE($D$12,$D$11*(INT((((YEAR(H5)-YEAR($D$12))*12+(MONTH(H5)-MONTH($D$12))-IF(DAY(H5)<DAY($D$12),1,0))/$D$11))+1))),$D$7)) | J5: =IF(H5="","",I5-H5) | K5: =IF(H5="","",IF($D$18="LEGAL",H5,EDATE($D$12,-$D$13))) | L5: =IF(H5="","",IFERROR(INDEX('Tipos BdE'!$B$7:$M$336,MATCH(DATE(YEAR(K5),MONTH(K5),1),'Tipos BdE'!$A$7:$A$336,1),MATCH($D$9,'Tipos BdE'!$B$6:$M$6,0)),0)) | M5: =IF(H5="","",IF($D$18="LEGAL",0,$D$10)) | N5: =IF(H5="","",IF(AND($D$14="Sí",(L5+M5)<0),0,L5+M5)) | O5: =IF(H5="","",$D$5*N5*J5/36500) | P5: =IF(H5="","",$D$5+SUM($O$5:O5))
A6: AccountClosureDate (cierre) | D6: ='Informe Subasta'!$D$15 | G6: =IF(H6="","",ROW()-4) | H6: =IF(OR(I5="",I5>=$D$7),"",I5) | I6: =IF(H6="","",MIN(IF($D$18="LEGAL",DATE(YEAR(H6)+1,1,1),EDATE($D$12,$D$11*(INT((((YEAR(H6)-YEAR($D$12))*12+(MONTH(H6)-MONTH($D$12))-IF(DAY(H6)<DAY($D$12),1,0))/$D$11))+1))),$D$7)) | J6: =IF(H6="","",I6-H6) | K6: =IF(H6="","",IF($D$18="LEGAL",H6,EDATE(H6,-$D$13))) | L6: =IF(H6="","",IFERROR(INDEX('Tipos BdE'!$B$7:$M$336,MATCH(DATE(YEAR(K6),MONTH(K6),1),'Tipos BdE'!$A$7:$A$336,1),MATCH($D$9,'Tipos BdE'!$B$6:$M$6,0)),0)) | M6: =IF(H6="","",IF($D$18="LEGAL",0,$D$10)) | N6: =IF(H6="","",IF(AND($D$14="Sí",(L6+M6)<0),0,L6+M6)) | O6: =IF(H6="","",$D$5*N6*J6/36500) | P6: =IF(H6="","",$D$5+SUM($O$5:O6))
A7: CalculationDate | D7: ='Informe Subasta'!$D$16 | G7: =IF(H7="","",ROW()-4) | H7: =IF(OR(I6="",I6>=$D$7),"",I6) | I7: =IF(H7="","",MIN(IF($D$18="LEGAL",DATE(YEAR(H7)+1,1,1),EDATE($D$12,$D$11*(INT((((YEAR(H7)-YEAR($D$12))*12+(MONTH(H7)-MONTH($D$12))-IF(DAY(H7)<DAY($D$12),1,0))/$D$11))+1))),$D$7)) | J7: =IF(H7="","",I7-H7) | K7: =IF(H7="","",IF($D$18="LEGAL",H7,EDATE(H7,-$D$13))) | L7: =IF(H7="","",IFERROR(INDEX('Tipos BdE'!$B$7:$M$336,MATCH(DATE(YEAR(K7),MONTH(K7),1),'Tipos BdE'!$A$7:$A$336,1),MATCH($D$9,'Tipos BdE'!$B$6:$M$6,0)),0)) | M7: =IF(H7="","",IF($D$18="LEGAL",0,$D$10)) | N7: =IF(H7="","",IF(AND($D$14="Sí",(L7+M7)<0),0,L7+M7)) | O7: =IF(H7="","",$D$5*N7*J7/36500) | P7: =IF(H7="","",$D$5+SUM($O$5:O7))
A8: Mode | D8: ='Informe Subasta'!$D$20 | G8: =IF(H8="","",ROW()-4) | H8: =IF(OR(I7="",I7>=$D$7),"",I7) | I8: =IF(H8="","",MIN(IF($D$18="LEGAL",DATE(YEAR(H8)+1,1,1),EDATE($D$12,$D$11*(INT((((YEAR(H8)-YEAR($D$12))*12+(MONTH(H8)-MONTH($D$12))-IF(DAY(H8)<DAY($D$12),1,0))/$D$11))+1))),$D$7)) | J8: =IF(H8="","",I8-H8) | K8: =IF(H8="","",IF($D$18="LEGAL",H8,EDATE(H8,-$D$13))) | L8: =IF(H8="","",IFERROR(INDEX('Tipos BdE'!$B$7:$M$336,MATCH(DATE(YEAR(K8),MONTH(K8),1),'Tipos BdE'!$A$7:$A$336,1),MATCH($D$9,'Tipos BdE'!$B$6:$M$6,0)),0)) | M8: =IF(H8="","",IF($D$18="LEGAL",0,$D$10)) | N8: =IF(H8="","",IF(AND($D$14="Sí",(L8+M8)<0),0,L8+M8)) | O8: =IF(H8="","",$D$5*N8*J8/36500) | P8: =IF(H8="","",$D$5+SUM($O$5:O8))
A9: ReferenceRate (BdE) | D9: ='Informe Subasta'!$K$20 | G9: =IF(H9="","",ROW()-4) | H9: =IF(OR(I8="",I8>=$D$7),"",I8) | I9: =IF(H9="","",MIN(IF($D$18="LEGAL",DATE(YEAR(H9)+1,1,1),EDATE($D$12,$D$11*(INT((((YEAR(H9)-YEAR($D$12))*12+(MONTH(H9)-MONTH($D$12))-IF(DAY(H9)<DAY($D$12),1,0))/$D$11))+1))),$D$7)) | J9: =IF(H9="","",I9-H9) | K9: =IF(H9="","",IF($D$18="LEGAL",H9,EDATE(H9,-$D$13))) | L9: =IF(H9="","",IFERROR(INDEX('Tipos BdE'!$B$7:$M$336,MATCH(DATE(YEAR(K9),MONTH(K9),1),'Tipos BdE'!$A$7:$A$336,1),MATCH($D$9,'Tipos BdE'!$B$6:$M$6,0)),0)) | M9: =IF(H9="","",IF($D$18="LEGAL",0,$D$10)) | N9: =IF(H9="","",IF(AND($D$14="Sí",(L9+M9)<0),0,L9+M9)) | O9: =IF(H9="","",$D$5*N9*J9/36500) | P9: =IF(H9="","",$D$5+SUM($O$5:O9))
A10: DifferentialRate (puntos) | D10: ='Informe Subasta'!$K$21+3 | G10: =IF(H10="","",ROW()-4) | H10: =IF(OR(I9="",I9>=$D$7),"",I9) | I10: =IF(H10="","",MIN(IF($D$18="LEGAL",DATE(YEAR(H10)+1,1,1),EDATE($D$12,$D$11*(INT((((YEAR(H10)-YEAR($D$12))*12+(MONTH(H10)-MONTH($D$12))-IF(DAY(H10)<DAY($D$12),1,0))/$D$11))+1))),$D$7)) | J10: =IF(H10="","",I10-H10) | K10: =IF(H10="","",IF($D$18="LEGAL",H10,EDATE(H10,-$D$13))) | L10: =IF(H10="","",IFERROR(INDEX('Tipos BdE'!$B$7:$M$336,MATCH(DATE(YEAR(K10),MONTH(K10),1),'Tipos BdE'!$A$7:$A$336,1),MATCH($D$9,'Tipos BdE'!$B$6:$M$6,0)),0)) | M10: =IF(H10="","",IF($D$18="LEGAL",0,$D$10)) | N10: =IF(H10="","",IF(AND($D$14="Sí",(L10+M10)<0),0,L10+M10)) | O10: =IF(H10="","",$D$5*N10*J10/36500) | P10: =IF(H10="","",$D$5+SUM($O$5:O10))
A11: UpdateRateFrequency (meses) | D11: ='Informe Subasta'!$K$22 | G11: =IF(H11="","",ROW()-4) | H11: =IF(OR(I10="",I10>=$D$7),"",I10) | I11: =IF(H11="","",MIN(IF($D$18="LEGAL",DATE(YEAR(H11)+1,1,1),EDATE($D$12,$D$11*(INT((((YEAR(H11)-YEAR($D$12))*12+(MONTH(H11)-MONTH($D$12))-IF(DAY(H11)<DAY($D$12),1,0))/$D$11))+1))),$D$7)) | J11: =IF(H11="","",I11-H11) | K11: =IF(H11="","",IF($D$18="LEGAL",H11,EDATE(H11,-$D$13))) | L11: =IF(H11="","",IFERROR(INDEX('Tipos BdE'!$B$7:$M$336,MATCH(DATE(YEAR(K11),MONTH(K11),1),'Tipos BdE'!$A$7:$A$336,1),MATCH($D$9,'Tipos BdE'!$B$6:$M$6,0)),0)) | M11: =IF(H11="","",IF($D$18="LEGAL",0,$D$10)) | N11: =IF(H11="","",IF(AND($D$14="Sí",(L11+M11)<0),0,L11+M11)) | O11: =IF(H11="","",$D$5*N11*J11/36500) | P11: =IF(H11="","",$D$5+SUM($O$5:O11))
A12: LastRateUpdateDate | D12: ='Informe Subasta'!$K$23 | G12: =IF(H12="","",ROW()-4) | H12: =IF(OR(I11="",I11>=$D$7),"",I11) | I12: =IF(H12="","",MIN(IF($D$18="LEGAL",DATE(YEAR(H12)+1,1,1),EDATE($D$12,$D$11*(INT((((YEAR(H12)-YEAR($D$12))*12+(MONTH(H12)-MONTH($D$12))-IF(DAY(H12)<DAY($D$12),1,0))/$D$11))+1))),$D$7)) | J12: =IF(H12="","",I12-H12) | K12: =IF(H12="","",IF($D$18="LEGAL",H12,EDATE(H12,-$D$13))) | L12: =IF(H12="","",IFERROR(INDEX('Tipos BdE'!$B$7:$M$336,MATCH(DATE(YEAR(K12),MONTH(K12),1),'Tipos BdE'!$A$7:$A$336,1),MATCH($D$9,'Tipos BdE'!$B$6:$M$6,0)),0)) | M12: =IF(H12="","",IF($D$18="LEGAL",0,$D$10)) | N12: =IF(H12="","",IF(AND($D$14="Sí",(L12+M12)<0),0,L12+M12)) | O12: =IF(H12="","",$D$5*N12*J12/36500) | P12: =IF(H12="","",$D$5+SUM($O$5:O12))
A13: RateDelay (meses) | D13: ='Informe Subasta'!$K$24 | G13: =IF(H13="","",ROW()-4) | H13: =IF(OR(I12="",I12>=$D$7),"",I12) | I13: =IF(H13="","",MIN(IF($D$18="LEGAL",DATE(YEAR(H13)+1,1,1),EDATE($D$12,$D$11*(INT((((YEAR(H13)-YEAR($D$12))*12+(MONTH(H13)-MONTH($D$12))-IF(DAY(H13)<DAY($D$12),1,0))/$D$11))+1))),$D$7)) | J13: =IF(H13="","",I13-H13) | K13: =IF(H13="","",IF($D$18="LEGAL",H13,EDATE(H13,-$D$13))) | L13: =IF(H13="","",IFERROR(INDEX('Tipos BdE'!$B$7:$M$336,MATCH(DATE(YEAR(K13),MONTH(K13),1),'Tipos BdE'!$A$7:$A$336,1),MATCH($D$9,'Tipos BdE'!$B$6:$M$6,0)),0)) | M13: =IF(H13="","",IF($D$18="LEGAL",0,$D$10)) | N13: =IF(H13="","",IF(AND($D$14="Sí",(L13+M13)<0),0,L13+M13)) | O13: =IF(H13="","",$D$5*N13*J13/36500) | P13: =IF(H13="","",$D$5+SUM($O$5:O13))
A14: NegativeRatesToZero | D14: ='Informe Subasta'!$D$24 | G14: =IF(H14="","",ROW()-4) | H14: =IF(OR(I13="",I13>=$D$7),"",I13) | I14: =IF(H14="","",MIN(IF($D$18="LEGAL",DATE(YEAR(H14)+1,1,1),EDATE($D$12,$D$11*(INT((((YEAR(H14)-YEAR($D$12))*12+(MONTH(H14)-MONTH($D$12))-IF(DAY(H14)<DAY($D$12),1,0))/$D$11))+1))),$D$7)) | J14: =IF(H14="","",I14-H14) | K14: =IF(H14="","",IF($D$18="LEGAL",H14,EDATE(H14,-$D$13))) | L14: =IF(H14="","",IFERROR(INDEX('Tipos BdE'!$B$7:$M$336,MATCH(DATE(YEAR(K14),MONTH(K14),1),'Tipos BdE'!$A$7:$A$336,1),MATCH($D$9,'Tipos BdE'!$B$6:$M$6,0)),0)) | M14: =IF(H14="","",IF($D$18="LEGAL",0,$D$10)) | N14: =IF(H14="","",IF(AND($D$14="Sí",(L14+M14)<0),0,L14+M14)) | O14: =IF(H14="","",$D$5*N14*J14/36500) | P14: =IF(H14="","",$D$5+SUM($O$5:O14))
A15: IsConsumer | D15: ='Informe Subasta'!$D$21 | G15: =IF(H15="","",ROW()-4) | H15: =IF(OR(I14="",I14>=$D$7),"",I14) | I15: =IF(H15="","",MIN(IF($D$18="LEGAL",DATE(YEAR(H15)+1,1,1),EDATE($D$12,$D$11*(INT((((YEAR(H15)-YEAR($D$12))*12+(MONTH(H15)-MONTH($D$12))-IF(DAY(H15)<DAY($D$12),1,0))/$D$11))+1))),$D$7)) | J15: =IF(H15="","",I15-H15) | K15: =IF(H15="","",IF($D$18="LEGAL",H15,EDATE(H15,-$D$13))) | L15: =IF(H15="","",IFERROR(INDEX('Tipos BdE'!$B$7:$M$336,MATCH(DATE(YEAR(K15),MONTH(K15),1),'Tipos BdE'!$A$7:$A$336,1),MATCH($D$9,'Tipos BdE'!$B$6:$M$6,0)),0)) | M15: =IF(H15="","",IF($D$18="LEGAL",0,$D$10)) | N15: =IF(H15="","",IF(AND($D$14="Sí",(L15+M15)<0),0,L15+M15)) | O15: =IF(H15="","",$D$5*N15*J15/36500) | P15: =IF(H15="","",$D$5+SUM($O$5:O15))
A16: InterestApplicableRate | D16: ='Informe Subasta'!$D$22 | G16: =IF(H16="","",ROW()-4) | H16: =IF(OR(I15="",I15>=$D$7),"",I15) | I16: =IF(H16="","",MIN(IF($D$18="LEGAL",DATE(YEAR(H16)+1,1,1),EDATE($D$12,$D$11*(INT((((YEAR(H16)-YEAR($D$12))*12+(MONTH(H16)-MONTH($D$12))-IF(DAY(H16)<DAY($D$12),1,0))/$D$11))+1))),$D$7)) | J16: =IF(H16="","",I16-H16) | K16: =IF(H16="","",IF($D$18="LEGAL",H16,EDATE(H16,-$D$13))) | L16: =IF(H16="","",IFERROR(INDEX('Tipos BdE'!$B$7:$M$336,MATCH(DATE(YEAR(K16),MONTH(K16),1),'Tipos BdE'!$A$7:$A$336,1),MATCH($D$9,'Tipos BdE'!$B$6:$M$6,0)),0)) | M16: =IF(H16="","",IF($D$18="LEGAL",0,$D$10)) | N16: =IF(H16="","",IF(AND($D$14="Sí",(L16+M16)<0),0,L16+M16)) | O16: =IF(H16="","",$D$5*N16*J16/36500) | P16: =IF(H16="","",$D$5+SUM($O$5:O16))
A17: PenaltyInterestApplicableRate | D17: ='Informe Subasta'!$D$23 | G17: =IF(H17="","",ROW()-4) | H17: =IF(OR(I16="",I16>=$D$7),"",I16) | I17: =IF(H17="","",MIN(IF($D$18="LEGAL",DATE(YEAR(H17)+1,1,1),EDATE($D$12,$D$11*(INT((((YEAR(H17)-YEAR($D$12))*12+(MONTH(H17)-MONTH($D$12))-IF(DAY(H17)<DAY($D$12),1,0))/$D$11))+1))),$D$7)) | J17: =IF(H17="","",I17-H17) | K17: =IF(H17="","",IF($D$18="LEGAL",H17,EDATE(H17,-$D$13))) | L17: =IF(H17="","",IFERROR(INDEX('Tipos BdE'!$B$7:$M$336,MATCH(DATE(YEAR(K17),MONTH(K17),1),'Tipos BdE'!$A$7:$A$336,1),MATCH($D$9,'Tipos BdE'!$B$6:$M$6,0)),0)) | M17: =IF(H17="","",IF($D$18="LEGAL",0,$D$10)) | N17: =IF(H17="","",IF(AND($D$14="Sí",(L17+M17)<0),0,L17+M17)) | O17: =IF(H17="","",$D$5*N17*J17/36500) | P17: =IF(H17="","",$D$5+SUM($O$5:O17))
A18: Régimen (automático) | D18: =IF(OR(ISNUMBER(SEARCH("legal",$D$9)),ISNUMBER(SEARCH("demora",$D$9)),ISNUMBER(SEARCH("mora procesal",$D$9)),ISNUMBER(SEARCH("576",$D$9))),"LEGAL","VARIABLE") | G18: =IF(H18="","",ROW()-4) | H18: =IF(OR(I17="",I17>=$D$7),"",I17) | I18: =IF(H18="","",MIN(IF($D$18="LEGAL",DATE(YEAR(H18)+1,1,1),EDATE($D$12,$D$11*(INT((((YEAR(H18)-YEAR($D$12))*12+(MONTH(H18)-MONTH($D$12))-IF(DAY(H18)<DAY($D$12),1,0))/$D$11))+1))),$D$7)) | J18: =IF(H18="","",I18-H18) | K18: =IF(H18="","",IF($D$18="LEGAL",H18,EDATE(H18,-$D$13))) | L18: =IF(H18="","",IFERROR(INDEX('Tipos BdE'!$B$7:$M$336,MATCH(DATE(YEAR(K18),MONTH(K18),1),'Tipos BdE'!$A$7:$A$336,1),MATCH($D$9,'Tipos BdE'!$B$6:$M$6,0)),0)) | M18: =IF(H18="","",IF($D$18="LEGAL",0,$D$10)) | N18: =IF(H18="","",IF(AND($D$14="Sí",(L18+M18)<0),0,L18+M18)) | O18: =IF(H18="","",$D$5*N18*J18/36500) | P18: =IF(H18="","",$D$5+SUM($O$5:O18))
G19: =IF(H19="","",ROW()-4) | H19: =IF(OR(I18="",I18>=$D$7),"",I18) | I19: =IF(H19="","",MIN(IF($D$18="LEGAL",DATE(YEAR(H19)+1,1,1),EDATE($D$12,$D$11*(INT((((YEAR(H19)-YEAR($D$12))*12+(MONTH(H19)-MONTH($D$12))-IF(DAY(H19)<DAY($D$12),1,0))/$D$11))+1))),$D$7)) | J19: =IF(H19="","",I19-H19) | K19: =IF(H19="","",IF($D$18="LEGAL",H19,EDATE(H19,-$D$13))) | L19: =IF(H19="","",IFERROR(INDEX('Tipos BdE'!$B$7:$M$336,MATCH(DATE(YEAR(K19),MONTH(K19),1),'Tipos BdE'!$A$7:$A$336,1),MATCH($D$9,'Tipos BdE'!$B$6:$M$6,0)),0)) | M19: =IF(H19="","",IF($D$18="LEGAL",0,$D$10)) | N19: =IF(H19="","",IF(AND($D$14="Sí",(L19+M19)<0),0,L19+M19)) | O19: =IF(H19="","",$D$5*N19*J19/36500) | P19: =IF(H19="","",$D$5+SUM($O$5:O19))
A20: RESULTADO | G20: =IF(H20="","",ROW()-4) | H20: =IF(OR(I19="",I19>=$D$7),"",I19) | I20: =IF(H20="","",MIN(IF($D$18="LEGAL",DATE(YEAR(H20)+1,1,1),EDATE($D$12,$D$11*(INT((((YEAR(H20)-YEAR($D$12))*12+(MONTH(H20)-MONTH($D$12))-IF(DAY(H20)<DAY($D$12),1,0))/$D$11))+1))),$D$7)) | J20: =IF(H20="","",I20-H20) | K20: =IF(H20="","",IF($D$18="LEGAL",H20,EDATE(H20,-$D$13))) | L20: =IF(H20="","",IFERROR(INDEX('Tipos BdE'!$B$7:$M$336,MATCH(DATE(YEAR(K20),MONTH(K20),1),'Tipos BdE'!$A$7:$A$336,1),MATCH($D$9,'Tipos BdE'!$B$6:$M$6,0)),0)) | M20: =IF(H20="","",IF($D$18="LEGAL",0,$D$10)) | N20: =IF(H20="","",IF(AND($D$14="Sí",(L20+M20)<0),0,L20+M20)) | O20: =IF(H20="","",$D$5*N20*J20/36500) | P20: =IF(H20="","",$D$5+SUM($O$5:O20))
A21: TOTAL INTERÉS ACTUALIZADO (€) | D21: =IF($D$8="FIJO",($D$7-$D$6)*IF($D$15="Y",$D$16,$D$17)*$D$5/365,SUM($O$5:$O$304)) | G21: =IF(H21="","",ROW()-4) | H21: =IF(OR(I20="",I20>=$D$7),"",I20) | I21: =IF(H21="","",MIN(IF($D$18="LEGAL",DATE(YEAR(H21)+1,1,1),EDATE($D$12,$D$11*(INT((((YEAR(H21)-YEAR($D$12))*12+(MONTH(H21)-MONTH($D$12))-IF(DAY(H21)<DAY($D$12),1,0))/$D$11))+1))),$D$7)) | J21: =IF(H21="","",I21-H21) | K21: =IF(H21="","",IF($D$18="LEGAL",H21,EDATE(H21,-$D$13))) | L21: =IF(H21="","",IFERROR(INDEX('Tipos BdE'!$B$7:$M$336,MATCH(DATE(YEAR(K21),MONTH(K21),1),'Tipos BdE'!$A$7:$A$336,1),MATCH($D$9,'Tipos BdE'!$B$6:$M$6,0)),0)) | M21: =IF(H21="","",IF($D$18="LEGAL",0,$D$10)) | N21: =IF(H21="","",IF(AND($D$14="Sí",(L21+M21)<0),0,L21+M21)) | O21: =IF(H21="","",$D$5*N21*J21/36500) | P21: =IF(H21="","",$D$5+SUM($O$5:O21))
G22: =IF(H22="","",ROW()-4) | H22: =IF(OR(I21="",I21>=$D$7),"",I21) | I22: =IF(H22="","",MIN(IF($D$18="LEGAL",DATE(YEAR(H22)+1,1,1),EDATE($D$12,$D$11*(INT((((YEAR(H22)-YEAR($D$12))*12+(MONTH(H22)-MONTH($D$12))-IF(DAY(H22)<DAY($D$12),1,0))/$D$11))+1))),$D$7)) | J22: =IF(H22="","",I22-H22) | K22: =IF(H22="","",IF($D$18="LEGAL",H22,EDATE(H22,-$D$13))) | L22: =IF(H22="","",IFERROR(INDEX('Tipos BdE'!$B$7:$M$336,MATCH(DATE(YEAR(K22),MONTH(K22),1),'Tipos BdE'!$A$7:$A$336,1),MATCH($D$9,'Tipos BdE'!$B$6:$M$6,0)),0)) | M22: =IF(H22="","",IF($D$18="LEGAL",0,$D$10)) | N22: =IF(H22="","",IF(AND($D$14="Sí",(L22+M22)<0),0,L22+M22)) | O22: =IF(H22="","",$D$5*N22*J22/36500) | P22: =IF(H22="","",$D$5+SUM($O$5:O22))
A23: Nº de tramos | D23: =COUNT($J$5:$J$304) | G23: =IF(H23="","",ROW()-4) | H23: =IF(OR(I22="",I22>=$D$7),"",I22) | I23: =IF(H23="","",MIN(IF($D$18="LEGAL",DATE(YEAR(H23)+1,1,1),EDATE($D$12,$D$11*(INT((((YEAR(H23)-YEAR($D$12))*12+(MONTH(H23)-MONTH($D$12))-IF(DAY(H23)<DAY($D$12),1,0))/$D$11))+1))),$D$7)) | J23: =IF(H23="","",I23-H23) | K23: =IF(H23="","",IF($D$18="LEGAL",H23,EDATE(H23,-$D$13))) | L23: =IF(H23="","",IFERROR(INDEX('Tipos BdE'!$B$7:$M$336,MATCH(DATE(YEAR(K23),MONTH(K23),1),'Tipos BdE'!$A$7:$A$336,1),MATCH($D$9,'Tipos BdE'!$B$6:$M$6,0)),0)) | M23: =IF(H23="","",IF($D$18="LEGAL",0,$D$10)) | N23: =IF(H23="","",IF(AND($D$14="Sí",(L23+M23)<0),0,L23+M23)) | O23: =IF(H23="","",$D$5*N23*J23/36500) | P23: =IF(H23="","",$D$5+SUM($O$5:O23))
A24: Tipo medio aplicado (ponderado) | D24: =IFERROR($D$21*36500/($D$5*IF($D$8="FIJO",$D$7-$D$6,SUM($J$5:$J$304))),0) | G24: =IF(H24="","",ROW()-4) | H24: =IF(OR(I23="",I23>=$D$7),"",I23) | I24: =IF(H24="","",MIN(IF($D$18="LEGAL",DATE(YEAR(H24)+1,1,1),EDATE($D$12,$D$11*(INT((((YEAR(H24)-YEAR($D$12))*12+(MONTH(H24)-MONTH($D$12))-IF(DAY(H24)<DAY($D$12),1,0))/$D$11))+1))),$D$7)) | J24: =IF(H24="","",I24-H24) | K24: =IF(H24="","",IF($D$18="LEGAL",H24,EDATE(H24,-$D$13))) | L24: =IF(H24="","",IFERROR(INDEX('Tipos BdE'!$B$7:$M$336,MATCH(DATE(YEAR(K24),MONTH(K24),1),'Tipos BdE'!$A$7:$A$336,1),MATCH($D$9,'Tipos BdE'!$B$6:$M$6,0)),0)) | M24: =IF(H24="","",IF($D$18="LEGAL",0,$D$10)) | N24: =IF(H24="","",IF(AND($D$14="Sí",(L24+M24)<0),0,L24+M24)) | O24: =IF(H24="","",$D$5*N24*J24/36500) | P24: =IF(H24="","",$D$5+SUM($O$5:O24))
G25: =IF(H25="","",ROW()-4) | H25: =IF(OR(I24="",I24>=$D$7),"",I24) | I25: =IF(H25="","",MIN(IF($D$18="LEGAL",DATE(YEAR(H25)+1,1,1),EDATE($D$12,$D$11*(INT((((YEAR(H25)-YEAR($D$12))*12+(MONTH(H25)-MONTH($D$12))-IF(DAY(H25)<DAY($D$12),1,0))/$D$11))+1))),$D$7)) | J25: =IF(H25="","",I25-H25) | K25: =IF(H25="","",IF($D$18="LEGAL",H25,EDATE(H25,-$D$13))) | L25: =IF(H25="","",IFERROR(INDEX('Tipos BdE'!$B$7:$M$336,MATCH(DATE(YEAR(K25),MONTH(K25),1),'Tipos BdE'!$A$7:$A$336,1),MATCH($D$9,'Tipos BdE'!$B$6:$M$6,0)),0)) | M25: =IF(H25="","",IF($D$18="LEGAL",0,$D$10)) | N25: =IF(H25="","",IF(AND($D$14="Sí",(L25+M25)<0),0,L25+M25)) | O25: =IF(H25="","",$D$5*N25*J25/36500) | P25: =IF(H25="","",$D$5+SUM($O$5:O25))
G26: =IF(H26="","",ROW()-4) | H26: =IF(OR(I25="",I25>=$D$7),"",I25) | I26: =IF(H26="","",MIN(IF($D$18="LEGAL",DATE(YEAR(H26)+1,1,1),EDATE($D$12,$D$11*(INT((((YEAR(H26)-YEAR($D$12))*12+(MONTH(H26)-MONTH($D$12))-IF(DAY(H26)<DAY($D$12),1,0))/$D$11))+1))),$D$7)) | J26: =IF(H26="","",I26-H26) | K26: =IF(H26="","",IF($D$18="LEGAL",H26,EDATE(H26,-$D$13))) | L26: =IF(H26="","",IFERROR(INDEX('Tipos BdE'!$B$7:$M$336,MATCH(DATE(YEAR(K26),MONTH(K26),1),'Tipos BdE'!$A$7:$A$336,1),MATCH($D$9,'Tipos BdE'!$B$6:$M$6,0)),0)) | M26: =IF(H26="","",IF($D$18="LEGAL",0,$D$10)) | N26: =IF(H26="","",IF(AND($D$14="Sí",(L26+M26)<0),0,L26+M26)) | O26: =IF(H26="","",$D$5*N26*J26/36500) | P26: =IF(H26="","",$D$5+SUM($O$5:O26))
G27: =IF(H27="","",ROW()-4) | H27: =IF(OR(I26="",I26>=$D$7),"",I26) | I27: =IF(H27="","",MIN(IF($D$18="LEGAL",DATE(YEAR(H27)+1,1,1),EDATE($D$12,$D$11*(INT((((YEAR(H27)-YEAR($D$12))*12+(MONTH(H27)-MONTH($D$12))-IF(DAY(H27)<DAY($D$12),1,0))/$D$11))+1))),$D$7)) | J27: =IF(H27="","",I27-H27) | K27: =IF(H27="","",IF($D$18="LEGAL",H27,EDATE(H27,-$D$13))) | L27: =IF(H27="","",IFERROR(INDEX('Tipos BdE'!$B$7:$M$336,MATCH(DATE(YEAR(K27),MONTH(K27),1),'Tipos BdE'!$A$7:$A$336,1),MATCH($D$9,'Tipos BdE'!$B$6:$M$6,0)),0)) | M27: =IF(H27="","",IF($D$18="LEGAL",0,$D$10)) | N27: =IF(H27="","",IF(AND($D$14="Sí",(L27+M27)<0),0,L27+M27)) | O27: =IF(H27="","",$D$5*N27*J27/36500) | P27: =IF(H27="","",$D$5+SUM($O$5:O27))
G28: =IF(H28="","",ROW()-4) | H28: =IF(OR(I27="",I27>=$D$7),"",I27) | I28: =IF(H28="","",MIN(IF($D$18="LEGAL",DATE(YEAR(H28)+1,1,1),EDATE($D$12,$D$11*(INT((((YEAR(H28)-YEAR($D$12))*12+(MONTH(H28)-MONTH($D$12))-IF(DAY(H28)<DAY($D$12),1,0))/$D$11))+1))),$D$7)) | J28: =IF(H28="","",I28-H28) | K28: =IF(H28="","",IF($D$18="LEGAL",H28,EDATE(H28,-$D$13))) | L28: =IF(H28="","",IFERROR(INDEX('Tipos BdE'!$B$7:$M$336,MATCH(DATE(YEAR(K28),MONTH(K28),1),'Tipos BdE'!$A$7:$A$336,1),MATCH($D$9,'Tipos BdE'!$B$6:$M$6,0)),0)) | M28: =IF(H28="","",IF($D$18="LEGAL",0,$D$10)) | N28: =IF(H28="","",IF(AND($D$14="Sí",(L28+M28)<0),0,L28+M28)) | O28: =IF(H28="","",$D$5*N28*J28/36500) | P28: =IF(H28="","",$D$5+SUM($O$5:O28))
G29: =IF(H29="","",ROW()-4) | H29: =IF(OR(I28="",I28>=$D$7),"",I28) | I29: =IF(H29="","",MIN(IF($D$18="LEGAL",DATE(YEAR(H29)+1,1,1),EDATE($D$12,$D$11*(INT((((YEAR(H29)-YEAR($D$12))*12+(MONTH(H29)-MONTH($D$12))-IF(DAY(H29)<DAY($D$12),1,0))/$D$11))+1))),$D$7)) | J29: =IF(H29="","",I29-H29) | K29: =IF(H29="","",IF($D$18="LEGAL",H29,EDATE(H29,-$D$13))) | L29: =IF(H29="","",IFERROR(INDEX('Tipos BdE'!$B$7:$M$336,MATCH(DATE(YEAR(K29),MONTH(K29),1),'Tipos BdE'!$A$7:$A$336,1),MATCH($D$9,'Tipos BdE'!$B$6:$M$6,0)),0)) | M29: =IF(H29="","",IF($D$18="LEGAL",0,$D$10)) | N29: =IF(H29="","",IF(AND($D$14="Sí",(L29+M29)<0),0,L29+M29)) | O29: =IF(H29="","",$D$5*N29*J29/36500) | P29: =IF(H29="","",$D$5+SUM($O$5:O29))
G30: =IF(H30="","",ROW()-4) | H30: =IF(OR(I29="",I29>=$D$7),"",I29) | I30: =IF(H30="","",MIN(IF($D$18="LEGAL",DATE(YEAR(H30)+1,1,1),EDATE($D$12,$D$11*(INT((((YEAR(H30)-YEAR($D$12))*12+(MONTH(H30)-MONTH($D$12))-IF(DAY(H30)<DAY($D$12),1,0))/$D$11))+1))),$D$7)) | J30: =IF(H30="","",I30-H30) | K30: =IF(H30="","",IF($D$18="LEGAL",H30,EDATE(H30,-$D$13))) | L30: =IF(H30="","",IFERROR(INDEX('Tipos BdE'!$B$7:$M$336,MATCH(DATE(YEAR(K30),MONTH(K30),1),'Tipos BdE'!$A$7:$A$336,1),MATCH($D$9,'Tipos BdE'!$B$6:$M$6,0)),0)) | M30: =IF(H30="","",IF($D$18="LEGAL",0,$D$10)) | N30: =IF(H30="","",IF(AND($D$14="Sí",(L30+M30)<0),0,L30+M30)) | O30: =IF(H30="","",$D$5*N30*J30/36500) | P30: =IF(H30="","",$D$5+SUM($O$5:O30))
G31: =IF(H31="","",ROW()-4) | H31: =IF(OR(I30="",I30>=$D$7),"",I30) | I31: =IF(H31="","",MIN(IF($D$18="LEGAL",DATE(YEAR(H31)+1,1,1),EDATE($D$12,$D$11*(INT((((YEAR(H31)-YEAR($D$12))*12+(MONTH(H31)-MONTH($D$12))-IF(DAY(H31)<DAY($D$12),1,0))/$D$11))+1))),$D$7)) | J31: =IF(H31="","",I31-H31) | K31: =IF(H31="","",IF($D$18="LEGAL",H31,EDATE(H31,-$D$13))) | L31: =IF(H31="","",IFERROR(INDEX('Tipos BdE'!$B$7:$M$336,MATCH(DATE(YEAR(K31),MONTH(K31),1),'Tipos BdE'!$A$7:$A$336,1),MATCH($D$9,'Tipos BdE'!$B$6:$M$6,0)),0)) | M31: =IF(H31="","",IF($D$18="LEGAL",0,$D$10)) | N31: =IF(H31="","",IF(AND($D$14="Sí",(L31+M31)<0),0,L31+M31)) | O31: =IF(H31="","",$D$5*N31*J31/36500) | P31: =IF(H31="","",$D$5+SUM($O$5:O31))
G32: =IF(H32="","",ROW()-4) | H32: =IF(OR(I31="",I31>=$D$7),"",I31) | I32: =IF(H32="","",MIN(IF($D$18="LEGAL",DATE(YEAR(H32)+1,1,1),EDATE($D$12,$D$11*(INT((((YEAR(H32)-YEAR($D$12))*12+(MONTH(H32)-MONTH($D$12))-IF(DAY(H32)<DAY($D$12),1,0))/$D$11))+1))),$D$7)) | J32: =IF(H32="","",I32-H32) | K32: =IF(H32="","",IF($D$18="LEGAL",H32,EDATE(H32,-$D$13))) | L32: =IF(H32="","",IFERROR(INDEX('Tipos BdE'!$B$7:$M$336,MATCH(DATE(YEAR(K32),MONTH(K32),1),'Tipos BdE'!$A$7:$A$336,1),MATCH($D$9,'Tipos BdE'!$B$6:$M$6,0)),0)) | M32: =IF(H32="","",IF($D$18="LEGAL",0,$D$10)) | N32: =IF(H32="","",IF(AND($D$14="Sí",(L32+M32)<0),0,L32+M32)) | O32: =IF(H32="","",$D$5*N32*J32/36500) | P32: =IF(H32="","",$D$5+SUM($O$5:O32))
G33: =IF(H33="","",ROW()-4) | H33: =IF(OR(I32="",I32>=$D$7),"",I32) | I33: =IF(H33="","",MIN(IF($D$18="LEGAL",DATE(YEAR(H33)+1,1,1),EDATE($D$12,$D$11*(INT((((YEAR(H33)-YEAR($D$12))*12+(MONTH(H33)-MONTH($D$12))-IF(DAY(H33)<DAY($D$12),1,0))/$D$11))+1))),$D$7)) | J33: =IF(H33="","",I33-H33) | K33: =IF(H33="","",IF($D$18="LEGAL",H33,EDATE(H33,-$D$13))) | L33: =IF(H33="","",IFERROR(INDEX('Tipos BdE'!$B$7:$M$336,MATCH(DATE(YEAR(K33),MONTH(K33),1),'Tipos BdE'!$A$7:$A$336,1),MATCH($D$9,'Tipos BdE'!$B$6:$M$6,0)),0)) | M33: =IF(H33="","",IF($D$18="LEGAL",0,$D$10)) | N33: =IF(H33="","",IF(AND($D$14="Sí",(L33+M33)<0),0,L33+M33)) | O33: =IF(H33="","",$D$5*N33*J33/36500) | P33: =IF(H33="","",$D$5+SUM($O$5:O33))
G34: =IF(H34="","",ROW()-4) | H34: =IF(OR(I33="",I33>=$D$7),"",I33) | I34: =IF(H34="","",MIN(IF($D$18="LEGAL",DATE(YEAR(H34)+1,1,1),EDATE($D$12,$D$11*(INT((((YEAR(H34)-YEAR($D$12))*12+(MONTH(H34)-MONTH($D$12))-IF(DAY(H34)<DAY($D$12),1,0))/$D$11))+1))),$D$7)) | J34: =IF(H34="","",I34-H34) | K34: =IF(H34="","",IF($D$18="LEGAL",H34,EDATE(H34,-$D$13))) | L34: =IF(H34="","",IFERROR(INDEX('Tipos BdE'!$B$7:$M$336,MATCH(DATE(YEAR(K34),MONTH(K34),1),'Tipos BdE'!$A$7:$A$336,1),MATCH($D$9,'Tipos BdE'!$B$6:$M$6,0)),0)) | M34: =IF(H34="","",IF($D$18="LEGAL",0,$D$10)) | N34: =IF(H34="","",IF(AND($D$14="Sí",(L34+M34)<0),0,L34+M34)) | O34: =IF(H34="","",$D$5*N34*J34/36500) | P34: =IF(H34="","",$D$5+SUM($O$5:O34))
G35: =IF(H35="","",ROW()-4) | H35: =IF(OR(I34="",I34>=$D$7),"",I34) | I35: =IF(H35="","",MIN(IF($D$18="LEGAL",DATE(YEAR(H35)+1,1,1),EDATE($D$12,$D$11*(INT((((YEAR(H35)-YEAR($D$12))*12+(MONTH(H35)-MONTH($D$12))-IF(DAY(H35)<DAY($D$12),1,0))/$D$11))+1))),$D$7)) | J35: =IF(H35="","",I35-H35) | K35: =IF(H35="","",IF($D$18="LEGAL",H35,EDATE(H35,-$D$13))) | L35: =IF(H35="","",IFERROR(INDEX('Tipos BdE'!$B$7:$M$336,MATCH(DATE(YEAR(K35),MONTH(K35),1),'Tipos BdE'!$A$7:$A$336,1),MATCH($D$9,'Tipos BdE'!$B$6:$M$6,0)),0)) | M35: =IF(H35="","",IF($D$18="LEGAL",0,$D$10)) | N35: =IF(H35="","",IF(AND($D$14="Sí",(L35+M35)<0),0,L35+M35)) | O35: =IF(H35="","",$D$5*N35*J35/36500) | P35: =IF(H35="","",$D$5+SUM($O$5:O35))
G36: =IF(H36="","",ROW()-4) | H36: =IF(OR(I35="",I35>=$D$7),"",I35) | I36: =IF(H36="","",MIN(IF($D$18="LEGAL",DATE(YEAR(H36)+1,1,1),EDATE($D$12,$D$11*(INT((((YEAR(H36)-YEAR($D$12))*12+(MONTH(H36)-MONTH($D$12))-IF(DAY(H36)<DAY($D$12),1,0))/$D$11))+1))),$D$7)) | J36: =IF(H36="","",I36-H36) | K36: =IF(H36="","",IF($D$18="LEGAL",H36,EDATE(H36,-$D$13))) | L36: =IF(H36="","",IFERROR(INDEX('Tipos BdE'!$B$7:$M$336,MATCH(DATE(YEAR(K36),MONTH(K36),1),'Tipos BdE'!$A$7:$A$336,1),MATCH($D$9,'Tipos BdE'!$B$6:$M$6,0)),0)) | M36: =IF(H36="","",IF($D$18="LEGAL",0,$D$10)) | N36: =IF(H36="","",IF(AND($D$14="Sí",(L36+M36)<0),0,L36+M36)) | O36: =IF(H36="","",$D$5*N36*J36/36500) | P36: =IF(H36="","",$D$5+SUM($O$5:O36))
... G304: =IF(H304="","",ROW()-4) | H304: =IF(OR(I303="",I303>=$D$7),"",I303) | I304: =IF(H304="","",MIN(IF($D$18="LEGAL",DATE(YEAR(H304)+1,1,1),EDATE($D$12,$D$11*(INT((((YEAR(H304)-YEAR($D$12))*12+(MONTH(H304)-MONTH($D$12))-IF(DAY(H304)<DAY($D$12),1,0))/$D$11))+1))),$D$7)) | J304: =IF(H304="","",I304-H304) | K304: =IF(H304="","",IF($D$18="LEGAL",H304,EDATE(H304,-$D$13))) | L304: =IF(H304="","",IFERROR(INDEX('Tipos BdE'!$B$7:$M$336,MATCH(DATE(YEAR(K304),MONTH(K304),1),'Tipos BdE'!$A$7:$A$336,1),MATCH($D$9,'Tipos BdE'!$B$6:$M$6,0)),0)) | M304: =IF(H304="","",IF($D$18="LEGAL",0,$D$10)) | N304: =IF(H304="","",IF(AND($D$14="Sí",(L304+M304)<0),0,L304+M304)) | O304: =IF(H304="","",$D$5*N304*J304/36500) | P304: =IF(H304="","",$D$5+SUM($O$5:O304))
